Workbook

Sheet Couv
A24: Les Finances des
A25: communes en 2024
A33: Collection
A34: Statistiques et finances locales (tableaux)
A101: Les tableaux « Les finances des communes en 2024 »
A102: ont été élaborés au Département des études et des statistiques locales (DESL)
A103: de la Direction générale des collectivités locales (DGCL)
A104: par Guillaume LEFORESTIER
A106: janvier 2026
A108: Directrice de la publication : Cécile Raquin

Sheet Index
A2: Les finances des communes en 2024
C3: Mise en ligne : janvier 2026
B6: Département des Etudes et Statistiques Locales - DGCL
B7: https://www.collectivites-locales.gouv.fr/etudes-et-statistiques-locales
B9: ► | C9: T 1.1 | D9: : | E9: Répartition des communes par strate de population en 2024 | G9: 2
B10: ► | C10: T 1.2 | D10: : | E10: Répartition des communes et de leur population par région et strate de population | G10: 3
B11: ► | C11: T 1.3 | D11: : | E11: Répartition des communes appartenant à un groupement à fiscalité propre selon le type de groupement | G11: 6
B12: ► | C12: T 1.4 | D12: : | E12: Répartition des communes selon leur caractère touristique et de montagne par strate de population | G12: 7
B13: ► | C13: T 1.5 | D13: : | E13: Répartition des communes selon leur caractère urbain ou rural par strate de population | G13: 9
B14: ► | C14: T 2.1 | D14: : | E14: Comptes des communes par strate de population en 2024 | G14: 11
B15: ► | C15: T 2.2 | D15: : | E15: Les dépenses et recettes par habitant des communes par strate de population | G15: 14
B16: ► | C16: T 2.3 | D16: : | E16: Evolution 2024/2023 des comptes des communes par strate de population | G16: 16
B17: ► | C17: T 3 | D17: : | E17: Données financières des communes par strate de population selon leurs caractéristiques en 2024 | G17: 18
B18: ► | C18: T 4.1 | D18: : | E18: Données financières des communes touristiques par strate de population (France métropolitaine) | G18: 22
B19: ► | C19: T 4.2 | D19: : | E19: Données financières des communes touristiques du littoral maritime par strate de population (France métropolitaine) | G19: 26
B20: ► | C20: T 4.3 | D20: : | E20: Données financières des communes touristiques «supports de stations de sports d'hiver» par strate de population (France métropolitaine) | G20: 30
... B39: ► | C39: Annexe 3 | D39: : | E39: Définitions des ratios financiers obligatoires | G39: 111
C41: Abréviations : | E41: - M€ : millions d'€
E42: - n.s. : non-significatif
E43: - n.d. : non-disponible
C44: Symbole : | E44: - : néant

Sheet T 1.1
A1: T 1.1 - Répartition du nombre de communes (a) par strate de population communale en 2024
A4: Population totale au 1er janvier 2024 (millésimée 2021).
B6: Outre-Mer (b) | E6: France métropolitaine | H6: France entière (c)
B8: Nombre | C8: Population | D8: Population | E8: Nombre | F8: Population | G8: Population | H8: Nombre | I8: Population | J8: Population
A9: Strates | B9: de | C9: des communes | D9: moyenne | E9: de | F9: des communes | G9: moyenne | H9: de | I9: des communes | J9: moyenne
B10: budgets | C10: en milliers | D10: d'une | E10: budgets | F10: en milliers | G10: d'une | H10: budgets | I10: en milliers | J10: d'une
B11: communaux | C11: d'habitants | D11: commune | E11: communaux | F11: d'habitants | G11: commune | H11: communaux | I11: d'habitants | J11: commune
A12: Moins de 100 habitants | B12: - | C12: - | D12: - | E12: 3285 | F12: 213.108 | G12: =F12*1000/E12 -> 64.873059 | H12: =E12 -> 3285 | I12: =F12 -> 213.108 | J12: =I12*1000/H12 -> 64.873059
A13: De 100 à moins de 200 habitants | B13: - | C13: - | D13: - | E13: 5363 | F13: 790.955 | G13: =F13*1000/E13 -> 147.48368 | H13: =E13 -> 5363 | I13: =F13 -> 790.955 | J13: =I13*1000/H13 -> 147.48368
A14: De 200 à moins de 500 habitants | B14: 3 | C14: 0.821 | D14: =C14*1000/B14 -> 273.66667 | E14: 9463 | F14: 3081.382 | G14: =F14*1000/E14 -> 325.62422 | H14: =B14+E14 -> 9466 | I14: =C14+F14 -> 3082.203 | J14: =I14*1000/H14 -> 325.60775
A15: De 500 à moins de 2 000 habitants | B15: 13 | C15: 17.832 | D15: =C15*1000/B15 -> 1371.6923 | E15: 11240 | F15: 11089.396 | G15: =F15*1000/E15 -> 986.60107 | H15: =B15+E15 -> 11253 | I15: =C15+F15 -> 11107.228 | J15: =I15*1000/H15 -> 987.04594
A16: De 2 000 à moins de 3 500 habitants | B16: 9 | C16: 25.502 | D16: =C16*1000/B16 -> 2833.5556 | E16: 2289 | F16: 5996.337 | G16: =F16*1000/E16 -> 2619.6317 | H16: =B16+E16 -> 2298 | I16: =C16+F16 -> 6021.839 | J16: =I16*1000/H16 -> 2620.4695
A17: De 3 500 à moins de 5 000 habitants | B17: 10 | C17: 42.654 | D17: =C17*1000/B17 -> 4265.4 | E17: 986 | F17: 4104.341 | G17: =F17*1000/E17 -> 4162.6176 | H17: =B17+E17 -> 996 | I17: =C17+F17 -> 4146.995 | J17: =I17*1000/H17 -> 4163.6496
A18: De 5 000 à moins de 10 000 habitants | B18: 35 | C18: 257.774 | D18: =C18*1000/B18 -> 7364.9714 | E18: 1192 | F18: 8271.659 | G18: =F18*1000/E18 -> 6939.3112 | H18: =B18+E18 -> 1227 | I18: =C18+F18 -> 8529.433 | J18: =I18*1000/H18 -> 6951.4531
A19: De 10 000 à moins de 20 000 habitants | B19: 30 | C19: 430.586 | D19: =C19*1000/B19 -> 14352.867 | E19: 523 | F19: 7115.114 | G19: =F19*1000/E19 -> 13604.424 | H19: =B19+E19 -> 553 | I19: =C19+F19 -> 7545.7 | J19: =I19*1000/H19 -> 13645.027
A20: De 20 000 à moins de 50 000 habitants | B20: 18 | C20: 553.179 | D20: =C20*1000/B20 -> 30732.167 | E20: 343 | F20: 10405.522 | G20: =F20*1000/E20 -> 30336.799 | H20: =B20+E20 -> 361 | I20: =C20+F20 -> 10958.701 | J20: =I20*1000/H20 -> 30356.512
A21: De 50 000 à moins de 100 000 habitants | B21: 9 | C21: 595.518 | D21: =C21*1000/B21 -> 66168.667 | E21: 82 | F21: 5539.209 | G21: =F21*1000/E21 -> 67551.329 | H21: =B21+E21 -> 91 | I21: =C21+F21 -> 6134.727 | J21: =I21*1000/H21 -> 67414.582
A22: 100 000 habitants et plus | B22: 2 | C22: 262.836 | D22: =C22*1000/B22 -> 131418 | E22: 40 | F22: 10089.735 | G22: =F22*1000/E22 -> 252243.38 | H22: =B22+E22 -> 42 | I22: =C22+F22 -> 10352.571 | J22: =I22*1000/H22 -> 246489.79
A23: Communes de moins de 10 000 habitants | B23: 70 | C23: 344.583 | D23: =C23*1000/B23 -> 4922.6143 | E23: 33818 | F23: 33547.178 | G23: =F23*1000/E23 -> 991.99178 | H23: =B23+E23 -> 33888 | I23: =C23+F23 -> 33891.761 | J23: =I23*1000/H23 -> 1000.111
A24: Communes de 10 000 habitants et plus (y. c. Paris) | B24: 59 | C24: 1842.119 | D24: =C24*1000/B24 -> 31222.356 | E24: 988 | F24: 33149.58 | G24: =F24*1000/E24 -> 33552.206 | H24: =B24+E24 -> 1047 | I24: =C24+F24 -> 34991.699 | J24: =I24*1000/H24 -> 33420.916
A25: Ensemble des communes (y compris Paris) | B25: 129 | C25: 2186.702 | D25: =C25*1000/B25 -> 16951.178 | E25: 34806 | F25: 66696.758 | G25: =F25*1000/E25 -> 1916.2431 | H25: =B25+E25 -> 34935 | I25: =C25+F25 -> 68883.46 | J25: =I25*1000/H25 -> 1971.7607
A26: (a) Il s'agit, plus précisément, du nombre de budgets principaux de communes présents dans le fichier des comptes de gestion.
A27: (b) Il s'agit des 5 départements d'outre-mer (y compris Mayotte).
A28: (c) Ensemble constitué de la France métropolitaine et des départements d'outre-mer y compris Mayotte.
A29: Lecture : en France métropolitaine, il y a 11 240 communes dans la strate des 500 à 2000 habitants, qui regroupent 11,089 millions d'habitants pour une taille moyenne de 987 habitants.
A30: Source : INSEE, Recensement de la population (population totale en 2024 - année de référence 2021) ; calculs DGCL.

Sheet T 1.2
A1: T 1.2.a - Répartition du nombre de communes (a) par région et strate communale en 2024
N2: Nombre de communes(a)
B4: Moins | C4: De 100 | D4: De 200 | E4: De 500 | F4: De 2 000 | G4: De 3 500 | H4: De 5 000 | I4: De 10 000 | J4: De 20 000 | K4: De 50 000 | L4: 100000 | M4: Nombre de | N4: Nombre de | O4: Nombre total
A5: REGIONS | B5: de 100 | C5: à moins de | D5: à moins de | E5: à moins de | F5: à moins de | G5: à moins de | H5: à moins de | I5: à moins de | J5: à moins de | K5: à moins de | L5: habitants | M5: communes de | N5: communes de | O5: de
B6: habitants | C6: 200 hab. | D6: 500 hab. | E6: 2 000 hab. | F6: 3 500 hab. | G6: 5 000 hab. | H6: 10 000 hab. | I6: 20 000 hab. | J6: 50 000 hab. | K6: 100 000 hab. | L6: et plus | M6: moins de 10 000 hab. | N6: 10 000 hab. et plus | O6: communes
A8: Auvergne-Rhône-Alpes | B8: 256 | C8: 431 | D8: 931 | E8: 1631 | F8: 355 | G8: 137 | H8: 180 | I8: 63 | J8: 33 | K8: 4 | L8: 6 | M8: 3921 | N8: 106 | O8: 4027
A9: Bourgogne-Franche-Comté | B9: 587 | C9: 851 | D9: 1156 | E9: 894 | F9: 102 | G9: 37 | H9: 47 | I9: 11 | J9: 10 | K9: - | L9: 2 | M9: 3674 | N9: 23 | O9: 3697
A10: Bretagne | B10: 2 | C10: 23 | D10: 162 | E10: 580 | F10: 202 | G10: 104 | H10: 90 | I10: 31 | J10: 7 | K10: 3 | L10: 2 | M10: 1163 | N10: 43 | O10: 1206
A11: Centre-Val de Loire | B11: 56 | C11: 193 | D11: 579 | E11: 692 | F11: 112 | G11: 48 | H11: 42 | I11: 22 | J11: 9 | K11: 1 | L11: 2 | M11: 1722 | N11: 34 | O11: 1756
A12: Corse | B12: 119 | C12: 85 | D12: 59 | E12: 63 | F12: 19 | G12: 6 | H12: 6 | I12: 1 | J12: 1 | K12: 1 | L12: - | M12: 357 | N12: 3 | O12: 360
A13: Grand Est | B13: 844 | C13: 1041 | D13: 1394 | E13: 1346 | F13: 228 | G13: 89 | H13: 103 | I13: 50 | J13: 16 | K13: 2 | L13: 5 | M13: 5045 | N13: 73 | O13: 5118
A14: Hauts-de-France | B14: 257 | C14: 610 | D14: 1157 | E14: 1214 | F14: 229 | G14: 97 | H14: 122 | I14: 62 | J14: 31 | K14: 7 | L14: 2 | M14: 3686 | N14: 102 | O14: 3788
A15: Normandie | B15: 129 | C15: 398 | D15: 892 | E15: 936 | F15: 137 | G15: 64 | H15: 52 | I15: 27 | J15: 12 | K15: 1 | L15: 3 | M15: 2608 | N15: 43 | O15: 2651
A16: Nouvelle-Aquitaine | B16: 190 | C16: 650 | D16: 1343 | E16: 1559 | F16: 272 | G16: 95 | H16: 123 | I16: 37 | J16: 27 | K16: 7 | L16: 2 | M16: 4232 | N16: 73 | O16: 4305
A17: Occitanie | B17: 733 | C17: 858 | D17: 1198 | E17: 1117 | F17: 238 | G17: 107 | H17: 128 | I17: 47 | J17: 19 | K17: 4 | L17: 4 | M17: 4379 | N17: 74 | O17: 4453
A18: Pays de la Loire | B18: 11 | C18: 57 | D18: 214 | E18: 525 | F18: 194 | G18: 80 | H18: 96 | I18: 32 | J18: 15 | K18: 5 | L18: 3 | M18: 1177 | N18: 55 | O18: 1232
A19: Provence-Alpes-Côte d'Azur | B19: 87 | C19: 110 | D19: 169 | E19: 246 | F19: 91 | G19: 59 | H19: 90 | I19: 52 | J19: 30 | K19: 8 | L19: 4 | M19: 852 | N19: 94 | O19: 946
A20: Île-de-France | B20: 14 | C20: 56 | D20: 209 | E20: 437 | F20: 110 | G20: 63 | H20: 113 | I20: 88 | J20: 133 | K20: 39 | L20: 5 | M20: 1002 | N20: 265 | O20: 1267
A21: France métropolitaine | B21: =SUM(B8:B20) -> 3285 | C21: =SUM(C8:C20) -> 5363 | D21: =SUM(D8:D20) -> 9463 | E21: =SUM(E8:E20) -> 11240 | F21: =SUM(F8:F20) -> 2289 | G21: =SUM(G8:G20) -> 986 | H21: =SUM(H8:H20) -> 1192 | I21: =SUM(I8:I20) -> 523 | ... O21: =SUM(O8:O20) -> 34806
A22: Outre-Mer (b) | B22: - | C22: - | D22: 3 | E22: 13 | F22: 9 | G22: 10 | H22: 35 | I22: 30 | J22: 18 | K22: 9 | L22: 2 | M22: 70 | N22: 59 | O22: 129
A23: - dont Guadeloupe | B23: - | C23: - | D23: - | E23: 4 | F23: 2 | G23: 3 | H23: 10 | I23: 7 | J23: 5 | K23: 1 | L23: - | M23: 19 | N23: 13 | O23: 32
A24: - dont Martinique | B24: - | C24: - | D24: - | E24: 6 | F24: 3 | G24: 6 | H24: 7 | I24: 9 | J24: 2 | K24: 1 | L24: - | M24: 22 | N24: 12 | O24: 34
A25: - dont Guyane | B25: - | C25: - | D25: 3 | E25: 3 | F25: 4 | G25: 1 | H25: 4 | I25: 2 | J25: 3 | K25: 2 | L25: - | M25: 15 | N25: 7 | O25: 22
A26: - dont Réunion | B26: - | C26: - | D26: - | E26: - | F26: - | G26: - | H26: 7 | I26: 4 | J26: 7 | K26: 4 | L26: 2 | M26: 7 | N26: 17 | O26: 24
A27: - dont Mayotte | B27: - | C27: - | D27: - | E27: - | F27: - | G27: - | H27: 7 | I27: 8 | J27: 1 | K27: 1 | L27: - | M27: 7 | N27: 10 | O27: 17
A28: France entière | B28: =SUM(B21:B22) -> 3285 | C28: =SUM(C21:C22) -> 5363 | D28: =SUM(D21:D22) -> 9466 | E28: =SUM(E21:E22) -> 11253 | F28: =SUM(F21:F22) -> 2298 | G28: =SUM(G21:G22) -> 996 | H28: =SUM(H21:H22) -> 1227 | I28: =SUM(I21:I22) -> 553 | ... O28: =SUM(O21:O22) -> 34935
A29: (a) Il s'agit, plus précisément, du nombre de budgets principaux de communes.
A30: (b) Il s'agit des communes des 5 départements d'outre-mer (y compris Mayotte).
A31: Lecture: il y a 256 budgets principaux de communes de moins de 100 habitants en région Auvergne- Rhône-Alpes
A32: Source : INSEE, Recensement de la population (population totale en 2024 - année de référence 2021) ; calculs DGCL.
A34: T 1.2.b - Répartition de la population des communes par région et strate communale en 2024
A35: Habitants décomptés selon la population totale de l'Insee | N35: En milliers d'habitants
B37: Moins | C37: De 100 | D37: De 200 | E37: De 500 | F37: De 2 000 | G37: De 3 500 | H37: De 5 000 | I37: De 10 000 | J37: De 20 000 | K37: De 50 000 | L37: 100000 | M37: Population des | N37: Population des | O37: Population
A38: REGIONS | B38: de 100 | C38: à moins de | D38: à moins de | E38: à moins de | F38: à moins de | G38: à moins de | H38: à moins de | I38: à moins de | J38: à moins de | K38: à moins de | L38: habitants | M38: communes de | N38: communes de | O38: totale des
B39: habitants | C39: 200 hab. | D39: 500 hab. | E39: 2 000 hab. | F39: 3 500 hab. | G39: 5 000 hab. | H39: 10 000 hab. | I39: 20 000 hab. | J39: 50 000 hab. | K39: 100 000 hab. | L39: et plus | M39: moins de 10 000 hab. | N39: 10 000 hab. et plus | O39: communes
A41: Auvergne-Rhône-Alpes | B41: 15.69 | C41: 63.145 | D41: 308.998 | E41: 1670.478 | F41: 924.668 | G41: 567.247 | H41: 1263.212 | I41: 872 | J41: 1047.359 | K41: 246.057 | L41: 1305.308 | M41: 4813.438 | N41: 3470.724 | O41: 8284.162
A42: Bourgogne-Franche-Comté | B42: 38.977 | C42: 125.814 | D42: 371.666 | E42: 840.068 | F42: 264.729 | G42: 153.354 | H42: 317.793 | I42: 157.511 | J42: 317.361 | K42: - | L42: 285.113 | M42: 2112.401 | N42: 759.985 | O42: 2872.386
A43: Bretagne | B43: 0.156 | C43: 3.647 | D43: 57.018 | E43: 652.679 | F43: 525.358 | G43: 430.936 | H43: 633.519 | I43: 424.519 | J43: 201.741 | K43: 181.558 | L43: 371.412 | M43: 2303.313 | N43: 1179.23 | O43: 3482.543
A44: Centre-Val de Loire | B44: 4.003 | C44: 29.114 | D44: 189.938 | E44: 685.931 | F44: 297.258 | G44: 198.842 | H44: 299.131 | I44: 306.221 | J44: 295.401 | K44: 65.723 | L44: 259.181 | M44: 1704.217 | N44: 926.526 | O44: 2630.743
A45: Corse | B45: 6.596 | C45: 11.675 | D45: 17.94 | E45: 61.545 | F45: 52.338 | G45: 23.549 | H45: 43.526 | I45: 11.382 | J45: 49.376 | K45: 74.632 | L45: - | M45: 217.169 | N45: 135.39 | O45: 352.559
A46: Grand Est | B46: 54.644 | C46: 149.836 | D46: 446.242 | E46: 1276.507 | F46: 590.3 | G46: 370.027 | H46: 682.599 | I46: 676.292 | J46: 473.883 | K46: 132.649 | L46: 812.478 | M46: 3570.155 | N46: 2095.302 | O46: 5665.457
A47: Hauts-de-France | B47: 17.607 | C47: 91.796 | D47: 371.584 | E47: 1153.388 | F47: 597.682 | G47: 413.16 | H47: 841.793 | I47: 800.799 | J47: 893.047 | K47: 530.002 | L47: 374.807 | M47: 3487.01 | N47: 2598.655 | O47: 6085.665
A48: Normandie | B48: 9.312 | C48: 60.778 | D48: 297.151 | E48: 886.169 | F48: 356.999 | G48: 268.604 | H48: 374.694 | I48: 351.76 | J48: 318.781 | K48: 80.02 | L48: 393.834 | M48: 2253.707 | N48: 1144.395 | O48: 3398.102
A49: Nouvelle-Aquitaine | B49: 13.989 | C49: 97.75 | D49: 440.253 | E49: 1501.243 | F49: 710.24 | G49: 396.356 | H49: 841.208 | I49: 494.176 | J49: 803.425 | K49: 510.739 | L49: 397.025 | M49: 4001.039 | N49: 2205.365 | O49: 6206.404
A50: Occitanie | B50: 45.124 | C50: 124.581 | D50: 378.161 | E50: 1090.16 | F50: 629.945 | G50: 445.152 | H50: 898.645 | I50: 603.678 | J50: 589.179 | K50: 253.726 | L50: 1086.417 | M50: 3611.768 | N50: 2533 | O50: 6144.768
A51: Pays de la Loire | B51: 0.729 | C51: 8.647 | D51: 74.748 | E51: 566.16 | F51: 510.238 | G51: 327.382 | H51: 668.542 | I51: 453.609 | J51: 407.767 | K51: 289.898 | L51: 636.38 | M51: 2156.446 | N51: 1787.654 | O51: 3944.1
A52: Provence-Alpes-Côte d'Azur | B52: 5.43 | C52: 15.678 | D52: 56.242 | E52: 261.963 | F52: 243.89 | G52: 245.767 | H52: 612.315 | I52: 706.401 | J52: 967.483 | K52: 523.591 | L52: 1563.134 | M52: 1441.285 | N52: 3760.609 | O52: 5201.894
A53: Île-de-France | B53: 0.851 | C53: 8.494 | D53: 71.441 | E53: 443.105 | F53: 292.692 | G53: 263.965 | H53: 794.682 | I53: 1256.766 | J53: 4040.719 | K53: 2650.614 | L53: 2604.646 | M53: 1875.23 | N53: 10552.745 | O53: 12427.975
A54: France métropolitaine | B54: =SUM(B41:B53) -> 213.108 | C54: =SUM(C41:C53) -> 790.955 | D54: =SUM(D41:D53) -> 3081.382 | E54: =SUM(E41:E53) -> 11089.396 | F54: =SUM(F41:F53) -> 5996.337 | G54: =SUM(G41:G53) -> 4104.341 | H54: =SUM(H41:H53) -> 8271.659 | I54: =SUM(I41:I53) -> 7115.114 | ... O54: =SUM(O41:O53) -> 66696.758
A55: Outre-Mer (a) | B55: - | C55: - | D55: 0.821 | E55: 17.832 | F55: 25.502 | G55: 42.654 | H55: 257.774 | I55: 430.586 | J55: 553.179 | K55: 595.518 | L55: 262.836 | M55: 344.583 | N55: 1842.119 | O55: 2186.702
A56: - dont Guadeloupe | B56: - | C56: - | D56: - | E56: 5.717 | F56: 5.787 | G56: 12.896 | H56: 72.172 | I56: 109.285 | J56: 130.834 | K56: 52.586 | L56: - | M56: 96.572 | N56: 292.705 | O56: 389.277
A57: - dont Martinique | B57: - | C57: - | D57: - | E57: 7.157 | F57: 7.907 | G57: 25.192 | H57: 56.268 | I57: 131.231 | J57: 61.534 | K57: 75.627 | L57: - | M57: 96.524 | N57: 268.392 | O57: 364.916
A58: - dont Guyane | B58: - | C58: - | D58: 0.821 | E58: 4.958 | F58: 11.808 | G58: 4.566 | H58: 33.904 | I58: 30.906 | J58: 87.446 | K58: 114.33 | L58: - | M58: 56.057 | N58: 232.682 | O58: 288.739
A59: - dont Réunion | B59: - | C59: - | D59: - | E59: - | F59: - | G59: - | H59: 45.403 | I59: 52.022 | J59: 240.613 | K59: 280.001 | L59: 262.836 | M59: 45.403 | N59: 835.472 | O59: 880.875
A60: - dont Mayotte | B60: - | C60: - | D60: - | E60: - | F60: - | G60: - | H60: 50.027 | I60: 107.142 | J60: 32.752 | K60: 72.974 | L60: - | M60: 50.027 | N60: 212.868 | O60: 262.895
A61: France entière | B61: =SUM(B54:B55) -> 213.108 | C61: =SUM(C54:C55) -> 790.955 | D61: =SUM(D54:D55) -> 3082.203 | E61: =SUM(E54:E55) -> 11107.228 | F61: =SUM(F54:F55) -> 6021.839 | G61: =SUM(G54:G55) -> 4146.995 | H61: =SUM(H54:H55) -> 8529.433 | I61: =SUM(I54:I55) -> 7545.7 | ... O61: =SUM(O54:O55) -> 68883.46
A62: (a) Il s'agit des communes des 5 départements d'outre-mer (y compris Mayotte).
A63: Lecture : les communes de moins de 100 habitants de la région Auvergne-Rhône-Alpes regroupent 16 000 habitants (exactement : 15 690 habitants).
A64: Source : INSEE, Recensement de la population (population totale en 2024 - année de référence 2021) ; calculs DGCL.
A66: T 1.2.c - Taille moyenne des communes par région et strate communale en 2024
A67: Habitants comptés selon la population totale de l'Insee | N67: Nombre d'habitants par commune
B69: Moins | C69: De 100 | D69: De 200 | E69: De 500 | F69: De 2 000 | G69: De 3 500 | H69: De 5 000 | I69: De 10 000 | J69: De 20 000 | K69: De 50 000 | L69: 100000 | M69: Taille moyenne des | N69: Taille moyenne des | O69: Taille
A70: REGIONS | B70: de 100 | C70: à moins de | D70: à moins de | E70: à moins de | F70: à moins de | G70: à moins de | H70: à moins de | I70: à moins de | J70: à moins de | K70: à moins de | L70: habitants | M70: communes de | N70: communes de | O70: moyenne des
B71: habitants | C71: 200 hab. | D71: 500 hab. | E71: 2 000 hab. | F71: 3 500 hab. | G71: 5 000 hab. | H71: 10 000 hab. | I71: 20 000 hab. | J71: 50 000 hab. | K71: 100 000 hab. | L71: et plus | M71: moins de 10 000 hab. | N71: 10 000 hab. et plus | O71: communes
A73: Auvergne-Rhône-Alpes | B73: =B41*1000/B8 -> 61.289062 | C73: =C41*1000/C8 -> 146.50812 | D73: =D41*1000/D8 -> 331.89903 | E73: =E41*1000/E8 -> 1024.2048 | F73: =F41*1000/F8 -> 2604.6986 | G73: =G41*1000/G8 -> 4140.4891 | H73: =H41*1000/H8 -> 7017.8444 | I73: =I41*1000/I8 -> 13841.27 | ... O73: =O41*1000/O8 -> 2057.1547
A74: Bourgogne-Franche-Comté | B74: =B42*1000/B9 -> 66.400341 | C74: =C42*1000/C9 -> 147.84254 | D74: =D42*1000/D9 -> 321.51038 | E74: =E42*1000/E9 -> 939.67338 | F74: =F42*1000/F9 -> 2595.3824 | G74: =G42*1000/G9 -> 4144.7027 | H74: =H42*1000/H9 -> 6761.5532 | I74: =I42*1000/I9 -> 14319.182 | J74: =J42*1000/J9 -> 31736.1 | K74: - | L74: =L42*1000/L9 -> 142556.5 | M74: =M42*1000/M9 -> 574.95944 | N74: =N42*1000/N9 -> 33042.826 | O74: =O42*1000/O9 -> 776.9505
A75: Bretagne | B75: =B43*1000/B10 -> 78 | C75: =C43*1000/C10 -> 158.56522 | D75: =D43*1000/D10 -> 351.96296 | E75: =E43*1000/E10 -> 1125.3086 | F75: =F43*1000/F10 -> 2600.7822 | G75: =G43*1000/G10 -> 4143.6154 | H75: =H43*1000/H10 -> 7039.1 | I75: =I43*1000/I10 -> 13694.161 | ... O75: =O43*1000/O10 -> 2887.6808
A76: Centre-Val de Loire | B76: =B44*1000/B11 -> 71.482143 | C76: =C44*1000/C11 -> 150.84974 | D76: =D44*1000/D11 -> 328.04491 | E76: =E44*1000/E11 -> 991.22977 | F76: =F44*1000/F11 -> 2654.0893 | G76: =G44*1000/G11 -> 4142.5417 | H76: =H44*1000/H11 -> 7122.1667 | I76: =I44*1000/I11 -> 13919.136 | ... O76: =O44*1000/O11 -> 1498.1452
A77: Corse | B77: =B45*1000/B12 -> 55.428571 | C77: =C45*1000/C12 -> 137.35294 | D77: =D45*1000/D12 -> 304.0678 | E77: =E45*1000/E12 -> 976.90476 | F77: =F45*1000/F12 -> 2754.6316 | G77: =G45*1000/G12 -> 3924.8333 | H77: =H45*1000/H12 -> 7254.3333 | I77: =I45*1000/I12 -> 11382 | ... K77: =K45*1000/K12 -> 74632 | L77: - | M77: =M45*1000/M12 -> 608.31653 | N77: =N45*1000/N12 -> 45130 | O77: =O45*1000/O12 -> 979.33056
A78: Grand Est | B78: =B46*1000/B13 -> 64.744076 | C78: =C46*1000/C13 -> 143.93468 | D78: =D46*1000/D13 -> 320.11621 | E78: =E46*1000/E13 -> 948.37073 | F78: =F46*1000/F13 -> 2589.0351 | G78: =G46*1000/G13 -> 4157.6067 | H78: =H46*1000/H13 -> 6627.1748 | I78: =I46*1000/I13 -> 13525.84 | ... O78: =O46*1000/O13 -> 1106.967
A79: Hauts-de-France | B79: =B47*1000/B14 -> 68.509728 | C79: =C47*1000/C14 -> 150.48525 | D79: =D47*1000/D14 -> 321.16162 | E79: =E47*1000/E14 -> 950.07249 | F79: =F47*1000/F14 -> 2609.9651 | G79: =G47*1000/G14 -> 4259.3814 | H79: =H47*1000/H14 -> 6899.9426 | I79: =I47*1000/I14 -> 12916.113 | ... O79: =O47*1000/O14 -> 1606.5641
A80: Normandie | B80: =B48*1000/B15 -> 72.186047 | C80: =C48*1000/C15 -> 152.70854 | D80: =D48*1000/D15 -> 333.12892 | E80: =E48*1000/E15 -> 946.76175 | F80: =F48*1000/F15 -> 2605.8321 | G80: =G48*1000/G15 -> 4196.9375 | H80: =H48*1000/H15 -> 7205.6538 | I80: =I48*1000/I15 -> 13028.148 | ... O80: =O48*1000/O15 -> 1281.8189
A81: Nouvelle-Aquitaine | B81: =B49*1000/B16 -> 73.626316 | C81: =C49*1000/C16 -> 150.38462 | D81: =D49*1000/D16 -> 327.8131 | E81: =E49*1000/E16 -> 962.95253 | F81: =F49*1000/F16 -> 2611.1765 | G81: =G49*1000/G16 -> 4172.1684 | H81: =H49*1000/H16 -> 6839.0894 | I81: =I49*1000/I16 -> 13356.108 | ... O81: =O49*1000/O16 -> 1441.6734
A82: Occitanie | B82: =B50*1000/B17 -> 61.560709 | C82: =C50*1000/C17 -> 145.1993 | D82: =D50*1000/D17 -> 315.66027 | E82: =E50*1000/E17 -> 975.97135 | F82: =F50*1000/F17 -> 2646.8277 | G82: =G50*1000/G17 -> 4160.2991 | H82: =H50*1000/H17 -> 7020.6641 | I82: =I50*1000/I17 -> 12844.213 | ... O82: =O50*1000/O17 -> 1379.9165
A83: Pays de la Loire | B83: =B51*1000/B18 -> 66.272727 | C83: =C51*1000/C18 -> 151.70175 | D83: =D51*1000/D18 -> 349.28972 | E83: =E51*1000/E18 -> 1078.4 | F83: =F51*1000/F18 -> 2630.0928 | G83: =G51*1000/G18 -> 4092.275 | H83: =H51*1000/H18 -> 6963.9792 | I83: =I51*1000/I18 -> 14175.281 | ... O83: =O51*1000/O18 -> 3201.3799
A84: Provence-Alpes-Côte d'Azur | B84: =B52*1000/B19 -> 62.413793 | C84: =C52*1000/C19 -> 142.52727 | D84: =D52*1000/D19 -> 332.7929 | E84: =E52*1000/E19 -> 1064.8902 | F84: =F52*1000/F19 -> 2680.1099 | G84: =G52*1000/G19 -> 4165.5424 | H84: =H52*1000/H19 -> 6803.5 | I84: =I52*1000/I19 -> 13584.635 | ... O84: =O52*1000/O19 -> 5498.8309
A85: Île-de-France | B85: =B53*1000/B20 -> 60.785714 | C85: =C53*1000/C20 -> 151.67857 | D85: =D53*1000/D20 -> 341.82297 | E85: =E53*1000/E20 -> 1013.9703 | F85: =F53*1000/F20 -> 2660.8364 | G85: =G53*1000/G20 -> 4189.9206 | H85: =H53*1000/H20 -> 7032.5841 | I85: =I53*1000/I20 -> 14281.432 | ... O85: =O53*1000/O20 -> 9808.9779
A86: France métropolitaine | B86: =B54*1000/B21 -> 64.873059 | C86: =C54*1000/C21 -> 147.48368 | D86: =D54*1000/D21 -> 325.62422 | E86: =E54*1000/E21 -> 986.60107 | F86: =F54*1000/F21 -> 2619.6317 | G86: =G54*1000/G21 -> 4162.6176 | H86: =H54*1000/H21 -> 6939.3112 | I86: =I54*1000/I21 -> 13604.424 | ... O86: =O54*1000/O21 -> 1916.2431
A87: Outre-Mer (a) | B87: - | C87: - | D87: =D55*1000/D22 -> 273.66667 | E87: =E55*1000/E22 -> 1371.6923 | F87: =F55*1000/F22 -> 2833.5556 | G87: =G55*1000/G22 -> 4265.4 | H87: =H55*1000/H22 -> 7364.9714 | I87: =I55*1000/I22 -> 14352.867 | J87: =J55*1000/J22 -> 30732.167 | K87: =K55*1000/K22 -> 66168.667 | ... O87: =O55*1000/O22 -> 16951.178
A88: - dont Guadeloupe | B88: - | C88: - | D88: - | E88: =E56*1000/E23 -> 1429.25 | F88: =F56*1000/F23 -> 2893.5 | G88: =G56*1000/G23 -> 4298.6667 | H88: =H56*1000/H23 -> 7217.2 | I88: =I56*1000/I23 -> 15612.143 | J88: =J56*1000/J23 -> 26166.8 | K88: =K56*1000/K23 -> 52586 | L88: - | M88: =M56*1000/M23 -> 5082.7368 | N88: =N56*1000/N23 -> 22515.769 | O88: =O56*1000/O23 -> 12164.906
A89: - dont Martinique | B89: - | C89: - | D89: - | E89: =E57*1000/E24 -> 1192.8333 | F89: =F57*1000/F24 -> 2635.6667 | G89: =G57*1000/G24 -> 4198.6667 | H89: =H57*1000/H24 -> 8038.2857 | I89: =I57*1000/I24 -> 14581.222 | J89: =J57*1000/J24 -> 30767 | K89: =K57*1000/K24 -> 75627 | L89: - | M89: =M57*1000/M24 -> 4387.4545 | N89: =N57*1000/N24 -> 22366 | O89: =O57*1000/O24 -> 10732.824
A90: - dont Guyane | B90: - | C90: - | D90: =D58*1000/D25 -> 273.66667 | E90: =E58*1000/E25 -> 1652.6667 | F90: =F58*1000/F25 -> 2952 | G90: =G58*1000/G25 -> 4566 | H90: =H58*1000/H25 -> 8476 | I90: =I58*1000/I25 -> 15453 | J90: =J58*1000/J25 -> 29148.667 | K90: =K58*1000/K25 -> 57165 | L90: - | M90: =M58*1000/M25 -> 3737.1333 | N90: =N58*1000/N25 -> 33240.286 | O90: =O58*1000/O25 -> 13124.5
A91: - dont Réunion | B91: - | C91: - | D91: - | E91: - | F91: - | G91: - | H91: =H59*1000/H26 -> 6486.1429 | I91: =I59*1000/I26 -> 13005.5 | J91: =J59*1000/J26 -> 34373.286 | K91: =K59*1000/K26 -> 70000.25 | L91: =L59*1000/L26 -> 131418 | M91: =M59*1000/M26 -> 6486.1429 | N91: =N59*1000/N26 -> 49145.412 | O91: =O59*1000/O26 -> 36703.125
A92: - dont Mayotte | B92: - | C92: - | D92: - | E92: - | F92: - | G92: - | H92: =H60*1000/H27 -> 7146.7143 | I92: =I60*1000/I27 -> 13392.75 | J92: =J60*1000/J27 -> 32752 | K92: =K60*1000/K27 -> 72974 | L92: - | M92: =M60*1000/M27 -> 7146.7143 | N92: =N60*1000/N27 -> 21286.8 | O92: =O60*1000/O27 -> 15464.412
A93: France entière | B93: =B61*1000/B28 -> 64.873059 | C93: =C61*1000/C28 -> 147.48368 | D93: =D61*1000/D28 -> 325.60775 | E93: =E61*1000/E28 -> 987.04594 | F93: =F61*1000/F28 -> 2620.4695 | G93: =G61*1000/G28 -> 4163.6496 | H93: =H61*1000/H28 -> 6951.4531 | I93: =I61*1000/I28 -> 13645.027 | ... O93: =O61*1000/O28 -> 1971.7607
A94: (a) Il s'agit des communes des 5 départements d'outre-mer (y compris Mayotte).
A95: Lecture : la taille moyenne d'une commune de moins de 100 habitants en région Auvergne-Rhône-Alpes est de 61 habitants.
A96: Source : DGFIP, comptes de gestion ; INSEE, Recensement de la population (population totale en 2024 - année de référence 2021) ; calculs DGCL.

Sheet T 1.3
A1: T 1.3.a - Répartition des communes (a) appartenant à un groupement à fiscalité propre selon le type de groupement (b) en 2024
B4: Moins | C4: De 100 | D4: De 200 | E4: De 500 | F4: De 2 000 | G4: De 3 500 | H4: De 5 000 | I4: De 10 000 | J4: De 20 000 | K4: De 50 000 | L4: 100000 | M4: Budgets des | N4: Budgets des | O4: Ensemble
A5: Strate des communes | B5: de 100 | C5: à moins de | D5: à moins de | E5: à moins de | F5: à moins de | G5: à moins de | H5: à moins de | I5: à moins de | J5: à moins de | K5: à moins de | L5: habitants | M5: communes de moins | N5: communes de | O5: des
B6: habitants | C6: 200 hab. | D6: 500 hab. | E6: 2 000 hab. | F6: 3 500 hab. | G6: 5 000 hab. | H6: 10 000 hab. | I6: 20 000 hab. | J6: 50 000 hab. | K6: 100 000 hab. | L6: et plus | M6: de 10 000 hab. | N6: 10 000 hab. et plus | O6: budgets
A8: Nombre de communes appartenant à :
A9: CU ou métropoles(c) | B9: 11 | C9: 50 | D9: 139 | E9: 448 | F9: 198 | G9: 125 | H9: 266 | I9: 158 | J9: 155 | K9: 43 | L9: 36 | M9: 1237 | N9: 392 | O9: 1629
A10: CA | B10: 225 | C10: 546 | D10: 1595 | E10: 3066 | F10: 820 | G10: 366 | H10: 468 | I10: 250 | J10: 197 | K10: 47 | L10: 6 | M10: 7086 | N10: 500 | O10: 7586
A11: CC à FPU | B11: 2215 | C11: 3670 | D11: 6340 | E11: 6782 | F11: 1168 | G11: 457 | H11: 452 | I11: 137 | J11: 9 | K11: 1 | L11: - | M11: 21084 | N11: 147 | O11: 21231
A12: CC à FA | B12: 834 | C12: 1097 | D12: 1390 | E12: 956 | F12: 112 | G12: 48 | H12: 40 | I12: 8 | J12: - | K12: - | L12: - | M12: 4477 | N12: 8 | O12: 4485
A13: non membre d'un groupement fiscalisé | B13: - | C13: - | D13: 2 | E13: 1 | F13: - | G13: - | H13: 1 | I13: - | J13: - | K13: - | L13: - | M13: 4 | N13: - | O13: 4
A14: Total | B14: =SUM(B9:B13) -> 3285 | C14: =SUM(C9:C13) -> 5363 | D14: =SUM(D9:D13) -> 9466 | E14: =SUM(E9:E13) -> 11253 | F14: =SUM(F9:F13) -> 2298 | G14: =SUM(G9:G13) -> 996 | H14: =SUM(H9:H13) -> 1227 | I14: =SUM(I9:I13) -> 553 | ... O14: =SUM(O9:O13) -> 34935
A15: Pourcentage de communes appartenant à :
A16: CU ou métropoles(c) | B16: =B9/B$14 -> 0.003348554 | C16: =C9/C$14 -> 0.00932314 | D16: =D9/D$14 -> 0.014684133 | E16: =E9/E$14 -> 0.039811606 | F16: =F9/F$14 -> 0.08616188 | G16: =G9/G$14 -> 0.12550201 | H16: =H9/H$14 -> 0.21678892 | I16: =I9/I$14 -> 0.28571429 | ... O16: =O9/O$14 -> 0.046629455
A17: CA | B17: =B10/B$14 -> 0.068493151 | C17: =C10/C$14 -> 0.10180869 | D17: =D10/D$14 -> 0.16849778 | E17: =E10/E$14 -> 0.27246068 | F17: =F10/F$14 -> 0.35683203 | G17: =G10/G$14 -> 0.36746988 | H17: =H10/H$14 -> 0.38141809 | I17: =I10/I$14 -> 0.45207957 | ... O17: =O10/O$14 -> 0.21714613
A18: CC à FPU | B18: =B11/B$14 -> 0.67427702 | C18: =C11/C$14 -> 0.68431848 | D18: =D11/D$14 -> 0.66976548 | E18: =E11/E$14 -> 0.60268373 | F18: =F11/F$14 -> 0.50826806 | G18: =G11/G$14 -> 0.45883534 | H18: =H11/H$14 -> 0.36837816 | I18: =I11/I$14 -> 0.2477396 | ... K18: =K11/K$14 -> 0.010989011 | L18: - | M18: =M11/M$14 -> 0.62216714 | N18: =N11/N$14 -> 0.14040115 | O18: =O11/O$14 -> 0.60772864
A19: CC à FA | B19: =B12/B$14 -> 0.25388128 | C19: =C12/C$14 -> 0.20454969 | D19: =D12/D$14 -> 0.14684133 | E19: =E12/E$14 -> 0.084955123 | F19: =F12/F$14 -> 0.048738033 | G19: =G12/G$14 -> 0.048192771 | H19: =H12/H$14 -> 0.032599837 | I19: =I12/I$14 -> 0.014466546 | J19: - | K19: - | L19: - | M19: =M12/M$14 -> 0.13211166 | N19: =N12/N$14 -> 0.0076408787 | O19: =O12/O$14 -> 0.12838128
A20: non membre d'un groupement fiscalisé | B20: - | C20: - | D20: =D13/D$14 -> 0.00021128248 | E20: =E13/E$14 -> 8.8865192e-05 | F20: - | G20: - | H20: =H13/H$14 -> 0.00081499593 | I20: - | J20: - | K20: - | L20: - | M20: =M13/M$14 -> 0.00011803588 | N20: - | O20: =O13/O$14 -> 0.00011449835
A21: Total | B21: =B14/B$14 -> 1 | C21: =C14/C$14 -> 1 | D21: =D14/D$14 -> 1 | E21: =E14/E$14 -> 1 | F21: =F14/F$14 -> 1 | G21: =G14/G$14 -> 1 | H21: =H14/H$14 -> 1 | I21: =I14/I$14 -> 1 | ... O21: =O14/O$14 -> 1
A22: (a) Il s'agit, plus précisément, du nombre de budgets principaux de communes.
A23: (b) Il y a 1255 groupements à fiscalité propre au 01/01/2024 (y. c. la métropole de Lyon).
A24: (c) Y compris la métropole de Lyon.
A25: FA: Fiscalité Additionnelle ; FPU: Fiscalité Professionnelle Unique ;
A26: CU: Communauté Urbaine ; CA: Communauté d'Agglomération ;
A27: CC: Communauté de Communes.
A28: Lecture : il y a 11 communes de moins de 100 habitants appartenant à une CU ou à une métropole et ces communes représentent 0,3 % des communes de cette strate.
A29: Source : DGFIP, comptes de gestion, budgets principaux ; INSEE, Recensement de la population (population totale en 2024 - année de référence 2021) ; calculs DGCL.
A31: T 1.3.b - Répartition de la population des communes appartenant à un groupement à fiscalité propre selon le type de groupement en 2024
A32: Habitants comptés selon la population totale de l'Insee
B34: Moins | C34: De 100 | D34: De 200 | E34: De 500 | F34: De 2 000 | G34: De 3 500 | H34: De 5 000 | I34: De 10 000 | J34: De 20 000 | K34: De 50 000 | L34: 100000 | M34: Communes | N34: Communes | O34: Ensemble
A35: Strate des communes | B35: de 100 | C35: à moins de | D35: à moins de | E35: à moins de | F35: à moins de | G35: à moins de | H35: à moins de | I35: à moins de | J35: à moins de | K35: à moins de | L35: habitants | M35: de moins | N35: de 10 000 hab. | O35: des
B36: habitants | C36: 200 hab. | D36: 500 hab. | E36: 2 000 hab. | F36: 3 500 hab. | G36: 5 000 hab. | H36: 10 000 hab. | I36: 20 000 hab. | J36: 50 000 hab. | K36: 100 000 hab. | L36: et plus | M36: de 10 000 hab. | N36: et plus | O36: communes
A38: Nombre d'habitants appartenant à :
A39: CU ou métropoles(a) | B39: 857 | C39: 7302 | D39: 48416 | E39: 501787 | F39: 520479 | G39: 521567 | H39: 1895546 | I39: 2152524 | J39: 4776233 | K39: 3032672 | L39: 9560835 | M39: 3495954 | N39: 19522264 | O39: 23018218
A40: CA | B40: 14636 | C40: 82071 | D40: 540907 | E40: 3174205 | F40: 2158202 | G40: 1523844 | H40: 3249981 | I40: 3522107 | J40: 5972482 | K40: 3051518 | L40: 791736 | M40: 10743846 | N40: 13337843 | O40: 24081689
A41: CC à FPU | B41: 145526 | C41: 541295 | D41: 2054577 | E41: 6561600 | F41: 3050888 | G41: 1900346 | H41: 3111498 | I41: 1760804 | J41: 209986 | K41: 50537 | L41: - | M41: 17365730 | N41: 2021327 | O41: 19387057
A42: CC à FA | B42: 52089 | C42: 160287 | D42: 437616 | E42: 868783 | F42: 292270 | G42: 201238 | H42: 267391 | I42: 110265 | J42: - | K42: - | L42: - | M42: 2279674 | N42: 110265 | O42: 2389939
A43: non membre d'un groupement fiscalisé | B43: - | C43: - | D43: 687 | E43: 853 | F43: - | G43: - | H43: 5017 | I43: - | J43: - | K43: - | L43: - | M43: 6557 | N43: - | O43: 6557
A44: Total | B44: =SUM(B39:B43) -> 213108 | C44: =SUM(C39:C43) -> 790955 | D44: =SUM(D39:D43) -> 3082203 | E44: =SUM(E39:E43) -> 11107228 | F44: =SUM(F39:F43) -> 6021839 | G44: =SUM(G39:G43) -> 4146995 | H44: =SUM(H39:H43) -> 8529433 | I44: =SUM(I39:I43) -> 7545700 | ... O44: =SUM(O39:O43) -> 68883460
A45: Pourcentage d'habitants appartenant à :
A46: CU ou métropoles(a) | B46: =B39/B$44 -> 0.0040214351 | C46: =C39/C$44 -> 0.0092318779 | D46: =D39/D$44 -> 0.015708245 | E46: =E39/E$44 -> 0.045176618 | F46: =F39/F$44 -> 0.086431902 | G46: =G39/G$44 -> 0.12576986 | H46: =H39/H$44 -> 0.22223587 | I46: =I39/I$44 -> 0.28526499 | ... O46: =O39/O$44 -> 0.33416176
A47: CA | B47: =B40/B$44 -> 0.068678792 | C47: =C40/C$44 -> 0.10376191 | D47: =D40/D$44 -> 0.17549363 | E47: =E40/E$44 -> 0.28577832 | F47: =F40/F$44 -> 0.35839583 | G47: =G40/G$44 -> 0.3674574 | H47: =H40/H$44 -> 0.38103131 | I47: =I40/I$44 -> 0.46677008 | ... O47: =O40/O$44 -> 0.34960046
A48: CC à FPU | B48: =B41/B$44 -> 0.68287441 | C48: =C41/C$44 -> 0.68435625 | D48: =D41/D$44 -> 0.66659367 | E48: =E41/E$44 -> 0.59075046 | F48: =F41/F$44 -> 0.50663726 | G48: =G41/G$44 -> 0.45824651 | H48: =H41/H$44 -> 0.36479541 | I48: =I41/I$44 -> 0.23335198 | ... K48: =K41/K$44 -> 0.0082378564 | L48: - | M48: =M41/M$44 -> 0.51238795 | N48: =N41/N$44 -> 0.0577659 | O48: =O41/O$44 -> 0.2814472
A49: CC à FA | B49: =B42/B$44 -> 0.24442536 | C49: =C42/C$44 -> 0.20264996 | D49: =D42/D$44 -> 0.14198156 | E49: =E42/E$44 -> 0.078217806 | F49: =F42/F$44 -> 0.048535007 | G49: =G42/G$44 -> 0.048526222 | H49: =H42/H$44 -> 0.031349212 | I49: =I42/I$44 -> 0.014612958 | J49: - | K49: - | L49: - | M49: =M42/M$44 -> 0.067263368 | N49: =N42/N$44 -> 0.0031511759 | O49: =O42/O$44 -> 0.034695397
A50: non membre d'un groupement fiscalisé | B50: - | C50: - | D50: =D43/D$44 -> 0.00022289252 | E50: =E43/E$44 -> 7.6796839e-05 | F50: - | G50: - | H50: =H43/H$44 -> 0.00058819854 | I50: - | J50: - | K50: - | L50: - | M50: =M43/M$44 -> 0.00019346885 | N50: - | O50: =O43/O$44 -> 9.518976e-05
A51: Total | B51: =B44/B$44 -> 1 | C51: =C44/C$44 -> 1 | D51: =D44/D$44 -> 1 | E51: =E44/E$44 -> 1 | F51: =F44/F$44 -> 1 | G51: =G44/G$44 -> 1 | H51: =H44/H$44 -> 1 | I51: =I44/I$44 -> 1 | ... O51: =O44/O$44 -> 1
A52: (a) Y compris la métropole de Lyon.
A53: FA: Fiscalité Additionnelle ; FPU: Fiscalité Professionnelle Unique ;
A54: CU: Communauté Urbaine ; CA: Communauté d'Agglomération ;
A55: CC: Communauté de Communes.
A56: Lecture : les communes de moins de 100 habitants appartenant à une CU ou métropole regroupent 857 habitants.
A57: Source : DGFIP, comptes de gestion ; INSEE, Recensement de la population (population totale en 2024 - année de référence 2021) ; calculs DGCL.

Sheet T 1.4
A1: T 1.4.a - Répartition des communes selon leur caractère touristique et de montagne en 2024
B4: Moins | C4: De 100 | D4: De 200 | E4: De 500 | F4: De 2 000 | G4: De 3 500 | H4: De 5 000 | I4: De 10 000 | J4: De 20 000 | K4: De 50 000 | L4: 100000 | M4: Communes | N4: Communes | O4: Ensemble
A5: Strate des communes | B5: de 100 | C5: à moins de | D5: à moins de | E5: à moins de | F5: à moins de | G5: à moins de | H5: à moins de | I5: à moins de | J5: à moins de | K5: à moins de | L5: habitants | M5: de moins | N5: de 10 000 hab. | O5: des
B6: habitants | C6: 200 hab. | D6: 500 hab. | E6: 2 000 hab. | F6: 3 500 hab. | G6: 5 000 hab. | H6: 10 000 hab. | I6: 20 000 hab. | J6: 50 000 hab. | K6: 100 000 hab. | L6: et plus | M6: de 10 000 hab. | N6: et plus | O6: communes
A7: En nombre de communes(a)
A8: Communes touristiques(b) :
A9: - Communes touristiques du littoral maritime | B9: 3 | C9: 18 | D9: 33 | E9: 160 | F9: 116 | G9: 74 | H9: 71 | I9: 37 | J9: 17 | K9: 3 | L9: - | M9: 475 | N9: 57 | O9: 532
A10: - Communes touristiques "supports de station de sport d'hiver" | B10: 10 | C10: 21 | D10: 77 | E10: 139 | F10: 27 | G10: 14 | H10: 7 | I10: 4 | J10: - | K10: - | L10: - | M10: 295 | N10: 4 | O10: 299
A11: - Autres communes touristiques de montagne | B11: 145 | C11: 141 | D11: 232 | E11: 258 | F11: 51 | G11: 17 | H11: 10 | I11: 1 | J11: 1 | K11: - | L11: - | M11: 854 | N11: 2 | O11: 856
A12: - Autres communes touristiques | B12: 6 | C12: 23 | D12: 66 | E12: 194 | F12: 72 | G12: 29 | H12: 32 | I12: 12 | J12: 3 | K12: - | L12: - | M12: 422 | N12: 15 | O12: 437
A13: Nombre total des communes touristiques(b) | B13: =SUM(B9:B12) -> 164 | C13: =SUM(C9:C12) -> 203 | D13: =SUM(D9:D12) -> 408 | E13: =SUM(E9:E12) -> 751 | F13: =SUM(F9:F12) -> 266 | G13: =SUM(G9:G12) -> 134 | H13: =SUM(H9:H12) -> 120 | I13: =SUM(I9:I12) -> 54 | ... K13: =SUM(K9:K12) -> 3 | L13: - | M13: =SUM(M9:M12) -> 2046 | N13: =SUM(N9:N12) -> 78 | O13: =SUM(O9:O12) -> 2124
A14: Communes non touristiques :
A15: - Communes de montagne | B15: 889 | C15: 963 | D15: 1332 | E15: 1222 | F15: 169 | G15: 69 | H15: 107 | I15: 44 | J15: 18 | K15: 6 | L15: 4 | M15: 4751 | N15: 72 | O15: 4823
A16: - Communes hors montagne | B16: 2232 | C16: 4197 | D16: 7726 | E16: 9280 | F16: 1863 | G16: 793 | H16: 1000 | I16: 455 | J16: 322 | K16: 82 | L16: 38 | M16: 27091 | N16: 897 | O16: 27988
A17: Nombre total des communes non touristiques | B17: =SUM(B15:B16) -> 3121 | C17: =SUM(C15:C16) -> 5160 | D17: =SUM(D15:D16) -> 9058 | E17: =SUM(E15:E16) -> 10502 | F17: =SUM(F15:F16) -> 2032 | G17: =SUM(G15:G16) -> 862 | H17: =SUM(H15:H16) -> 1107 | I17: =SUM(I15:I16) -> 499 | ... O17: =SUM(O15:O16) -> 32811
A18: Part des communes touristiques(b) appartenant à :
A19: - Communes touristiques du littoral maritime | B19: =B9/B$13 -> 0.018292683 | C19: =C9/C$13 -> 0.088669951 | D19: =D9/D$13 -> 0.080882353 | E19: =E9/E$13 -> 0.21304927 | F19: =F9/F$13 -> 0.43609023 | G19: =G9/G$13 -> 0.55223881 | H19: =H9/H$13 -> 0.59166667 | I19: =I9/I$13 -> 0.68518519 | ... K19: =K9/K$13 -> 1 | L19: - | M19: =M9/M$13 -> 0.23216031 | N19: =N9/N$13 -> 0.73076923 | O19: =O9/O$13 -> 0.25047081
A20: - Communes touristiques "supports de station de sport d'hiver" | B20: =B10/B$13 -> 0.06097561 | C20: =C10/C$13 -> 0.10344828 | D20: =D10/D$13 -> 0.18872549 | E20: =E10/E$13 -> 0.18508655 | F20: =F10/F$13 -> 0.10150376 | G20: =G10/G$13 -> 0.10447761 | H20: =H10/H$13 -> 0.058333333 | I20: =I10/I$13 -> 0.074074074 | J20: - | K20: - | L20: - | M20: =M10/M$13 -> 0.14418377 | N20: =N10/N$13 -> 0.051282051 | O20: =O10/O$13 -> 0.14077213
A21: - Autres communes touristiques de montagne | B21: =B11/B$13 -> 0.88414634 | C21: =C11/C$13 -> 0.69458128 | D21: =D11/D$13 -> 0.56862745 | E21: =E11/E$13 -> 0.34354194 | F21: =F11/F$13 -> 0.19172932 | G21: =G11/G$13 -> 0.12686567 | H21: =H11/H$13 -> 0.083333333 | I21: =I11/I$13 -> 0.018518519 | J21: =J11/J$13 -> 0.047619048 | K21: - | L21: - | M21: =M11/M$13 -> 0.4173998 | N21: =N11/N$13 -> 0.025641026 | O21: =O11/O$13 -> 0.40301318
A22: - Autres communes touristiques | B22: =B12/B$13 -> 0.036585366 | C22: =C12/C$13 -> 0.11330049 | D22: =D12/D$13 -> 0.16176471 | E22: =E12/E$13 -> 0.25832224 | F22: =F12/F$13 -> 0.27067669 | G22: =G12/G$13 -> 0.21641791 | H22: =H12/H$13 -> 0.26666667 | I22: =I12/I$13 -> 0.22222222 | J22: =J12/J$13 -> 0.14285714 | K22: - | L22: - | M22: =M12/M$13 -> 0.20625611 | N22: =N12/N$13 -> 0.19230769 | O22: =O12/O$13 -> 0.20574388
A23: Ensemble des communes touristiques(b) | B23: =B13/B$13 -> 1 | C23: =C13/C$13 -> 1 | D23: =D13/D$13 -> 1 | E23: =E13/E$13 -> 1 | F23: =F13/F$13 -> 1 | G23: =G13/G$13 -> 1 | H23: =H13/H$13 -> 1 | I23: =I13/I$13 -> 1 | ... K23: =K13/K$13 -> 1 | L23: - | M23: =M13/M$13 -> 1 | N23: =N13/N$13 -> 1 | O23: =O13/O$13 -> 1
A24: Part des communes non touristiques appartenant à :
A25: - Communes de montagne | B25: =B15/B$17 -> 0.2848446 | C25: =C15/C$17 -> 0.18662791 | D25: =D15/D$17 -> 0.14705233 | E25: =E15/E$17 -> 0.11635879 | F25: =F15/F$17 -> 0.083169291 | G25: =G15/G$17 -> 0.080046404 | H25: =H15/H$17 -> 0.096657633 | I25: =I15/I$17 -> 0.088176353 | ... O25: =O15/O$17 -> 0.14699339
A26: - Communes hors montagne | B26: =B16/B$17 -> 0.7151554 | C26: =C16/C$17 -> 0.81337209 | D26: =D16/D$17 -> 0.85294767 | E26: =E16/E$17 -> 0.88364121 | F26: =F16/F$17 -> 0.91683071 | G26: =G16/G$17 -> 0.9199536 | H26: =H16/H$17 -> 0.90334237 | I26: =I16/I$17 -> 0.91182365 | ... O26: =O16/O$17 -> 0.85300661
A27: Ensemble des communes non touristiques | B27: =B17/B$17 -> 1 | C27: =C17/C$17 -> 1 | D27: =D17/D$17 -> 1 | E27: =E17/E$17 -> 1 | F27: =F17/F$17 -> 1 | G27: =G17/G$17 -> 1 | H27: =H17/H$17 -> 1 | I27: =I17/I$17 -> 1 | ... O27: =O17/O$17 -> 1
A28: (a) Il s'agit, plus précisément, du nombre de budgets principaux de communes.
A29: (b) Les communes touristiques concernent uniquement la France métropolitaine.
A30: Lecture : il y a seulement trois communes touristiques du littoral maritime de moins de 100 habitants. Elle correspond à 1,8 % de l'ensemble des communes touristiques de moins de 100 habitants.
A31: Source : DGFIP, comptes de gestion ; INSEE, Recensement de la population (population totale en 2024 - année de référence 2021) ; calculs DGCL. ; calculs DGCL.
A33: T 1.4.b - Répartition de la «population DGF» des communes selon leur caractère touristique et de montagne en 2024
B36: Moins | C36: De 100 | D36: De 200 | E36: De 500 | F36: De 2 000 | G36: De 3 500 | H36: De 5 000 | I36: De 10 000 | J36: De 20 000 | K36: De 50 000 | L36: 100000 | M36: Communes | N36: Communes | O36: Ensemble
A37: Strate des communes(a) | B37: de 100 | C37: à moins de | D37: à moins de | E37: à moins de | F37: à moins de | G37: à moins de | H37: à moins de | I37: à moins de | J37: à moins de | K37: à moins de | L37: habitants | M37: de moins | N37: de 10 000 hab. | O37: des
B38: habitants | C38: 200 hab. | D38: 500 hab. | E38: 2 000 hab. | F38: 3 500 hab. | G38: 5 000 hab. | H38: 10 000 hab. | I38: 20 000 hab. | J38: 50 000 hab. | K38: 100 000 hab. | L38: et plus | M38: de 10 000 hab. | N38: et plus | O38: communes
A40: Nombre d'habitants «DGF» des communes touristiques(b) :
A41: - Communes touristiques du littoral maritime | B41: 466 | C41: 6063 | D41: 18917 | E41: 322405 | F41: 477537 | G41: 503400 | H41: 750217 | I41: 709482 | J41: 719743 | K41: 239732 | L41: - | M41: 2079005 | N41: 1668957 | O41: 3747962
A42: - Communes touristiques "supports de station de sport d'hiver" | B42: 2261 | C42: 11791 | D42: 72572 | E42: 334525 | F42: 131352 | G42: 94591 | H42: 81819 | I42: 56358 | J42: - | K42: - | L42: - | M42: 728911 | N42: 56358 | O42: 785269
A43: - Autres communes touristiques de montagne | B43: 15497 | C43: 33841 | D43: 109980 | E43: 302490 | F43: 145325 | G43: 79307 | H43: 67262 | I43: 14934 | J43: 23545 | K43: - | L43: - | M43: 753702 | N43: 38479 | O43: 792181
A44: - Autres communes touristiques | B44: 537 | C44: 5122 | D44: 29518 | E44: 242182 | F44: 214716 | G44: 127250 | H44: 245562 | I44: 168340 | J44: 74549 | K44: - | L44: - | M44: 864887 | N44: 242889 | O44: 1107776
A45: Nombre total d'habitants «DGF» des communes touristiques(b) | B45: =SUM(B41:B44) -> 18761 | C45: =SUM(C41:C44) -> 56817 | D45: =SUM(D41:D44) -> 230987 | E45: =SUM(E41:E44) -> 1201602 | F45: =SUM(F41:F44) -> 968930 | G45: =SUM(G41:G44) -> 804548 | H45: =SUM(H41:H44) -> 1144860 | I45: =SUM(I41:I44) -> 949114 | ... K45: =SUM(K41:K44) -> 239732 | L45: - | M45: =SUM(M41:M44) -> 4426505 | N45: =SUM(N41:N44) -> 2006683 | O45: =SUM(O41:O44) -> 6433188
A46: Nombre d'habitants «DGF» des communes non touristiques :
A47: - Communes de montagne | B47: 81999 | C47: 191177 | D47: 514746 | E47: 1270852 | F47: 459529 | G47: 290551 | H47: 781805 | I47: 630302 | J47: 564977 | K47: 413173 | L47: 584276 | M47: 3590659 | N47: 2192728 | O47: 5783387
A48: - Communes hors montagne | B48: 169167 | C48: 680698 | D48: 2687075 | E48: 9484619 | F48: 4976523 | G48: 3365063 | H48: 7029789 | I48: 6278733 | J48: 9868384 | K48: 5679292 | L48: 10107427 | M48: 28392934 | N48: 31933836 | O48: 60326770
A49: Nombre total d'habitants «DGF» des communes non touristiques | B49: =SUM(B47:B48) -> 251166 | C49: =SUM(C47:C48) -> 871875 | D49: =SUM(D47:D48) -> 3201821 | E49: =SUM(E47:E48) -> 10755471 | F49: =SUM(F47:F48) -> 5436052 | G49: =SUM(G47:G48) -> 3655614 | H49: =SUM(H47:H48) -> 7811594 | I49: =SUM(I47:I48) -> 6909035 | ... O49: =SUM(O47:O48) -> 66110157
A50: Proportion d'habitants «DGF» des communes touristiques(b) appartenant à :
A51: - Communes touristiques du littoral maritime | B51: =B41/B$45 -> 0.024838761 | C51: =C41/C$45 -> 0.10671102 | D51: =D41/D$45 -> 0.081896384 | E51: =E41/E$45 -> 0.26831264 | F51: =F41/F$45 -> 0.49284984 | G51: =G41/G$45 -> 0.62569294 | H51: =H41/H$45 -> 0.65529148 | I51: =I41/I$45 -> 0.74752032 | ... K51: =K41/K$45 -> 1 | L51: - | M51: =M41/M$45 -> 0.4696719 | N51: =N41/N$45 -> 0.83169938 | O51: =O41/O$45 -> 0.58259793
A52: - Communes touristiques "supports de station de sport d'hiver" | B52: =B42/B$45 -> 0.12051596 | C52: =C42/C$45 -> 0.20752592 | D52: =D42/D$45 -> 0.31418218 | E52: =E42/E$45 -> 0.27839917 | F52: =F42/F$45 -> 0.13556397 | G52: =G42/G$45 -> 0.11757036 | H52: =H42/H$45 -> 0.07146638 | I52: =I42/I$45 -> 0.05937959 | J52: - | K52: - | L52: - | M52: =M42/M$45 -> 0.16466964 | N52: =N42/N$45 -> 0.028085153 | O52: =O42/O$45 -> 0.1220653
A53: - Autres communes touristiques de montagne | B53: =B43/B$45 -> 0.82602207 | C53: =C43/C$45 -> 0.59561399 | D53: =D43/D$45 -> 0.47613069 | E53: =E43/E$45 -> 0.25173893 | F53: =F43/F$45 -> 0.14998504 | G53: =G43/G$45 -> 0.09857336 | H53: =H43/H$45 -> 0.058751288 | I53: =I43/I$45 -> 0.015734675 | J53: =J43/J$45 -> 0.028789355 | K53: - | L53: - | M53: =M43/M$45 -> 0.17027022 | N53: =N43/N$45 -> 0.019175425 | O53: =O43/O$45 -> 0.12313972
A54: - Autres communes touristiques | B54: =B44/B$45 -> 0.028623208 | C54: =C44/C$45 -> 0.090149075 | D54: =D44/D$45 -> 0.12779074 | E54: =E44/E$45 -> 0.20154927 | F54: =F44/F$45 -> 0.22160115 | G54: =G44/G$45 -> 0.15816334 | H54: =H44/H$45 -> 0.21449085 | I54: =I44/I$45 -> 0.17736542 | J54: =J44/J$45 -> 0.091153861 | K54: - | L54: - | M54: =M44/M$45 -> 0.19538824 | N54: =N44/N$45 -> 0.12104004 | O54: =O44/O$45 -> 0.17219705
A55: Ensemble des communes touristiques(b) | B55: =B45/B$45 -> 1 | C55: =C45/C$45 -> 1 | D55: =D45/D$45 -> 1 | E55: =E45/E$45 -> 1 | F55: =F45/F$45 -> 1 | G55: =G45/G$45 -> 1 | H55: =H45/H$45 -> 1 | I55: =I45/I$45 -> 1 | ... K55: =K45/K$45 -> 1 | L55: - | M55: =M45/M$45 -> 1 | N55: =N45/N$45 -> 1 | O55: =O45/O$45 -> 1
A56: Proportion d'habitants «DGF» des communes non touristiques appartenant à:
A57: - Communes de montagne | B57: =B47/B$49 -> 0.32647333 | C57: =C47/C$49 -> 0.21927111 | D57: =D47/D$49 -> 0.16076664 | E57: =E47/E$49 -> 0.11815866 | F57: =F47/F$49 -> 0.084533592 | G57: =G47/G$49 -> 0.079480766 | H57: =H47/H$49 -> 0.10008265 | I57: =I47/I$49 -> 0.091228659 | ... O57: =O47/O$49 -> 0.087481066
A58: - Communes hors montagne | B58: =B48/B$49 -> 0.67352667 | C58: =C48/C$49 -> 0.78072889 | D58: =D48/D$49 -> 0.83923336 | E58: =E48/E$49 -> 0.88184134 | F58: =F48/F$49 -> 0.91546641 | G58: =G48/G$49 -> 0.92051923 | H58: =H48/H$49 -> 0.89991735 | I58: =I48/I$49 -> 0.90877134 | ... O58: =O48/O$49 -> 0.91251893
A59: Ensemble des communes non touristiques | B59: =B49/B$49 -> 1 | C59: =C49/C$49 -> 1 | D59: =D49/D$49 -> 1 | E59: =E49/E$49 -> 1 | F59: =F49/F$49 -> 1 | G59: =G49/G$49 -> 1 | H59: =H49/H$49 -> 1 | I59: =I49/I$49 -> 1 | ... O59: =O49/O$49 -> 1
A60: (a) Les strates de communes sont calculées à partir de la population totale de l'Insee (population totale en 2024 - année de référence 2021).
A61: (b) Les communes touristiques concernent uniquement la France métropolitaine.
A62: Lecture: il y a 2 261 habitants « DGF » dans les communes touristiques "supports de station de sport d'hiver" de moins de 100 habitants. Elles regroupent 12,1 % de la population « DGF » des communes touristiques de moins de 100 habitants.
A63: Source : INSEE, Recensement de la population (population DGF en 2024 - année de référence 2021) ; calculs DGCL.
A65: Les communes touristiques : au sens de l'article L2334-7 du CGCT, la dénomination "commune touristique" désigne les collectivités qui étaient bénéficiaires de la dotation supplémentaire touristique aujourd'hui intégrée au sein de la dotation forfaitaire (loi n°93-1436 du 31 décembre 1993) dans la dotation globale de fonctionnement (source : Ministère de l'Intérieur, DGCL). La dotation touristique se fondait sur la capacité d'accueil et d'hébergement de la commune. Les communes touristiques concernent uniquement la métropole.
A69: Parmi les communes touristiques, on distingue les catégories suivantes :
A71: Communes touristiques du littoral maritime : ce sont les communes touristiques appartenant également à la liste des communes du littoral maritime. Cette liste comprend les communes de bord de mer et les communes d'estuaires, en aval de la limite transversale de la mer (source : Institut Français de l'Environnement).
A74: Communes touristiques de montagne : Les communes de montagne sont repérées à l'aide du classement en zone défavorisée réalisé par le Ministère de l'Agriculture. Les communes retenues sont celles qui sont entièrement classées "montagne" ou "haute montagne" et en métropole (source : Ministère de l'Agriculture, de la pêche, de la ruralité et de l'aménagement du territoire).
A78: Communes touristiques "supports de station de sports d'hiver" : ce sont les communes touristiques également classées comme "supports de stations de sports d'hiver". Ces dernières sont définies à partir de la capacité d'hébergement et de la présence de remontées mécaniques. Les critères de sélection des communes touristiques conduisent à exclure du champ d'étude les communes dont l'activité liée au tourisme d'hiver est mineure (faible capacité d'hébergement et nombre réduit de remontées mécaniques) (source : Service d'Etudes d'Aménagement Touristique de la Montagne).
A83: Les communes classées en zone de montagne : Le classement des communes en zone de montagne repose sur les dispositions du règlement n°1257/1999 du Conseil de l’UE du 17 mai 1999 concernant le soutien au développement rural et plus particulièrement sur son article 18 pour la montagne, et la directive 76/401/CEE du Conseil du 6 avril 1976 (détermination précise des critères pour le classement en France en zone de montagne). La zone de montagne est définie comme se caractérisant par des handicaps liés à l’altitude, à la pente, et/ou au climat, qui ont pour effet de restreindre de façon conséquente les possibilités d’utilisation des terres et d’augmenter de manière générale le coût de tous les travaux. Cette liste de communes zones de montagne sert notamment au calcul de la dotation globale de fonctionnement des communes par la DGCL.
A85: Population totale et population « DGF » : Dans le recensement de la population, la « population totale » est égale à la « population municipale » augmentée de la « population comptée à part », c’est-à-dire les personnes recensées sur d’autres communes mais qui ont conservé un lien avec une résidence sur la commune (par exemple les étudiants). La somme de toutes les populations totales dépasse donc la population réelle, du fait des personnes comptées à part, comptées une fois dans leur commune de résidence et une fois dans leur commune de rattachement occasionnel. Pour le calcul des dotations on inclut ces habitants comptés à part ; on considère en effet que ces personnes pèsent sur le budget de fonctionnement de la commune même si elles résident habituellement dans une autre commune. Pour tenir compte des conditions particulières de certaines communes, qui pèsent sur leur fonctionnement, cette population totale est, en plus, majorée en fonction de deux critères particuliers. Il ne s’agit plus d’habitants « réels » recensés, mais d’une attribution forfaitaire exprimée en nombre d’habitants par commodité de calcul. - majoration en fonction du nombre de résidences secondaires : la population totale issue du recensement est forfaitairement majorée d’un habitant par résidence secondaire. Elles sont particulièrement nombreuses dans les zones touristiques. Cela aboutit à majorer la population nationale à ce titre d’un forfait de plus de 3 millions « d’habitants ». - majoration pour places de caravanes dans les aires d’accueil des gens du voyage. Selon la même logique, la population totale est majorée d’un habitant par place de caravane située sur une aire d’accueil des gens du voyage. La majoration de population est portée à deux habitants par place de caravane pour les communes éligibles l’année précédente à la dotation de solidarité urbaine (DSU) ou à la première fraction (bourg-centre) de la dotation de solidarité rurale (DSR). Les caravanes de campings dans le cadre de l’hôtellerie de plein air ne sont pas concernées. Une fois effectuées ces deux majorations de la population totale, on obtient une population forfaitaire, dite « population DGF », car utilisée pour calculer la principale dotation que lui verse l’État pour son fonctionnement, la dotation globale de fonctionnement (DGF).

Sheet T 1.5
A1: T 1.5.a - Répartition des communes selon leur caractère urbain ou rural en 2024
B4: Moins | C4: De 100 | D4: De 200 | E4: De 500 | F4: De 2 000 | G4: De 3 500 | H4: De 5 000 | I4: De 10 000 | J4: De 20 000 | K4: De 50 000 | L4: 100000 | M4: Budgets des | N4: Budgets des | O4: Ensemble
A5: Strate des communes | B5: de 100 | C5: à moins de | D5: à moins de | E5: à moins de | F5: à moins de | G5: à moins de | H5: à moins de | I5: à moins de | J5: à moins de | K5: à moins de | L5: habitants | M5: communes de moins | N5: communes de | O5: des
B6: habitants | C6: 200 hab. | D6: 500 hab. | E6: 2 000 hab. | F6: 3 500 hab. | G6: 5 000 hab. | H6: 10 000 hab. | I6: 20 000 hab. | J6: 50 000 hab. | K6: 100 000 hab. | L6: et plus | M6: de 10 000 hab. | N6: 10 000 hab. et plus | O6: budgets
A7: En nombre de communes (a)
A8: Budgets des communes appartenant à :
A9: Communes rurales | B9: 3285 | C9: 5361 | D9: 9405 | E9: 10245 | F9: 1565 | G9: 560 | H9: 302 | I9: 16 | J9: 4 | K9: - | L9: - | M9: 30723 | N9: 20 | O9: 30743
A10: Communes urbaines | B10: - | C10: 2 | D10: 61 | E10: 1008 | F10: 733 | G10: 436 | H10: 925 | I10: 537 | J10: 357 | K10: 91 | L10: 42 | M10: 3165 | N10: 1027 | O10: 4192
A11: Total des communes rurales et urbaines | B11: =SUM(B9:B10) -> 3285 | C11: =SUM(C9:C10) -> 5363 | D11: =SUM(D9:D10) -> 9466 | E11: =SUM(E9:E10) -> 11253 | F11: =SUM(F9:F10) -> 2298 | G11: =SUM(G9:G10) -> 996 | H11: =SUM(H9:H10) -> 1227 | I11: =SUM(I9:I10) -> 553 | ... O11: =SUM(O9:O10) -> 34935
A12: Type de communes rurales et urbaines :
A13: Grands centres urbains | B13: - | C13: - | D13: - | E13: 10 | F13: 32 | G13: 45 | H13: 166 | I13: 191 | J13: 215 | K13: 73 | L13: 41 | M13: 253 | N13: 520 | O13: 773
A14: Centres urbains intermédiaires | B14: - | C14: - | D14: - | E14: 8 | F14: 20 | G14: 23 | H14: 135 | I14: 225 | J14: 115 | K14: 18 | L14: 1 | M14: 186 | N14: 359 | O14: 545
A15: Petites villes | B15: - | C15: 2 | D15: 26 | E15: 263 | F15: 157 | G15: 108 | H15: 273 | I15: 63 | J15: 9 | K15: - | L15: - | M15: 829 | N15: 72 | O15: 901
A16: Ceintures urbaines | B16: - | C16: - | D16: 35 | E16: 727 | F16: 524 | G16: 260 | H16: 351 | I16: 58 | J16: 18 | K16: - | L16: - | M16: 1897 | N16: 76 | O16: 1973
A17: Bourgs ruraux | B17: 2 | C17: 11 | D17: 154 | E17: 3035 | F17: 1161 | G17: 468 | H17: 256 | I17: 13 | J17: 4 | K17: - | L17: - | M17: 5087 | N17: 17 | O17: 5104
A18: Rural à habitat dispersé | B18: 1093 | C18: 3243 | D18: 6949 | E18: 6577 | F18: 382 | G18: 90 | H18: 43 | I18: 3 | J18: - | K18: - | L18: - | M18: 18377 | N18: 3 | O18: 18380
A19: Rural à habitat très dispersé | B19: 2190 | C19: 2107 | D19: 2302 | E19: 632 | F19: 22 | G19: 2 | H19: 3 | I19: - | J19: - | K19: - | L19: - | M19: 7258 | N19: - | O19: 7258
A20: Ensemble des communes rurales et urbaines | B20: =SUM(B13:B19) -> 3285 | C20: =SUM(C13:C19) -> 5363 | D20: =SUM(D13:D19) -> 9466 | E20: =SUM(E13:E19) -> 11252 | F20: =SUM(F13:F19) -> 2298 | G20: =SUM(G13:G19) -> 996 | H20: =SUM(H13:H19) -> 1227 | I20: =SUM(I13:I19) -> 553 | ... O20: =SUM(O13:O19) -> 34934
A21: Proportion des communes appartenant à :
A22: Communes rurales | B22: =B9/B$11 -> 1 | C22: =C9/C$11 -> 0.99962707 | D22: =D9/D$11 -> 0.99355588 | E22: =E9/E$11 -> 0.91042389 | F22: =F9/F$11 -> 0.68102698 | G22: =G9/G$11 -> 0.562249 | H22: =H9/H$11 -> 0.24612877 | I22: =I9/I$11 -> 0.028933092 | J22: =J9/J$11 -> 0.011080332 | K22: - | L22: - | M22: =M9/M$11 -> 0.90660411 | N22: =N9/N$11 -> 0.019102197 | O22: =O9/O$11 -> 0.88000572
A23: Communes urbaines | B23: - | C23: - | D23: =D10/D$11 -> 0.0064441158 | E23: =E10/E$11 -> 0.089576113 | F23: =F10/F$11 -> 0.31897302 | G23: =G10/G$11 -> 0.437751 | H23: =H10/H$11 -> 0.75387123 | I23: =I10/I$11 -> 0.97106691 | J23: =J10/J$11 -> 0.98891967 | K23: =K10/K$11 -> 1 | ... O23: =O10/O$11 -> 0.11999428
A24: Ensemble des communes rurales et urbaines | B24: =B11/B$11 -> 1 | C24: =C11/C$11 -> 1 | D24: =D11/D$11 -> 1 | E24: =E11/E$11 -> 1 | F24: =F11/F$11 -> 1 | G24: =G11/G$11 -> 1 | H24: =H11/H$11 -> 1 | I24: =I11/I$11 -> 1 | ... O24: =O11/O$11 -> 1
A25: Type de communes rurales et urbaines :
A26: Grands centres urbains | B26: - | C26: - | D26: - | E26: =E13/E$20 -> 0.00088873089 | F26: =F13/F$20 -> 0.013925152 | G26: =G13/G$20 -> 0.045180723 | H26: =H13/H$20 -> 0.13528932 | I26: =I13/I$20 -> 0.34538879 | J26: =J13/J$20 -> 0.59556787 | K26: =K13/K$20 -> 0.8021978 | L26: =L13/L$20 -> 0.97619048 | ... O26: =O13/O$20 -> 0.02212744
A27: Centres urbains intermédiaires | B27: - | C27: - | D27: - | E27: =E14/E$20 -> 0.00071098471 | F27: =F14/F$20 -> 0.0087032202 | G27: =G14/G$20 -> 0.023092369 | H27: =H14/H$20 -> 0.11002445 | I27: =I14/I$20 -> 0.40687161 | J27: =J14/J$20 -> 0.31855956 | K27: =K14/K$20 -> 0.1978022 | L27: =L14/L$20 -> 0.023809524 | ... O27: =O14/O$20 -> 0.015600847
A28: Petites villes | B28: - | C28: =C15/C$20 -> 0.0003729256 | D28: =D15/D$20 -> 0.0027466723 | E28: =E15/E$20 -> 0.023373622 | F28: =F15/F$20 -> 0.068320279 | G28: =G15/G$20 -> 0.10843373 | H28: =H15/H$20 -> 0.22249389 | I28: =I15/I$20 -> 0.11392405 | J28: =J15/J$20 -> 0.024930748 | K28: - | L28: - | M28: =M15/M$20 -> 0.024463659 | N28: =N15/N$20 -> 0.068767908 | O28: =O15/O$20 -> 0.025791493
A29: Ceintures urbaines | B29: - | C29: - | D29: =D16/D$20 -> 0.0036974435 | E29: =E16/E$20 -> 0.064610736 | F29: =F16/F$20 -> 0.22802437 | G29: =G16/G$20 -> 0.26104418 | H29: =H16/H$20 -> 0.28606357 | I29: =I16/I$20 -> 0.10488246 | J29: =J16/J$20 -> 0.049861496 | K29: - | L29: - | M29: =M16/M$20 -> 0.055980169 | N29: =N16/N$20 -> 0.072588348 | O29: =O16/O$20 -> 0.05647793
A30: Bourgs ruraux | B30: =B17/B$20 -> 0.00060882801 | C30: =C17/C$20 -> 0.0020510908 | D30: =D17/D$20 -> 0.016268751 | E30: =E17/E$20 -> 0.26972983 | F30: =F17/F$20 -> 0.50522193 | G30: =G17/G$20 -> 0.46987952 | H30: =H17/H$20 -> 0.20863896 | I30: =I17/I$20 -> 0.023508137 | J30: =J17/J$20 -> 0.011080332 | K30: - | L30: - | M30: =M17/M$20 -> 0.15011656 | N30: =N17/N$20 -> 0.016236867 | O30: =O17/O$20 -> 0.14610408
A31: Rural à habitat dispersé | B31: =B18/B$20 -> 0.33272451 | C31: =C18/C$20 -> 0.60469886 | D31: =D18/D$20 -> 0.73410099 | E31: =E18/E$20 -> 0.58451831 | F31: =F18/F$20 -> 0.16623151 | G31: =G18/G$20 -> 0.090361446 | H31: =H18/H$20 -> 0.035044825 | I31: =I18/I$20 -> 0.0054249548 | J31: - | K31: - | L31: - | M31: =M18/M$20 -> 0.54230236 | N31: =N18/N$20 -> 0.0028653295 | O31: =O18/O$20 -> 0.526135
A32: Rural à habitat très dispersé | B32: =B19/B$20 -> 0.66666667 | C32: =C19/C$20 -> 0.39287712 | D32: =D19/D$20 -> 0.24318614 | E32: =E19/E$20 -> 0.056167792 | F32: =F19/F$20 -> 0.0095735422 | G32: =G19/G$20 -> 0.0020080321 | H32: =H19/H$20 -> 0.0024449878 | I32: - | J32: - | K32: - | L32: - | M32: =M19/M$20 -> 0.21418243 | N32: - | O32: =O19/O$20 -> 0.20776321
A33: Ensemble des communes rurales et urbaines | B33: =B20/B$20 -> 1 | C33: =C20/C$20 -> 1 | D33: =D20/D$20 -> 1 | E33: =E20/E$20 -> 1 | F33: =F20/F$20 -> 1 | G33: =G20/G$20 -> 1 | H33: =H20/H$20 -> 1 | I33: =I20/I$20 -> 1 | ... O33: =O20/O$20 -> 1
A34: (a) Il s'agit, plus précisément, du nombre de budgets principaux de communes.
A35: Lecture : il y a 3 285 communes rurales de moins de 100 habitants qui constituent 100,0 % des communes de cette strate.
A36: Source : DGFIP, comptes de gestion, budgets principaux. INSEE, Recensement de la population (population totale en 2024 - année de référence 2021) ; calculs DGCL. Grille de densité de l'Insee au 1er janvier 2024 définissant le rural.
A38: T 1.5.b - Répartition de la population totale des communes selon leur caractère urbain ou rural en 2024
B41: Moins | C41: De 100 | D41: De 200 | E41: De 500 | F41: De 2 000 | G41: De 3 500 | H41: De 5 000 | I41: De 10 000 | J41: De 20 000 | K41: De 50 000 | L41: 100000 | M41: Communes | N41: Communes | O41: Ensemble
A42: Strate des communes | B42: de 100 | C42: à moins de | D42: à moins de | E42: à moins de | F42: à moins de | G42: à moins de | H42: à moins de | I42: à moins de | J42: à moins de | K42: à moins de | L42: habitants | M42: de moins | N42: de 10 000 hab. | O42: des
B43: habitants | C43: 200 hab. | D43: 500 hab. | E43: 2 000 hab. | F43: 3 500 hab. | G43: 5 000 hab. | H43: 10 000 hab. | I43: 20 000 hab. | J43: 50 000 hab. | K43: 100 000 hab. | L43: et plus | M43: de 10 000 hab. | N43: et plus | O43: communes
A44: En nombre d'habitants
A45: Nombre d'habitants des communes appartenant à :
A46: Communes rurales | B46: 213108 | C46: 790566 | D46: 3056843 | E46: 9876783 | F46: 4049756 | G46: 2313708 | H46: 1898664 | I46: 232425 | J46: 93620 | K46: - | L46: - | M46: 22199428 | N46: 326045 | O46: 22525473
A47: Communes urbaines | B47: - | C47: 389 | D47: 25360 | E47: 1230445 | F47: 1972083 | G47: 1833287 | H47: 6630769 | I47: 7313275 | J47: 10865081 | K47: 6134727 | L47: 10352571 | M47: 11692333 | N47: 34665654 | O47: 46357987
A48: Total des communes rurales et urbaines | B48: =SUM(B46:B47) -> 213108 | C48: =SUM(C46:C47) -> 790955 | D48: =SUM(D46:D47) -> 3082203 | E48: =SUM(E46:E47) -> 11107228 | F48: =SUM(F46:F47) -> 6021839 | G48: =SUM(G46:G47) -> 4146995 | H48: =SUM(H46:H47) -> 8529433 | I48: =SUM(I46:I47) -> 7545700 | ... O48: =SUM(O46:O47) -> 68883460
A49: Type de communes rurales et urbaines :
A50: Grands centres urbains | B50: - | C50: - | D50: - | E50: 13613 | F50: 92589 | G50: 195193 | H50: 1227121 | I50: 2648013 | J50: 6571474 | K50: 5039061 | L50: 10246017 | M50: 1528516 | N50: 24504565 | O50: 26033081
A51: Centres urbains intermédiaires | B51: - | C51: - | D51: - | E51: 13653 | F51: 58672 | G51: 97508 | H51: 1055910 | I51: 3114502 | J51: 3565593 | K51: 1095666 | L51: 106554 | M51: 1225743 | N51: 7882315 | O51: 9108058
A52: Petites villes | B52: - | C52: 389 | D52: 10182 | E52: 313335 | F52: 415563 | G52: 453659 | H52: 1951980 | I52: 816445 | J52: 232547 | K52: - | L52: - | M52: 3145108 | N52: 1048992 | O52: 4194100
A53: Ceintures urbaines | B53: - | C53: - | D53: 15178 | E53: 889844 | F53: 1405259 | G53: 1086927 | H53: 2395758 | I53: 734315 | J53: 495467 | K53: - | L53: - | M53: 5792966 | N53: 1229782 | O53: 7022748
A54: Bourgs ruraux | B54: 195 | C54: 1886 | D54: 60210 | E54: 3703662 | F54: 3022195 | G54: 1935424 | H54: 1576525 | I54: 197024 | J54: 93620 | K54: - | L54: - | M54: 10300097 | N54: 290644 | O54: 10590741
A55: Rural à habitat dispersé | B55: 84535 | C55: 480713 | D55: 2296601 | E55: 5701417 | F55: 974413 | G55: 369615 | H55: 304453 | I55: 35401 | J55: - | K55: - | L55: - | M55: 10211747 | N55: 35401 | O55: 10247148
A56: Rural à habitat très dispersé | B56: 128378 | C56: 307967 | D56: 700032 | E56: 470077 | F56: 53148 | G56: 8669 | H56: 17686 | I56: - | J56: - | K56: - | L56: - | M56: 1685957 | N56: - | O56: 1685957
A57: Ensemble des communes rurales et urbaines | B57: =SUM(B50:B56) -> 213108 | C57: =SUM(C50:C56) -> 790955 | D57: =SUM(D50:D56) -> 3082203 | E57: =SUM(E50:E56) -> 11105601 | F57: =SUM(F50:F56) -> 6021839 | G57: =SUM(G50:G56) -> 4146995 | H57: =SUM(H50:H56) -> 8529433 | I57: =SUM(I50:I56) -> 7545700 | ... O57: =SUM(O50:O56) -> 68881833
A58: Pourcentage d'habitants des communes appartenant à :
A59: Communes rurales | B59: =B46/B$48 -> 1 | C59: =C46/C$48 -> 0.99950819 | D59: =D46/D$48 -> 0.99177212 | E59: =E46/E$48 -> 0.88922124 | F59: =F46/F$48 -> 0.6725115 | G59: =G46/G$48 -> 0.55792399 | H59: =H46/H$48 -> 0.22260143 | I59: =I46/I$48 -> 0.030802311 | J59: =J46/J$48 -> 0.0085429833 | K59: - | L59: - | M59: =M46/M$48 -> 0.65500958 | N59: =N46/N$48 -> 0.0093177813 | O59: =O46/O$48 -> 0.32700844
A60: Communes urbaines | B60: - | C60: - | D60: =D47/D$48 -> 0.0082278812 | E60: =E47/E$48 -> 0.11077876 | F60: =F47/F$48 -> 0.3274885 | G60: =G47/G$48 -> 0.44207601 | H60: =H47/H$48 -> 0.77739857 | I60: =I47/I$48 -> 0.96919769 | J60: =J47/J$48 -> 0.99145702 | K60: =K47/K$48 -> 1 | ... O60: =O47/O$48 -> 0.67299156
A61: Ensemble des communes rurales et urbaines | B61: =B48/B$48 -> 1 | C61: =C48/C$48 -> 1 | D61: =D48/D$48 -> 1 | E61: =E48/E$48 -> 1 | F61: =F48/F$48 -> 1 | G61: =G48/G$48 -> 1 | H61: =H48/H$48 -> 1 | I61: =I48/I$48 -> 1 | ... O61: =O48/O$48 -> 1
A62: Type de communes rurales et urbaines :
A63: Grands centres urbains | B63: - | C63: - | D63: - | E63: =E50/E$57 -> 0.0012257779 | F63: =F50/F$57 -> 0.015375536 | G63: =G50/G$57 -> 0.04706854 | H63: =H50/H$57 -> 0.143869 | I63: =I50/I$57 -> 0.35093007 | J63: =J50/J$57 -> 0.59965812 | K63: =K50/K$57 -> 0.82139939 | L63: =L50/L$57 -> 0.98970748 | ... O63: =O50/O$57 -> 0.37793827
A64: Centres urbains intermédiaires | B64: - | C64: - | D64: - | E64: =E51/E$57 -> 0.0012293797 | F64: =F51/F$57 -> 0.009743203 | G64: =G51/G$57 -> 0.023512929 | H64: =H51/H$57 -> 0.12379604 | I64: =I51/I$57 -> 0.4127519 | J64: =J51/J$57 -> 0.32536639 | K64: =K51/K$57 -> 0.17860061 | L64: =L51/L$57 -> 0.010292516 | ... O64: =O51/O$57 -> 0.13222729
A65: Petites villes | B65: - | C65: =C52/C$57 -> 0.00049181053 | D65: =D52/D$57 -> 0.0033034813 | E65: =E52/E$57 -> 0.028214142 | F65: =F52/F$57 -> 0.069009318 | G65: =G52/G$57 -> 0.10939463 | H65: =H52/H$57 -> 0.22885226 | I65: =I52/I$57 -> 0.10820003 | J65: =J52/J$57 -> 0.021220307 | K65: - | L65: - | M65: =M52/M$57 -> 0.092803056 | N65: =N52/N$57 -> 0.02997831 | O65: =O52/O$57 -> 0.060888333
A66: Ceintures urbaines | B66: - | C66: - | D66: =D53/D$57 -> 0.0049243999 | E66: =E53/E$57 -> 0.080125695 | F66: =F53/F$57 -> 0.23336044 | G66: =G53/G$57 -> 0.26209991 | H66: =H53/H$57 -> 0.28088127 | I66: =I53/I$57 -> 0.09731569 | J66: =J53/J$57 -> 0.045212202 | K66: - | L66: - | M66: =M53/M$57 -> 0.1709337 | N66: =N53/N$57 -> 0.035144964 | O66: =O53/O$57 -> 0.10195356
A67: Bourgs ruraux | B67: =B54/B$57 -> 0.000915029 | C67: =C54/C$57 -> 0.0023844593 | D67: =D54/D$57 -> 0.019534729 | E67: =E54/E$57 -> 0.33349496 | F67: =F54/F$57 -> 0.50187243 | G67: =G54/G$57 -> 0.46670517 | H67: =H54/H$57 -> 0.18483351 | I67: =I54/I$57 -> 0.026110765 | J67: =J54/J$57 -> 0.0085429833 | K67: - | L67: - | M67: =M54/M$57 -> 0.30392612 | N67: =N54/N$57 -> 0.0083060843 | O67: =O54/O$57 -> 0.15375231
A68: Rural à habitat dispersé | B68: =B55/B$57 -> 0.3966768 | C68: =C55/C$57 -> 0.60776277 | D68: =D55/D$57 -> 0.74511672 | E68: =E55/E$57 -> 0.51338212 | F68: =F55/F$57 -> 0.16181319 | G68: =G55/G$57 -> 0.089128393 | H68: =H55/H$57 -> 0.035694401 | I68: =I55/I$57 -> 0.0046915462 | J68: - | K68: - | L68: - | M68: =M55/M$57 -> 0.30131917 | N68: =N55/N$57 -> 0.0010116971 | O68: =O55/O$57 -> 0.14876416
A69: Rural à habitat très dispersé | B69: =B56/B$57 -> 0.60240817 | C69: =C56/C$57 -> 0.38936096 | D69: =D56/D$57 -> 0.22712067 | E69: =E56/E$57 -> 0.042327921 | F69: =F56/F$57 -> 0.0088258753 | G69: =G56/G$57 -> 0.0020904293 | H69: =H56/H$57 -> 0.0020735259 | I69: - | J69: - | K69: - | L69: - | M69: =M56/M$57 -> 0.049747723 | N69: - | O69: =O56/O$57 -> 0.024476076
A70: Ensemble des communes rurales et urbaines | B70: =B57/B$57 -> 1 | C70: =C57/C$57 -> 1 | D70: =D57/D$57 -> 1 | E70: =E57/E$57 -> 1 | F70: =F57/F$57 -> 1 | G70: =G57/G$57 -> 1 | H70: =H57/H$57 -> 1 | I70: =I57/I$57 -> 1 | ... O70: =O57/O$57 -> 1
A71: Lecture : il y a 213 108 habitants dans les communes rurales de moins de 100 habitants. Ces habitants représentent 100,0 % de la population des communes de moins de 100 habitants.
A72: Source : DGFIP, comptes de gestion. INSEE, Recensement de la population (population totale en 2024 - année de référence 2021) ; calculs DGCL. Grille de densité de l'Insee au 1er janvier 2024 définissant le rural.
A74: Communes rurales et urbaines : la grille communale de densité permet de classer les communes en fonction du nombre d’habitants et de la répartition de ces habitants sur leur territoire. Plus la population est concentrée et nombreuse, plus la commune est considérée comme dense. L’appartenance à un niveau de la grille n’est pas simplement liée à la densité moyenne de population calculée sur l’ensemble de la commune (incluant les surfaces non habitées comme les forêts, la montagne et les champs), elle prend en compte la présence au sein de la commune de zones concentrant un grand nombre d’habitants sur une faible surface. Plus précisément, la définition retenue par l’Union européenne s’appuie sur le découpage du territoire en carreaux de 1 kilomètre de côté et sur l’agrégation de carreaux de densité équivalente, définissant des « taches » ou « clusters ». Chaque commune est ensuite affectée dans une catégorie en fonction de la part de la population communale comprise dans les différents types de cluster. Les données de population sont issues des fichiers démographiques sur les logements et les individus (Fideli 2021). Dans son premier niveau, à 3 catégories, la grille communale permet ainsi de distinguer trois types de communes : les communes densément peuplées, les communes de densité intermédiaire, les communes rurales. Les communes densément peuplées et les communes de densité intermédiaire constituent l'espace urbain et sont appelées « communes urbaines ». Une grille détaillée, à 7 niveaux, a été définie suite à des travaux récents au niveau international. Il s’agit d’une subdivision de la grille à 3 catégories ; en particulier, les définitions de l’urbain et du rural sont inchangées. Les communes denses, ou densément peuplées, restent aussi identiques. Elles correspondent aux communes des « cities » européennes, dénommées « grands centres urbains » dans la grille à 7 niveaux. Au sein des communes de densité intermédiaire, la grille à 7 niveaux permet de différencier : les « centres urbains intermédiaires », les « ceintures urbaines », les « petites villes ». Au sein des communes rurales, la grille distingue : les « bourgs ruraux », le « rural à habitat dispersé », le « rural à habitat très dispersé ».
A76: Population totale et population « DGF » : Dans le recensement de la population, la « population totale » est égale à la « population municipale » augmentée de la « population comptée à part », c’est-à-dire les personnes recensées sur d’autres communes mais qui ont conservé un lien avec une résidence sur la commune (par exemple les étudiants). La somme de toutes les populations totales dépasse donc la population réelle, du fait des personnes comptées à part, comptées une fois dans leur commune de résidence et une fois dans leur commune de rattachement occasionnel. Pour le calcul des dotations on inclut ces habitants comptés à part ; on considère en effet que ces personnes pèsent sur le budget de fonctionnement de la commune même si elles résident habituellement dans une autre commune. Pour tenir compte des conditions particulières de certaines communes, qui pèsent sur leur fonctionnement, cette population totale est, en plus, majorée en fonction de deux critères particuliers. Il ne s’agit plus d’habitants « réels » recensés, mais d’une attribution forfaitaire exprimée en nombre d’habitants par commodité de calcul. - majoration en fonction du nombre de résidences secondaires : la population totale issue du recensement est forfaitairement majorée d’un habitant par résidence secondaire. Elles sont particulièrement nombreuses dans les zones touristiques. Cela aboutit à majorer la population nationale à ce titre d’un forfait de plus de 3 millions « d’habitants ». - majoration pour places de caravanes dans les aires d’accueil des gens du voyage. Selon la même logique, la population totale est majorée d’un habitant par place de caravane située sur une aire d’accueil des gens du voyage. La majoration de population est portée à deux habitants par place de caravane pour les communes éligibles l’année précédente à la dotation de solidarité urbaine (DSU) ou à la première fraction (bourg-centre) de la dotation de solidarité rurale (DSR). Les caravanes de campings dans le cadre de l’hôtellerie de plein air ne sont pas concernées. Une fois effectuées ces deux majorations de la population totale, on obtient une population forfaitaire, dite « population DGF », car utilisée pour calculer la principale dotation que lui verse l’État pour son fonctionnement, la dotation globale de fonctionnement (DGF).

Sheet T 2.1
A1: T 2.1.a - Comptes des communes par strate de population en 2024
O2: En millions d'euros
A3: Exercice 2024 | B3: Moins | C3: De 100 | D3: De 200 | E3: De 500 | F3: De 2 000 | G3: De 3 500 | H3: De 5 000 | I3: De 10 000 | J3: De 20 000 | K3: De 50 000 | L3: 100000 | M3: Communes | N3: Communes | O3: Ensemble
A4: Opérations réelles | B4: de 100 | C4: à moins de | D4: à moins de | E4: à moins de | F4: à moins de | G4: à moins de | H4: à moins de | I4: à moins de | J4: à moins de | K4: à moins de | L4: habitants | M4: de moins | N4: de 10 000 hab. | O4: des
A5: Hors gestion active de la dette | B5: habitants | C5: 200 hab. | D5: 500 hab. | E5: 2 000 hab. | F5: 3 500 hab. | G5: 5 000 hab. | H5: 10 000 hab. | I5: 20 000 hab. | J5: 50 000 hab. | K5: 100 000 hab. | L5: et plus | M5: de 10 000 hab. | N5: et plus | O5: communes
A7: DÉPENSES DE FONCTIONNEMENT (1) | B7: 236.14415 | C7: 657.05893 | D7: 2230.9703 | E7: 8411.4372 | F7: 5268.2178 | G7: 4143.8454 | H7: 9454.0355 | I7: 9446.0116 | J7: 15316.956 | K7: 9242.6118 | L7: 18394.633 | M7: 30401.709 | N7: 52400.213 | O7: 82801.922
A8: Achats et charges externes | B8: 95.217149 | C8: 253.84986 | D8: 809.33058 | E8: 2912.2829 | F8: 1750.3841 | G8: 1290.4513 | H8: 2710.278 | I8: 2465.7321 | J8: 3800.826 | K8: 2098.2897 | L8: 3394.4908 | M8: 9821.7939 | N8: 11759.339 | O8: 21581.133
A9: Frais de personnel | B9: 53.954731 | C9: 183.70054 | D9: 777.62825 | E9: 3725.8857 | F9: 2664.1262 | G9: 2224.9285 | H9: 5375.3304 | I9: 5610.6607 | J9: 9307.8862 | K9: 5582.0481 | L9: 9156.2487 | M9: 15005.554 | N9: 29656.844 | O9: 44662.398
A10: Charges financières | B10: 3.4415664 | C10: 10.967835 | D10: 38.639138 | E10: 161.93275 | F10: 102.66174 | G10: 75.225389 | H10: 171.04714 | I10: 163.33077 | J10: 301.3237 | K10: 240.00432 | L10: 447.12192 | M10: 563.91557 | N10: 1151.7807 | O10: 1715.6963
A11: Dépenses d'intervention | B11: 29.52835 | C11: 91.1942 | D11: 342.0985 | E11: 901.31633 | F11: 466.33267 | G11: 365.32943 | H11: 874.18558 | I11: 942.09891 | J11: 1538.2989 | K11: 1074.4666 | L11: 4963.1689 | M11: 3069.9851 | N11: 8518.0333 | O11: 11588.018
A12: Autres dépenses de fonctionnement | B12: 54.002351 | C12: 117.34649 | D12: 263.27382 | E12: 710.01948 | F12: 284.71313 | G12: 187.91079 | H12: 323.19432 | I12: 264.18904 | J12: 368.62129 | K12: 247.80304 | L12: 433.60314 | M12: 1940.4604 | N12: 1314.2165 | O12: 3254.6769
A13: RECETTES DE FONCTIONNEMENT (2) | B13: 327.33664 | C13: 879.40834 | D13: 2876.9452 | E13: 10524.91 | F13: 6502.965 | G13: 5057.2184 | H13: 11267.436 | I13: 10972.136 | J13: 17591.779 | K13: 10685.609 | L13: 20325.466 | M13: 37436.22 | N13: 59574.99 | O13: 97011.209
A14: Impôts et taxes | B14: 139.84497 | C14: 406.35498 | D14: 1463.9781 | E14: 6048.5737 | F14: 4077.9159 | G14: 3287.0285 | H14: 7537.5227 | I14: 7453.0177 | J14: 12106.778 | K14: 7342.6629 | L14: 14740.481 | M14: 22961.219 | N14: 41642.939 | O14: 64604.158
A15: - Impôts locaux | B15: 96.505899 | C15: 312.26567 | D15: 1210.9477 | E15: 5351.1737 | F15: 3676.6251 | G15: 2922.2429 | H15: 6653.7597 | I15: 6566.59 | J15: 10998.451 | K15: 6532.6312 | L15: 10477.738 | M15: 20223.521 | N15: 34575.41 | O15: 54798.931
A16: (dont : fiscalité reversée) | B16: 15.667474 | C16: 38.275645 | D16: 142.92086 | E16: 865.34718 | F16: 690.43938 | G16: 582.49506 | H16: 1410.796 | I16: 1456.8664 | J16: 2230.5912 | K16: 1474.5025 | L16: 2032.1082 | M16: 3745.9416 | N16: 7194.0683 | O16: 10940.01
A17: - Autres impôts et taxes | B17: 43.339069 | C17: 94.089303 | D17: 253.03041 | E17: 697.40005 | F17: 401.29086 | G17: 364.78559 | H17: 883.76301 | I17: 886.4277 | J17: 1108.3268 | K17: 810.03173 | L17: 4262.7424 | M17: 2737.6983 | N17: 7067.5286 | O17: 9805.2269
A18: Concours de l'État | B18: 109.89019 | C18: 267.36099 | D18: 795.64879 | E18: 2507.7392 | F18: 1309.7665 | G18: 923.54249 | H18: 1918.4624 | I18: 1810.5485 | J18: 2743.5581 | K18: 1676.9876 | L18: 2168.5447 | M18: 7832.4106 | N18: 8399.639 | O18: 16232.05
... A44: Dette au 31 décembre (12) | B44: 137.78751 | C44: 460.62662 | D44: 1564.9891 | E44: 6342.5843 | F44: 3924.3565 | G44: 2989.5653 | H44: 6507.3161 | I44: 6068.3689 | J44: 10808.237 | K44: 8112.9677 | L44: 19615.128 | M44: 21927.225 | N44: 44604.702 | O44: 66531.928
A45: Ratios
A46: Taux d'épargne brute = (3) / (2) | B46: 0.27858932 | C46: 0.25283978 | D46: 0.224535 | E46: 0.20080673 | F46: 0.1898745 | G46: 0.18060779 | H46: 0.16094173 | I46: 0.13909091 | J46: 0.1293117 | K46: 0.13504117 | L46: 0.094995741 | M46: 0.18790654 | N46: 0.1204327 | O46: 0.14647057
A47: Taux d'épargne nette = [(3)-(8)] / (2) | B47: 0.19914299 | C47: 0.16730207 | D47: 0.14113036 | E47: 0.12064206 | F47: 0.12104443 | G47: 0.11762612 | H47: 0.097989305 | I47: 0.08101283 | J47: 0.066003645 | K47: 0.058143412 | L47: 0.035164821 | M47: 0.11684357 | N47: 0.056836677 | O47: 0.079993087
A48: Taux d'endettement = (12) / (2) | B48: 0.42093518 | C48: 0.52379151 | D48: 0.543976 | E48: 0.60262599 | F48: 0.60347187 | G48: 0.59114816 | H48: 0.57753299 | I48: 0.55307088 | J48: 0.61439138 | K48: 0.75924243 | L48: 0.96505183 | M48: 0.58572221 | N48: 0.74871523 | O48: 0.68581691
A49: Délai de désendettement = (12) / (3) | B49: 1.5109523 | C49: 2.0716341 | D49: 2.422678 | E49: 3.0010249 | F49: 3.1782671 | G49: 3.2731044 | H49: 3.5884603 | I49: 3.9763264 | J49: 4.7512436 | K49: 5.6223035 | L49: 10.158896 | M49: 3.1170933 | N49: 6.2168764 | O49: 4.6822846
A50: R7 : Dépenses de personnel / dépenses réelles de fonctionnement (DRF) | B50: 0.22848219 | C50: 0.27958001 | D50: 0.34856056 | E50: 0.44295471 | F50: 0.5056978 | G50: 0.53692363 | H50: 0.56857523 | I50: 0.5939714 | J50: 0.60768511 | K50: 0.60394705 | L50: 0.49776739 | M50: 0.49357601 | N50: 0.565968 | O50: 0.53938842
A51: R9 : Marge d'autofinancement courant (MAC)=(DRF+Remboursement de dette) / RRF | B51: 0.80035742 | C51: 0.83239488 | D51: 0.85831564 | E51: 0.87831883 | F51: 0.87679475 | G51: 0.87913537 | H51: 0.898259 | I51: 0.91597124 | J51: 0.93185245 | K51: 0.94033988 | L51: 0.96396023 | M51: 0.88086822 | N51: 0.94140425 | O51: 0.91804365
A52: R10 : Dépenses d'équipement brutes (a) / RRF (Taux d'équipement) | B52: 0.46193054 | C52: 0.44625725 | D52: 0.41192113 | E52: 0.39868697 | F52: 0.3754264 | G52: 0.345373 | H52: 0.31807931 | I52: 0.26707508 | J52: 0.2507679 | K52: 0.25324962 | L52: 0.19474769 | M52: 0.36587075 | N52: 0.23510372 | O52: 0.28556617
A53: (a) C'est-à-dire y compris les travaux en régie, les travaux effectués d'office pour le compte de tiers, les opérations di'nvestissement sur établissements d'enseignement et les opérations sous mandat.
A54: Champ : France entière (France métropolitaine et DOM).
A55: Lecture : Les dépenses de fonctionnement des communes de moins de 100 habitants se montent à 236 M€.
A56: Source : DGFiP-Comptes de gestion ; budgets principaux - opérations réelles. Calculs DGCL. Montants calculés hors gestion active de la dette. INSEE, Recensement de la population (population totale en 2024 - année de référence 2021)
A58: T 2.1.b - Structure des dépenses et recettes des communes par strate de population en 2024
O59: En %
A60: Exercice 2024 | B60: Moins | C60: De 100 | D60: De 200 | E60: De 500 | F60: De 2 000 | G60: De 3 500 | H60: De 5 000 | I60: De 10 000 | J60: De 20 000 | K60: De 50 000 | L60: 100000 | M60: Communes | N60: Communes | O60: Ensemble
A61: Opérations réelles | B61: de 100 | C61: à moins de | D61: à moins de | E61: à moins de | F61: à moins de | G61: à moins de | H61: à moins de | I61: à moins de | J61: à moins de | K61: à moins de | L61: habitants | M61: de moins | N61: de 10 000 hab. | O61: des
A62: Hors gestion active de la dette | B62: habitants | C62: 200 hab. | D62: 500 hab. | E62: 2 000 hab. | F62: 3 500 hab. | G62: 5 000 hab. | H62: 10 000 hab. | I62: 20 000 hab. | J62: 50 000 hab. | K62: 100 000 hab. | L62: et plus | M62: de 10 000 hab. | N62: et plus | O62: communes
A63: Structure de fonctionnement
A64: DÉPENSES DE FONCTIONNEMENT (1) | B64: =B7/B$7 -> 1 | C64: =C7/C$7 -> 1 | D64: =D7/D$7 -> 1 | E64: =E7/E$7 -> 1 | F64: =F7/F$7 -> 1 | G64: =G7/G$7 -> 1 | H64: =H7/H$7 -> 1 | I64: =I7/I$7 -> 1 | ... O64: =O7/O$7 -> 1
A65: Achats et charges externes | B65: =B8/B$7 -> 0.40321621 | C65: =C8/C$7 -> 0.38634261 | D65: =D8/D$7 -> 0.36277067 | E65: =E8/E$7 -> 0.34622894 | F65: =F8/F$7 -> 0.33225356 | G65: =G8/G$7 -> 0.31141395 | H65: =H8/H$7 -> 0.28667948 | I65: =I8/I$7 -> 0.26103421 | ... O65: =O8/O$7 -> 0.26063565
A66: Frais de personnel | B66: =B9/B$7 -> 0.22848219 | C66: =C9/C$7 -> 0.27958001 | D66: =D9/D$7 -> 0.34856056 | E66: =E9/E$7 -> 0.4429547 | F66: =F9/F$7 -> 0.5056978 | G66: =G9/G$7 -> 0.53692363 | H66: =H9/H$7 -> 0.56857523 | I66: =I9/I$7 -> 0.5939714 | ... O66: =O9/O$7 -> 0.53938842
A67: Charges financières | B67: =B10/B$7 -> 0.014574007 | C67: =C10/C$7 -> 0.016692316 | D67: =D10/D$7 -> 0.017319432 | E67: =E10/E$7 -> 0.019251497 | F67: =F10/F$7 -> 0.019486996 | G67: =G10/G$7 -> 0.018153522 | H67: =H10/H$7 -> 0.018092501 | I67: =I10/I$7 -> 0.017290978 | ... O67: =O10/O$7 -> 0.020720489
A68: Dépenses d'intervention | B68: =B11/B$7 -> 0.12504375 | C68: =C11/C$7 -> 0.13879151 | D68: =D11/D$7 -> 0.15334068 | E68: =E11/E$7 -> 0.10715367 | F68: =F11/F$7 -> 0.088518107 | G68: =G11/G$7 -> 0.088161937 | H68: =H11/H$7 -> 0.092466924 | I68: =I11/I$7 -> 0.0997351 | ... O68: =O11/O$7 -> 0.13994866
A69: Autres dépenses de fonctionnement | B69: =B12/B$7 -> 0.22868384 | C69: =C12/C$7 -> 0.17859356 | D69: =D12/D$7 -> 0.11800866 | E69: =E12/E$7 -> 0.084411197 | F69: =F12/F$7 -> 0.054043539 | G69: =G12/G$7 -> 0.045346959 | H69: =H12/H$7 -> 0.034185858 | I69: =I12/I$7 -> 0.027968317 | ... O69: =O12/O$7 -> 0.039306779
A70: RECETTES DE FONCTIONNEMENT (2) | B70: =B13/B$13 -> 1 | C70: =C13/C$13 -> 1 | D70: =D13/D$13 -> 1 | E70: =E13/E$13 -> 1 | F70: =F13/F$13 -> 1 | G70: =G13/G$13 -> 1 | H70: =H13/H$13 -> 1 | I70: =I13/I$13 -> 1 | ... O70: =O13/O$13 -> 1
A71: Impôts et taxes | B71: =B14/B$13 -> 0.42722064 | C71: =C14/C$13 -> 0.46207769 | D71: =D14/D$13 -> 0.50886548 | E71: =E14/E$13 -> 0.57469126 | F71: =F14/F$13 -> 0.62708563 | G71: =G14/G$13 -> 0.64996767 | H71: =H14/H$13 -> 0.6689652 | I71: =I14/I$13 -> 0.67926771 | ... O71: =O14/O$13 -> 0.66594529
A72: - Impôts locaux | B72: =B15/B$13 -> 0.29482156 | C72: =C15/C$13 -> 0.35508609 | D72: =D15/D$13 -> 0.42091441 | E72: =E15/E$13 -> 0.50842941 | F72: =F15/F$13 -> 0.56537672 | G72: =G15/G$13 -> 0.57783601 | H72: =H15/H$13 -> 0.59053006 | I72: =I15/I$13 -> 0.59847873 | ... O72: =O15/O$13 -> 0.56487215
A73: (dont : fiscalité reversée) | B73: =B16/B$13 -> 0.04786349 | C73: =C16/C$13 -> 0.043524314 | D73: =D16/D$13 -> 0.049677993 | E73: =E16/E$13 -> 0.082218964 | F73: =F16/F$13 -> 0.10617301 | G73: =G16/G$13 -> 0.11518092 | H73: =H16/H$13 -> 0.12521003 | I73: =I16/I$13 -> 0.13277874 | ... O73: =O16/O$13 -> 0.11277057
A74: - Autres impôts et taxes | B74: =B17/B$13 -> 0.13239908 | C74: =C17/C$13 -> 0.1069916 | D74: =D17/D$13 -> 0.087951072 | E74: =E17/E$13 -> 0.066261855 | F74: =F17/F$13 -> 0.061708906 | G74: =G17/G$13 -> 0.072131665 | H74: =H17/H$13 -> 0.078435148 | I74: =I17/I$13 -> 0.080788982 | ... O74: =O17/O$13 -> 0.10107313
A75: Concours de l'État | B75: =B18/B$13 -> 0.33571002 | C75: =C18/C$13 -> 0.30402371 | D75: =D18/D$13 -> 0.27656029 | E75: =E18/E$13 -> 0.23826705 | F75: =F18/F$13 -> 0.20141067 | G75: =G18/G$13 -> 0.18261867 | H75: =H18/H$13 -> 0.1702661 | I75: =I18/I$13 -> 0.16501331 | ... O75: =O18/O$13 -> 0.16732138
A76: - DGF | B76: =B19/B$13 -> 0.17901284 | C76: =C19/C$13 -> 0.19319434 | D76: =D19/D$13 -> 0.18615173 | E76: =E19/E$13 -> 0.17202945 | F76: =F19/F$13 -> 0.14959581 | G76: =G19/G$13 -> 0.13405728 | H76: =H19/H$13 -> 0.12351604 | I76: =I19/I$13 -> 0.12491343 | ... O76: =O19/O$13 -> 0.1283406
A77: - Autres dotations | B77: =B20/B$13 -> 0.070801293 | C77: =C20/C$13 -> 0.045757242 | D77: =D20/D$13 -> 0.021762276 | E77: =E20/E$13 -> 0.0060442132 | F77: =F20/F$13 -> 0.0030190218 | G77: =G20/G$13 -> 0.0024548332 | H77: =H20/H$13 -> 0.0020484069 | I77: =I20/I$13 -> 0.0016777333 | ... O77: =O20/O$13 -> 0.0044499935
A78: - Péréquation et compensations fiscales | B78: =B21/B$13 -> 0.085895893 | C78: =C21/C$13 -> 0.065072127 | D78: =D21/D$13 -> 0.068646281 | E78: =E21/E$13 -> 0.060193383 | F78: =F21/F$13 -> 0.048795832 | G78: =G21/G$13 -> 0.046106556 | H78: =H21/H$13 -> 0.044701653 | I78: =I21/I$13 -> 0.038422147 | ... O78: =O21/O$13 -> 0.034530791
A79: Subventions reçues et participations | B79: =B22/B$13 -> 0.020879479 | C79: =C22/C$13 -> 0.021170593 | D79: =D22/D$13 -> 0.022339896 | E79: =E22/E$13 -> 0.028287005 | F79: =F22/F$13 -> 0.03565569 | G79: =G22/G$13 -> 0.039792494 | H79: =H22/H$13 -> 0.047382258 | I79: =I22/I$13 -> 0.049918564 | ... O79: =O22/O$13 -> 0.042733704
A80: Ventes de biens et services | B80: =B23/B$13 -> 0.098391309 | C80: =C23/C$13 -> 0.092224019 | D80: =D23/D$13 -> 0.083726407 | E80: =E23/E$13 -> 0.082291447 | F80: =F23/F$13 -> 0.077780001 | G80: =G23/G$13 -> 0.081841865 | H80: =H23/H$13 -> 0.075754112 | I80: =I23/I$13 -> 0.074246979 | ... O80: =O23/O$13 -> 0.079256793
A81: Autres recettes de fonctionnement | B81: =B24/B$13 -> 0.11779855 | C81: =C24/C$13 -> 0.12050398 | D81: =D24/D$13 -> 0.10850793 | E81: =E24/E$13 -> 0.076463238 | F81: =F24/F$13 -> 0.058068014 | G81: =G24/G$13 -> 0.045779302 | H81: =H24/H$13 -> 0.037632322 | I81: =I24/I$13 -> 0.031553432 | ... O81: =O24/O$13 -> 0.044742833
A82: Structure d'investissement
A83: DÉPENSES D'INVESTISSEMENT hors remboursements (4) | B83: =B27/B$27 -> 1 | C83: =C27/C$27 -> 1 | D83: =D27/D$27 -> 1 | E83: =E27/E$27 -> 1 | F83: =F27/F$27 -> 1 | G83: =G27/G$27 -> 1 | H83: =H27/H$27 -> 1 | I83: =I27/I$27 -> 1 | ... O83: =O27/O$27 -> 1
A84: Dépenses d'équipement | B84: =B28/B$27 -> 0.95516332 | C84: =C28/C$27 -> 0.9494582 | D84: =D28/D$27 -> 0.94000067 | E84: =E28/E$27 -> 0.94590545 | F84: =F28/F$27 -> 0.94120398 | G84: =G28/G$27 -> 0.9397122 | H84: =H28/H$27 -> 0.93964706 | I84: =I28/I$27 -> 0.9299422 | ... O84: =O28/O$27 -> 0.91043911
A85: Subventions d'équipement versées | B85: =B29/B$27 -> 0.028313016 | C85: =C29/C$27 -> 0.0345435 | D85: =D29/D$27 -> 0.034496788 | E85: =E29/E$27 -> 0.030064399 | F85: =F29/F$27 -> 0.031212511 | G85: =G29/G$27 -> 0.035251432 | H85: =H29/H$27 -> 0.037521365 | I85: =I29/I$27 -> 0.040599683 | ... O85: =O29/O$27 -> 0.056605182
A86: Autres depenses d'investissement | B86: =B30/B$27 -> 0.016523668 | C86: =C30/C$27 -> 0.015998297 | D86: =D30/D$27 -> 0.025502541 | E86: =E30/E$27 -> 0.024030153 | F86: =F30/F$27 -> 0.027583513 | G86: =G30/G$27 -> 0.025036373 | H86: =H30/H$27 -> 0.022831571 | I86: =I30/I$27 -> 0.029458113 | ... O86: =O30/O$27 -> 0.032955706
A87: RECETTES D'INVESTISSEMENT hors emprunts (5) | B87: =B31/B$31 -> 1 | C87: =C31/C$31 -> 1 | D87: =D31/D$31 -> 1 | E87: =E31/E$31 -> 1 | F87: =F31/F$31 -> 1 | G87: =G31/G$31 -> 1 | H87: =H31/H$31 -> 1 | I87: =I31/I$31 -> 1 | ... O87: =O31/O$31 -> 1
A88: FCTVA | B88: =B32/B$31 -> 0.22422613 | C88: =C32/C$31 -> 0.21292029 | D88: =D32/D$31 -> 0.21015329 | E88: =E32/E$31 -> 0.21977504 | F88: =F32/F$31 -> 0.21718226 | G88: =G32/G$31 -> 0.24380387 | H88: =H32/H$31 -> 0.24317365 | I88: =I32/I$31 -> 0.24893691 | ... O88: =O32/O$31 -> 0.24243793
A89: Dotations et Subventions d'équipement | B89: =B33/B$31 -> 0.7168262 | C89: =C33/C$31 -> 0.70039565 | D89: =D33/D$31 -> 0.67461508 | E89: =E33/E$31 -> 0.65074178 | F89: =F33/F$31 -> 0.57262418 | G89: =G33/G$31 -> 0.58235042 | H89: =H33/H$31 -> 0.58626545 | I89: =I33/I$31 -> 0.59174549 | ... O89: =O33/O$31 -> 0.5713263
A90: Autres recettes d'investissement | B90: =B34/B$31 -> 0.058947673 | C90: =C34/C$31 -> 0.086684056 | D90: =D34/D$31 -> 0.11523163 | E90: =E34/E$31 -> 0.12948317 | F90: =F34/F$31 -> 0.21019356 | G90: =G34/G$31 -> 0.17384571 | H90: =H34/H$31 -> 0.1705609 | I90: =I34/I$31 -> 0.1593176 | ... O90: =O34/O$31 -> 0.18623577
A91: Champ : France entière (France métropolitaine et DOM).
A92: Lecture : Les achats et charges externes des communes de moins de 100 habitants représentent 40,3 % de leurs dépenses de fonctionnement.
A93: Source : DGFiP-Comptes de gestion ; budgets principaux - opérations réelles. Calculs DGCL. Montants calculés hors gestion active de la dette.
A96: Liste des 11 ratios
A97: Pour les communes de 3 500 habitants et plus, les données synthétiques sur la situation financière de la collectivité, prévues par l’article L. 2313-1 du code général des collectivités territoriales (CGCT), comprennent 11 ratios définis à l’article R. 2313-1. Ces ratios sont aussi calculés pour les groupements à fiscalité propre, les départements (articles L. 3313-1 et R. 3313-1) et les régions (articles L. 4313-2 et R. 4313-1). Toutefois, le ratio 8, qui correspond au coefficient de mobilisation du potentiel fiscal, n’est plus calculé.
A99: À noter : pour la détermination des montants de dépenses ou recettes réelles de fonctionnement à retenir pour le calcul des ratios, les reversements de fiscalité liés au FNGIR et aux différents fonds de péréquation horizontale sont comptabilisés en moindres recettes.
A101: • Ratio 1 = dépenses réelles de fonctionnement (DRF) / population : montant total des dépenses de fonctionnement en mouvement réels. Les dépenses liées à des travaux en régie sont exclues des DRF.
A103: • Ratio 2 = produit des impositions directes / population : (recettes hors fiscalité reversée).
A105: • Ratio 2 bis = produit net des impositions directes / population : en plus des impositions directes, ce ratio intègre les prélèvements pour reversements de fiscalité et la fiscalité reversée aux communes par les groupements à fiscalité propre.
A107: • Ratio 3 = recettes réelles de fonctionnement (RRF) / population : montant total des recettes de fonctionnement en mouvements réels. Ressources dont dispose la collectivité, à comparer aux dépenses de fonctionnement dans leur rythme de croissance.
A109: • Ratio 4 = dépenses d’équipement «brutes»/ population : dépenses des comptes 20 (immobilisations incorporelles) sauf 204 (subventions d’équipement versées), 21 (immobilisations corporelles), 23 (immobilisations en cours sauf 2324 en M57, diminué des crédits des comptes 236, 237 et 238), 454 (travaux effectués d’office pour le compte de tiers), 456 (opérations d’investissement sur établissement d’enseignement) et 458 (opérations d’investissement sous mandat). Les travaux en régie (crédit du compte 72 en opérations budgétaires) sont ajoutés au calcul. Pour les départements et les régions, on rajoute le débit du compte correspondant aux opérations d’investissement sur établissements publics locaux d’enseignement (compte 455 ou 456 selon les nomenclatures).
A111: • Ratio 5 = dette / population : capital restant dû au 31 décembre de l’exercice. Endettement d’une collectivité à compléter avec un ratio de capacité de désendettement (dette / épargne brute) et le taux d’endettement (ratio 11).
... A123: Les ratios 7 à 11 sont exprimés en pourcentage.

Sheet T 2.2
A1: T 2.2 - Dépenses et recettes par habitant (a) des communes en 2024
O2: En €/habitant
A3: Exercice 2024 | B3: Moins | C3: De 100 | D3: De 200 | E3: De 500 | F3: De 2 000 | G3: De 3 500 | H3: De 5 000 | I3: De 10 000 | J3: De 20 000 | K3: De 50 000 | L3: 100000 | M3: Communes | N3: Communes | O3: Ensemble
A4: Opérations réelles | B4: de 100 | C4: à moins de | D4: à moins de | E4: à moins de | F4: à moins de | G4: à moins de | H4: à moins de | I4: à moins de | J4: à moins de | K4: à moins de | L4: habitants | M4: de moins | N4: de 10 000 hab. | O4: des
A5: Hors gestion active de la dette | B5: habitants | C5: 200 hab. | D5: 500 hab. | E5: 2 000 hab. | F5: 3 500 hab. | G5: 5 000 hab. | H5: 10 000 hab. | I5: 20 000 hab. | J5: 50 000 hab. | K5: 100 000 hab. | L5: et plus | M5: de 10 000 hab. | N5: et plus | O5: communes
A7: DÉPENSES DE FONCTIONNEMENT (1) | B7: 1108.0961 | C7: 830.71594 | D7: 723.82328 | E7: 757.29401 | F7: 874.85198 | G7: 999.2405 | H7: 1108.4014 | I7: 1251.8403 | J7: 1397.6981 | K7: 1506.6052 | L7: 1776.8179 | M7: 897.02359 | N7: 1497.5041 | O7: 1202.0581
A8: Achats et charges externes | B8: 446.80232 | C8: 320.94096 | D8: 262.58186 | E8: 262.1971 | F8: 290.67268 | G8: 311.17744 | H8: 317.75594 | I8: 326.77315 | J8: 346.8318 | K8: 342.03474 | L8: 327.88867 | M8: 289.79887 | N8: 336.06081 | O8: 313.2992
A9: Frais de personnel | B9: 253.18022 | C9: 232.25157 | D9: 252.29625 | E9: 335.44694 | F9: 442.41073 | G9: 536.51583 | H9: 630.20958 | I9: 743.55735 | J9: 849.36035 | K9: 909.90978 | L9: 884.44201 | M9: 442.74932 | N9: 847.5394 | O9: 648.37623
A10: Charges financières | B10: 16.1494 | C10: 13.866573 | D10: 12.536208 | E10: 14.579043 | F10: 17.048237 | G10: 18.139735 | H10: 20.053753 | I10: 21.645543 | J10: 27.496298 | K10: 39.122249 | L10: 43.189457 | M10: 16.638721 | N10: 32.915827 | O10: 24.907231
A11: Dépenses d'intervention | B11: 138.5605 | C11: 115.29632 | D11: 110.99155 | E11: 81.146829 | F11: 77.440242 | G11: 88.094978 | H11: 102.49047 | I11: 124.85242 | J11: 140.37238 | K11: 175.14497 | L11: 479.41413 | M11: 90.582046 | N11: 243.43011 | O11: 168.22643
A12: Autres dépenses de fonctionnement | B12: 253.40368 | C12: 148.36052 | D12: 85.417417 | E12: 63.924093 | F12: 47.280097 | G12: 45.312518 | H12: 37.891653 | I12: 35.011867 | J12: 33.637316 | K12: 40.393491 | L12: 41.883619 | M12: 57.254634 | N12: 37.557951 | O12: 47.249033
A13: RECETTES DE FONCTIONNEMENT (2) | B13: 1536.0129 | C13: 1111.8311 | D13: 933.40548 | E13: 947.57305 | F13: 1079.8969 | G13: 1219.4899 | H13: 1321.0065 | I13: 1454.0912 | J13: 1605.2796 | K13: 1741.823 | L13: 1963.3254 | M13: 1104.5817 | N13: 1702.5464 | O13: 1408.3382
A14: Impôts et taxes | B14: 656.21642 | C14: 513.75233 | D14: 474.97783 | E14: 544.56195 | F14: 677.1878 | G14: 792.629 | H14: 883.70736 | I14: 987.71721 | J14: 1104.7639 | K14: 1196.9013 | L14: 1423.8473 | M14: 677.48675 | N14: 1190.0805 | O14: 937.8762
A15: - Impôts locaux | B15: 452.84973 | C15: 394.79575 | D15: 392.88382 | E15: 481.774 | F15: 610.54855 | G15: 704.66516 | H15: 780.09402 | I15: 870.24266 | J15: 1003.6272 | K15: 1064.8609 | L15: 1012.0905 | M15: 596.70905 | N15: 988.10322 | O15: 795.53104
A16: (dont : fiscalité reversée) | B16: 73.518939 | C16: 48.391684 | D16: 46.369711 | E16: 77.908474 | F16: 114.6559 | G16: 140.46196 | H16: 165.40325 | I16: 193.0724 | J16: 203.54522 | K16: 240.3534 | L16: 196.29019 | M16: 110.52661 | N16: 205.59357 | O16: 158.81911
A17: - Autres impôts et taxes | B17: 203.36669 | C17: 118.95658 | D17: 82.094013 | E17: 62.787948 | F17: 66.639254 | G17: 87.963836 | H17: 103.61334 | I17: 117.47455 | J17: 101.13669 | K17: 132.04039 | L17: 411.75688 | M17: 80.777694 | N17: 201.97729 | O17: 142.34516
A18: Concours de l'État | B18: 515.65493 | C18: 338.02301 | D18: 258.14289 | E18: 225.77543 | F18: 217.50275 | G18: 222.70162 | H18: 224.92262 | I18: 239.94441 | J18: 250.35431 | K18: 273.35978 | L18: 209.4692 | M18: 231.10073 | N18: 240.04662 | O18: 235.6451
... A44: Dette au 31 décembre (12) | B44: 646.56187 | C44: 582.36767 | D44: 507.75018 | E44: 571.03215 | F44: 651.68738 | G44: 720.89919 | H44: 762.92482 | I44: 804.2155 | J44: 986.26993 | K44: 1322.466 | L44: 1894.7108 | M44: 646.97805 | N44: 1274.7224 | O44: 965.86216
A45: Ratios (voir définitions en annexe 3)
A46: R1 : Dépenses réelles de fonctionnement (DRF) (b) / habitant | B46: 1107.3287 | C46: 830.379 | D46: 723.30617 | E46: 756.30938 | F46: 872.51853 | G46: 995.29116 | H46: 1103.4454 | I46: 1247.4549 | J46: 1394.2566 | K46: 1503.9634 | L46: 1775.1001 | M46: 894.49607 | N46: 1494.5092 | O46: 1199.2932
A47: R2 : Produit des impositions directes hors fiscalité reversée / habitant | B47: 439.65874 | C47: 374.84659 | D47: 376.48396 | E47: 419.33634 | F47: 495.05395 | G47: 562.32375 | H47: 613.43065 | I47: 674.81097 | J47: 796.75594 | K47: 830.04873 | L47: 898.25901 | M47: 494.32517 | N47: 806.32678 | O47: 652.81701
A48: R2 bis : Produit des impositions directes y compris fiscalité reversée / habitant | B48: 452.84973 | C48: 394.79575 | D48: 392.88382 | E48: 481.774 | F48: 610.54855 | G48: 704.66516 | H48: 780.09402 | I48: 870.24266 | J48: 1003.6272 | K48: 1064.8609 | L48: 1012.0905 | M48: 596.70905 | N48: 988.10322 | O48: 795.53104
A49: R3 : Recettes réelles de fonctionnement (RRF) / habitant | B49: 1536.0129 | C49: 1111.8311 | D49: 933.40548 | E49: 947.57305 | F49: 1079.8969 | G49: 1219.4899 | H49: 1321.0065 | I49: 1454.0912 | J49: 1605.2796 | K49: 1741.823 | L49: 1963.3254 | M49: 1104.5817 | N49: 1702.5464 | O49: 1408.3382
A50: R4 : Dépenses d'équipement brutes (c) / habitant | B50: 709.53128 | C50: 496.16267 | D50: 384.48944 | E50: 377.78503 | F50: 405.42179 | G50: 421.17888 | H50: 420.18482 | I50: 388.35153 | J50: 402.55259 | K50: 441.11602 | L50: 382.35309 | M50: 404.13414 | N50: 400.27498 | O50: 402.17375
A51: R5 : Dette / habitant | B51: 646.56187 | C51: 582.36767 | D51: 507.75018 | E51: 571.03215 | F51: 651.68738 | G51: 720.89919 | H51: 762.92482 | I51: 804.2155 | J51: 986.26993 | K51: 1322.466 | L51: 1894.7108 | M51: 646.97805 | N51: 1274.7224 | O51: 965.86216
A52: R6 : DGF / habitant | B52: 274.96603 | C52: 214.79947 | D52: 173.75505 | E52: 163.01047 | F52: 161.54805 | G52: 163.48149 | H52: 163.16549 | I52: 181.63553 | J52: 204.72187 | K52: 228.52022 | L52: 175.55012 | M52: 165.73702 | N52: 195.28509 | O52: 180.74697
A53: (a) Habitants comptés selon la population totale de l'Insee
A54: (b) Diminuées des travaux en régie.
A55: (c) C'est-à-dire y compris les travaux en régie, les travaux effectués d'office pour le compte de tiers, les opérations di'nvestissement sur établissements d'enseignement et les opérations sous mandat.
A56: Champ : France entière (France métropolitaine et DOM).
A57: Source : DGFiP-Comptes de gestion ; budgets principaux - opérations réelles. Calculs DGCL. Montants calculés hors gestion active de la dette. INSEE, Recensement de la population (population totale en 2024 - année de référence 2021).
A59: Liste des 11 ratios
A60: Pour les communes de 3 500 habitants et plus, les données synthétiques sur la situation financière de la collectivité, prévues par l’article L. 2313-1 du code général des collectivités territoriales (CGCT), comprennent 11 ratios définis à l’article R. 2313-1. Ces ratios sont aussi calculés pour les groupements à fiscalité propre, les départements (articles L. 3313-1 et R. 3313-1) et les régions (articles L. 4313-2 et R. 4313-1). Toutefois, le ratio 8, qui correspond au coefficient de mobilisation du potentiel fiscal, n’est plus calculé.
A62: À noter : pour la détermination des montants de dépenses ou recettes réelles de fonctionnement à retenir pour le calcul des ratios, les reversements de fiscalité liés au FNGIR et aux différents fonds de péréquation horizontale sont comptabilisés en moindres recettes.
A64: • Ratio 1 = dépenses réelles de fonctionnement (DRF) / population : montant total des dépenses de fonctionnement en mouvement réels. Les dépenses liées à des travaux en régie sont exclues des DRF.
A66: • Ratio 2 = produit des impositions directes / population : (recettes hors fiscalité reversée).
A68: • Ratio 2 bis = produit net des impositions directes / population : en plus des impositions directes, ce ratio intègre les prélèvements pour reversements de fiscalité et la fiscalité reversée aux communes par les groupements à fiscalité propre.
A70: • Ratio 3 = recettes réelles de fonctionnement (RRF) / population : montant total des recettes de fonctionnement en mouvements réels. Ressources dont dispose la collectivité, à comparer aux dépenses de fonctionnement dans leur rythme de croissance.
... A86: Les ratios 7 à 11 sont exprimés en pourcentage.

Sheet T 2.3
A1: T 2.3 - Évolution à champ constant (a) par strate de population des communes
O2: en %
A3: Evolutions 2024 / 2023 en % | B3: Moins | C3: De 100 | D3: De 200 | E3: De 500 | F3: De 2 000 | G3: De 3 500 | H3: De 5 000 | I3: De 10 000 | J3: De 20 000 | K3: De 50 000 | L3: 100000 | M3: Communes | N3: Communes | O3: Ensemble
B4: de 100 | C4: à moins de | D4: à moins de | E4: à moins de | F4: à moins de | G4: à moins de | H4: à moins de | I4: à moins de | J4: à moins de | K4: à moins de | L4: habitants | M4: de moins | N4: de 10 000 hab. | O4: des
A5: Hors gestion active de la dette | B5: habitants | C5: 200 hab. | D5: 500 hab. | E5: 2 000 hab. | F5: 3 500 hab. | G5: 5 000 hab. | H5: 10 000 hab. | I5: 20 000 hab. | J5: 50 000 hab. | K5: 100 000 hab. | L5: et plus | M5: de 10 000 hab. | N5: et plus | O5: communes
A7: DÉPENSES DE FONCTIONNEMENT (1) | B7: 4.6100856 | C7: 4.8977878 | D7: 5.0125776 | E7: 4.6936129 | F7: 4.4424634 | G7: 3.5155404 | H7: 3.9889944 | I7: 3.6466346 | J7: 3.1540938 | K7: 3.627244 | L7: 5.3359965 | M7: 4.2955539 | N7: 4.0847469 | O7: 4.1620653
A8: Achats et charges externes | B8: 6.4336699 | C8: 7.0924199 | D8: 7.1713984 | E8: 6.0000483 | F8: 4.6404008 | G8: 3.353362 | H8: 3.406772 | I8: 3.4393186 | J8: 2.3247435 | K8: 3.3255518 | L8: 5.2223946 | M8: 4.8055309 | N8: 3.562075 | O8: 4.124406
A9: Frais de personnel | B9: 3.8836793 | C9: 4.4745246 | D9: 4.3903661 | E9: 4.8849371 | F9: 5.1499875 | G9: 4.9081525 | H9: 4.3891233 | I9: 3.9405646 | J9: 3.5330309 | K9: 3.0771965 | L9: 5.4632195 | M9: 4.7225524 | N9: 4.1124521 | O9: 4.3167059
A10: Charges financières | B10: 17.125087 | C10: 12.03851 | D10: 11.353643 | E10: 6.9606478 | F10: 5.4956332 | G10: 5.4575541 | H10: 3.9433644 | I10: 8.0313274 | J10: 6.8154595 | K10: 12.233177 | L10: 14.822678 | M10: 5.9939665 | N10: 11.122901 | O10: 9.3827758
A11: Dépenses d'intervention | B11: 6.7800082 | C11: 4.1205624 | D11: 3.7492181 | E11: 5.3032026 | F11: 5.7456184 | G11: 4.6126 | H11: 4.432204 | I11: 3.5667759 | J11: 4.7742123 | K11: 4.6279636 | L11: 4.9963777 | M11: 4.8416545 | N11: 4.7498038 | O11: 4.7741205
A12: Autres dépenses de fonctionnement | B12: 0.47600774 | C12: 1.0434908 | D12: 1.2799354 | E12: -2.3663845 | F12: -4.916101 | G12: -11.84207 | H12: 1.1780929 | I12: -2.5596417 | J12: -6.332706 | K12: 6.743282 | L12: -1.110946 | M12: -2.4424305 | N12: -1.5750069 | O12: -2.0940267
A13: RECETTES DE FONCTIONNEMENT (2) | B13: 0.4744945 | C13: 2.1725028 | D13: 3.258756 | E13: 3.7016363 | F13: 4.1117775 | G13: 3.4790005 | H13: 3.6983833 | I13: 3.1171785 | J13: 2.7172115 | K13: 3.8322215 | L13: 1.7837631 | M13: 3.6416294 | N13: 2.6670261 | O13: 3.0409965
A14: Impôts et taxes | B14: -1.285355 | C14: 0.7563497 | D14: 2.7827501 | E14: 4.0785023 | F14: 4.1513335 | G14: 4.2077727 | H14: 3.4230463 | I14: 2.9979262 | J14: 2.5342541 | K14: 2.4361694 | L14: 0.76346247 | M14: 3.7155912 | N14: 1.9644064 | O14: 2.5801111
A15: - Impôts locaux | B15: 6.0440669 | C15: 5.3809798 | D15: 6.2170425 | E15: 6.0609412 | F15: 5.8364998 | G15: 6.0530797 | H15: 4.8485256 | I15: 4.2480123 | J15: 3.7521005 | K15: 3.346697 | L15: 3.3018952 | M15: 5.6157563 | N15: 3.6319344 | O15: 4.3555071
A16: (dont : fiscalité reversée) | B16: 4.7301984 | C16: 2.8238101 | D16: 3.6477088 | E16: 1.7691972 | F16: 1.7676999 | G16: 1.6744694 | H16: -0.21604584 | I16: 0.4689909 | J16: 0.037405332 | K16: -0.90880117 | L16: 3.0503434 | M16: 1.088374 | N16: 0.76071335 | O16: 0.87263978
A17: - Autres impôts et taxes | B17: -14.451799 | C17: -12.052812 | D17: -10.990043 | E17: -8.9721285 | F17: -9.1067647 | G17: -8.5341333 | H17: -6.1803262 | I17: -5.4051133 | J17: -8.1529419 | K17: -4.3593864 | L17: -4.975974 | M17: -8.4488048 | N17: -5.471767 | O17: -6.3222695
A18: Concours de l'État | B18: 9.1733602 | C18: 6.3094659 | D18: 4.3808851 | E18: 3.3895667 | F18: 3.374376 | G18: 3.1720261 | H18: 3.9873709 | I18: 2.3285736 | J18: 2.8129218 | K18: 3.8138889 | L18: 2.6579564 | M18: 3.7822837 | N18: 2.8659346 | O18: 3.3060133
... A44: Dette au 31 décembre (12) | B44: -4.2609714 | C44: -3.6299315 | D44: -3.3352027 | E44: -2.63306 | F44: -1.1601224 | G44: -0.11215563 | H44: -1.0076264 | I44: 0.20439601 | J44: 0.94414027 | K44: 1.2051041 | L44: 5.7850491 | M44: -1.6358988 | N44: 2.9630985 | O44: 1.4001106
A45: Ratios (voir définitions en annexe 3)
A46: Taux d'épargne brute (c) = (3) / (2) | B46: -2.8519808 | C46: -1.9411511 | D46: -1.2950739 | E46: -0.75735493 | F46: -0.25654229 | G46: -0.028926774 | H46: -0.234486 | I46: -0.43977658 | J46: -0.36871368 | K46: 0.1710912 | L46: -3.0519352 | M46: -0.50921967 | N46: -1.1980129 | O46: -0.91864101
A47: Taux d'épargne nette (c) = [(3)-(8)] / (2) | B47: -3.5225266 | C47: -1.8361699 | D47: -0.93662104 | E47: -0.66343018 | F47: 0.083527824 | G47: 0.18608638 | H47: -0.064985261 | I47: -0.24813124 | J47: -0.19523387 | K47: 0.64870919 | L47: -2.6319673 | M47: -0.31880713 | N47: -0.88566254 | O47: -0.65475249
A48: Taux d'endettement (c) = (12) / (2) | B48: -2.0820393 | C48: -3.1537446 | D48: -3.7111552 | E48: -3.9212829 | F48: -3.2191078 | G48: -2.1255897 | H48: -2.7455407 | I48: -1.6076891 | J48: -1.0777763 | K48: -1.9708679 | L48: 3.650278 | M48: -3.1428095 | N48: 0.21526055 | O48: -1.1097037
A49: Délai de désendettement (d) = (12) / (3) | B49: 0.072520398 | C49: 0.03186799 | D49: -0.024147905 | E49: -0.079070745 | F49: -0.1249588 | G49: -0.11232074 | H49: -0.11661074 | I49: 0.009826986 | J49: 0.050368549 | K49: -0.21996467 | L49: 2.7609883 | M49: -0.080590083 | N49: 0.57843805 | O49: 0.20504604
A50: R1 : Dépenses réelles de fonctionnement (DRF) (e) / habitant | B50: 4.9489483 | C50: 5.1792957 | D50: 5.1058449 | E50: 4.5578548 | F50: 4.1533843 | G50: 3.1652642 | H50: 3.5942261 | I50: 3.0884685 | J50: 2.58651 | K50: 3.1198092 | L50: 5.2125221 | M50: 4.0735402 | N50: 3.6598295 | O50: 3.8359606
A51: R2 : Produit des impositions directes hors fiscalité reversée / habitant | B51: 6.9626799 | C51: 5.9373203 | D51: 6.2950005 | E51: 6.5147375 | F51: 6.3414283 | G51: 6.6218386 | H51: 5.7935141 | I51: 4.8355003 | J51: 4.1952684 | K51: 4.0194424 | L51: 3.2957658 | M51: 6.2762595 | N51: 3.9632611 | O51: 4.8380507
A52: R2 bis : Produit des impositions directes y compris fiscalité reversée / habitant | B52: 6.39488 | C52: 5.6213314 | D52: 6.2874613 | E52: 5.8957676 | F52: 5.4982006 | G52: 5.6436267 | H52: 4.4485135 | I52: 3.664623 | J52: 3.164849 | K52: 2.8305639 | L52: 3.1617189 | M52: 5.3647743 | N52: 3.190987 | O52: 4.0079572
A53: R3 : Recettes réelles de fonctionnement (RRF) / habitant | B53: 0.80688239 | C53: 2.4055365 | D53: 3.3272135 | E53: 3.5401369 | F53: 3.7789912 | G53: 3.0794856 | H53: 3.3027592 | I53: 2.5401175 | J53: 2.1358176 | K53: 3.3136635 | L53: 1.6456469 | M53: 3.3953387 | N53: 2.2301844 | O53: 2.6978246
A54: R4 : Dépenses d'équipement brutes (f) / habitant | B54: 2.9544511 | C54: 6.6172791 | D54: 9.3354332 | E54: 10.073417 | F54: 13.15576 | G54: 10.940887 | H54: 12.472103 | I54: 4.6050502 | J54: 9.6477545 | K54: 7.2736608 | L54: 10.756158 | M54: 11.087467 | N54: 8.4047395 | O54: 9.7153797
A55: R5 : Dette / habitant | B55: -3.9442493 | C55: -3.4101319 | D55: -3.2711169 | E55: -2.784694 | F55: -1.4760573 | G55: -0.49780567 | H55: -1.3852964 | I55: -0.35636456 | J55: 0.37278216 | K55: 0.6996665 | L55: 5.6415033 | M55: -1.8696482 | N55: 2.524997 | O55: 1.0624035
A56: R6 : DGF / habitant | B56: -0.14094339 | C56: 1.2567208 | D56: 1.3758756 | E56: 1.212642 | F56: 1.4815866 | G56: 0.94284524 | H56: 1.7063934 | I56: 0.75842214 | J56: 2.2011062 | K56: 2.5618744 | L56: 1.8251078 | M56: 1.3429547 | N56: 1.8931402 | O56: 1.6517763
A57: R7 : Dépenses de personnel / dépenses réelles de fonctionnement (c) | B57: -0.15976609 | C57: -0.11326775 | D57: -0.20776031 | E57: 0.080808293 | F57: 0.3403494 | G57: 0.71275094 | H57: 0.21793781 | I57: 0.16796717 | J57: 0.22240582 | K57: -0.32228228 | L57: 0.060046959 | M57: 0.2012668 | N57: 0.015059648 | O57: 0.079956587
... A59: R10 : Dépenses d'équipement brutes (f) / RRF (Taux d'équipement) (c) | B59: 0.96355969 | C59: 1.7628668 | D59: 2.2639376 | E59: 2.3671996 | F59: 3.1091196 | G59: 2.4474875 | H59: 2.5931572 | I59: 0.52721363 | J59: 1.7208359 | K59: 0.93486862 | L59: 1.6019434 | M59: 2.5334268 | N59: 1.339729 | O59: 1.8269937
A60: (a) C'est-à-dire en ne conservant que les communes présentes sur les deux années, en 2023 et 2024 (et donc hors communes nouvelles de 2024). Les strates sont celles des communes en 2024.
A61: (b) La forte augmentation de l'épargne brute et nette de la strate des communes de 100 000 habitants et plus est due à la ville de Paris.
A62: (c) Écarts en point de pourcentage entre 2024 et 2023.
A63: (d) Écarts en nombre d'années.
A64: (e) Diminuées des travaux en régie.
A65: (f) C'est-à-dire y compris les travaux en régie, les travaux effectués d'office pour le compte de tiers, les opérations di'nvestissement sur établissements d'enseignement et les opérations sous mandat.
A66: Champ : France entière (France métropolitaine et DOM).
A67: Source : DGFiP-Comptes de gestion ; budgets principaux - opérations réelles. Calculs DGCL. Montants calculés hors gestion active de la dette. INSEE, Recensement de la population (population totale en 2024 - année de référence 2021).
A69: Liste des 11 ratios
A70: Pour les communes de 3 500 habitants et plus, les données synthétiques sur la situation financière de la collectivité, prévues par l’article L. 2313-1 du code général des collectivités territoriales (CGCT), comprennent 11 ratios définis à l’article R. 2313-1. Ces ratios sont aussi calculés pour les groupements à fiscalité propre, les départements (articles L. 3313-1 et R. 3313-1) et les régions (articles L. 4313-2 et R. 4313-1). Toutefois, le ratio 8, qui correspond au coefficient de mobilisation du potentiel fiscal, n’est plus calculé.
A72: À noter : pour la détermination des montants de dépenses ou recettes réelles de fonctionnement à retenir pour le calcul des ratios, les reversements de fiscalité liés au FNGIR et aux différents fonds de péréquation horizontale sont comptabilisés en moindres recettes.
A74: • Ratio 1 = dépenses réelles de fonctionnement (DRF) / population : montant total des dépenses de fonctionnement en mouvement réels. Les dépenses liées à des travaux en régie sont exclues des DRF.
... A96: Les ratios 7 à 11 sont exprimés en pourcentage.

Sheet T 3
A1: T 3 - Données financières des communes par strate (a) de population selon leurs caractéristiques en 2024
A4: T 3.a - Dépenses de fonctionnement par «habitant DGF» (b) selon les caractéristiques des communes | L4: Données financières en opérations réelles | O4: en € / habitant «DGF»
B5: Moins | C5: De 100 | D5: De 200 | E5: De 500 | F5: De 2 000 | G5: De 3 500 | H5: De 5 000 | I5: De 10 000 | J5: De 20 000 | K5: De 50 000 | L5: 100000 | M5: Communes | N5: Communes | O5: Ensemble
A6: Exercice 2024 | B6: de 100 | C6: à moins de | D6: à moins de | E6: à moins de | F6: à moins de | G6: à moins de | H6: à moins de | I6: à moins de | J6: à moins de | K6: à moins de | L6: habitants | M6: de moins | N6: de 10 000 hab. | O6: des
B7: habitants | C7: 200 hab. | D7: 500 hab. | E7: 2 000 hab. | F7: 3 500 hab. | G7: 5 000 hab. | H7: 10 000 hab. | I7: 20 000 hab. | J7: 50 000 hab. | K7: 100 000 hab. | L7: et plus | M7: de 10 000 hab. | N7: et plus | O7: communes
A8: Ensemble des communes (c) | B8: 874.8445 | C8: 707.5101 | D8: 649.8966 | E8: 703.4696 | F8: 822.5188 | G8: 929.0796 | H8: 1055.5556 | I8: 1202.0657 | J8: 1361.3622 | K8: 1459.6216 | L8: 1720.4587 | M8: 834.9802 | N8: 1450.1939 | O8: 1141.4131
A10: communes touristiques (d) | B10: 992.7009 | C10: 1000.6271 | D10: 963.9649 | E10: 963.6016 | F10: 1026.2788 | G10: 1100.364 | H10: 1121.2226 | I10: 1201.6367 | J10: 1209.0527 | K10: 1323.506 | L10: - | M10: 1043.5629 | N10: 1219.2185 | O10: 1098.3546
A11: dont :
A12: - communes du littoral maritime (e) | B12: 2590.8553 | C12: 1091.0952 | D12: 896.4534 | E12: 862.4866 | F12: 882.2204 | G12: 1081.2336 | H12: 1107.8834 | I12: 1157.7407 | J12: 1200.2951 | K12: 1323.506 | L12: - | M12: 1009.9012 | N12: 1199.9033 | O12: 1094.5086
A13: - supports de stations de sports d'hiver | B13: 1159.2672 | C13: 1131.1867 | D13: 1219.8739 | E13: 1300.6124 | F13: 1786.9322 | G13: 1288.5497 | H13: 1465.7195 | I13: 1354.7988 | J13: - | K13: - | L13: - | M13: 1393.9987 | N13: 1354.7988 | O13: 1391.1854
A14: - autres communes de montagne | B14: 925.637 | C14: 981.4505 | D14: 864.5835 | E14: 843.0073 | F14: 902.3506 | G14: 949.6542 | H14: 975.9951 | I14: 1846.3358 | J14: 1180.3559 | K14: - | L14: - | M14: 888.6028 | N14: 1438.8279 | O14: 915.3292
A15: - autres communes touristiques | B15: 839.8935 | C15: 719.6861 | D15: 748.3426 | E15: 783.3238 | F15: 965.2202 | G15: 1130.0841 | H15: 1086.9711 | I15: 1278.1698 | J15: 1302.6668 | K15: - | L15: - | M15: 964.1768 | N15: 1285.6886 | O15: 1034.6709
A17: communes non touristiques (f) | B17: 866.0411 | C17: 688.4087 | D17: 626.3964 | E17: 672.5538 | F17: 780.3699 | G17: 881.9456 | H17: 1033.3387 | I17: 1194.6182 | J17: 1366.9864 | K17: 1472.0928 | L17: 1727.1547 | M17: 798.2174 | N17: 1466.8632 | O17: 1135.7125
A19: communes rurales/urbaines (c)
A21: - communes rurales | B21: 874.8445 | C21: 707.5729 | D21: 650.5588 | E21: 704.419 | F21: 826.9407 | G21: 918.4412 | H21: 968.556 | I21: 1073.8472 | J21: 871.3329 | K21: - | L21: - | M21: 765.2172 | N21: 1017.9044 | O21: 768.7322
A22: - communes urbaines | B22: - | C22: 565.9848 | D22: 563.0686 | E22: 695.4174 | F22: 813.0446 | G22: 942.6881 | H22: 1080.9709 | I22: 1206.2274 | J22: 1365.5035 | K22: 1459.6216 | L22: 1720.4587 | M22: 973.18 | N22: 1454.3163 | O22: 1331.9017
A24: montagne et tourisme (f) | B24: 874.8445 | C24: 707.5101 | D24: 649.1161 | E24: 701.8488 | F24: 817.7266 | G24: 921.7756 | H24: 1044.9263 | I24: 1195.5181 | J24: 1354.8937 | K24: 1465.8664 | L24: 1727.1547 | M24: 828.3498 | N24: 1452.3444 | O24: 1132.2924
A25: dont :
A26: - communes de montagne touristiques | B26: 951.6026 | C26: 1017.2187 | D26: 1001.722 | E26: 1064.0213 | F26: 1249.6968 | G26: 1085.9965 | H26: 1201.0542 | I26: 1405.9024 | J26: 1180.3559 | K26: - | L26: - | M26: 1109.8054 | N26: 1366.5983 | O26: 1128.1503
A27: - communes de montagne non touristiques | B27: 992.6774 | C27: 817.7412 | D27: 751.8922 | E27: 708.2335 | F27: 780.0856 | G27: 897.2598 | H27: 1023.4957 | I27: 1160.8194 | J27: 1247.6307 | K27: - | L27: 1464.7082 | M27: 810.725 | N27: 1282.1891 | O27: 913.1491
A28: - communes touristiques et hors montagne (e) | B28: 2274.1499 | C28: 857.0346 | D28: 783.9863 | E28: 813.6497 | F28: 899.6221 | G28: 1106.1971 | H28: 1104.9725 | I28: 1174.4268 | J28: 1209.9033 | K28: 1323.506 | L28: - | M28: 999.9963 | N28: 1208.5788 | O28: 1085.9471
A29: - communes non touristiques et hors montagne | B29: 804.6577 | C29: 652.085 | D29: 602.3485 | E29: 667.8031 | F29: 780.3958 | G29: 880.7392 | H29: 1034.2386 | I29: 1196.9444 | J29: 1369.5924 | K29: 1472.0928 | L29: 1735.3654 | M29: 796.7123 | N29: 1472.4279 | O29: 1151.9409
A30: (a) Les strates sont calculées avec la population totale recensée par l'Insee en 2024 - année de référence 2021.
A31: (b) Les habitants «DGF» sont comptés selon la population «DGF» en 2024 - année de référence 2021.
A32: (c) En France entière (France métropolitaine et DOM).
A33: (d) Les communes touristiques concernent uniquement la France métropolitaine.
A34: (e) Le montant élevé pour les communes touristiques du littoral maritime de moins de 100 habitants est dû à la présence de la commune atypique du Mont-Saint-Michel.
A35: (f) En France métropolitaine.
A36: Source : DGFiP-Comptes de gestion ; budgets principaux - opérations réelles. Calculs DGCL. Strates de population calculées avec la population totale recensée par l'Insee en 2024 (année de référence 2021).
A38: T 3.b - Recettes de fonctionnement par «habitant DGF» (b) selon les caractéristiques des communes | O38: en € / habitant «DGF»
B39: Moins | C39: De 100 | D39: De 200 | E39: De 500 | F39: De 2 000 | G39: De 3 500 | H39: De 5 000 | I39: De 10 000 | J39: De 20 000 | K39: De 50 000 | L39: 100000 | M39: Communes | N39: Communes | O39: Ensemble
A40: Exercice 2024 | B40: de 100 | C40: à moins de | D40: à moins de | E40: à moins de | F40: à moins de | G40: à moins de | H40: à moins de | I40: à moins de | J40: à moins de | K40: à moins de | L40: habitants | M40: de moins | N40: de 10 000 hab. | O40: des
B41: habitants | C41: 200 hab. | D41: 500 hab. | E41: 2 000 hab. | F41: 3 500 hab. | G41: 5 000 hab. | H41: 10 000 hab. | I41: 20 000 hab. | J41: 50 000 hab. | K41: 100 000 hab. | L41: et plus | M41: de 10 000 hab. | N41: et plus | O41: communes
A42: Ensemble des communes (c) | B42: 1212.6858 | C42: 946.9322 | D42: 838.0734 | E42: 880.2246 | F42: 1015.2979 | G42: 1133.8643 | H42: 1258.0242 | I42: 1396.2749 | J42: 1563.5472 | K42: 1687.5042 | L42: 1901.0504 | M42: 1028.1823 | N42: 1648.7583 | O42: 1337.2861
A44: communes touristiques (d) | B44: 1407.2928 | C44: 1346.8158 | D44: 1261.7149 | E44: 1229.877 | F44: 1293.9155 | G44: 1400.1497 | H44: 1406.348 | I44: 1459.3622 | J44: 1444.8777 | K44: 1450.8609 | L44: - | M44: 1324.3991 | N44: 1452.4433 | O44: 1364.3395
A45: dont :
A46: - communes du littoral maritime (e) | B46: 3729.5565 | C46: 1212.3182 | D46: 1146.4752 | E46: 992.4772 | F46: 1078.5926 | G46: 1301.9031 | H46: 1316.9902 | I46: 1376.7905 | J46: 1412.8633 | K46: 1413.5399 | L46: - | M46: 1207.478 | N46: 1397.6032 | O46: 1292.1272
A47: - supports de stations de sports d'hiver | B47: 1490.0207 | C47: 1436.2599 | D47: 1416.0016 | E47: 1591.9014 | F47: 2018.4967 | G47: 1785.2113 | H47: 1744.0557 | I47: 1585.2418 | J47: - | K47: - | L47: - | M47: 1690.0676 | N47: 1585.2418 | O47: 1682.5211
A48: - autres communes de montagne | B48: 1252.4293 | C48: 1292.3639 | D48: 1096.6448 | E48: 1029.381 | F48: 1070.3786 | G48: 1099.137 | H48: 1169.4899 | I48: 2021.4989 | J48: 1322.1394 | K48: - | L48: - | M48: 1083.0081 | N48: 1593.2512 | O48: 1107.4663
A49: - autres communes touristiques | B49: 1084.4292 | C49: 889.311 | D49: 907.7596 | E49: 940.5038 | F49: 1125.3709 | G49: 1302.7346 | H49: 1292.3309 | I49: 1416.0072 | J49: 1580.2697 | K49: - | L49: - | M49: 1137.9831 | N49: 1468.6403 | O49: 1207.0138
A51: communes non touristiques (f) | B51: 1198.1495 | C51: 920.8732 | D51: 806.1207 | E51: 839.244 | F51: 959.7146 | G51: 1066.7406 | H51: 1226.6046 | I51: 1383.788 | J51: 1569.1089 | K51: 1710.7443 | L51: 1907.1367 | M51: 979.9229 | N51: 1665.4433 | O51: 1325.9353
A53: communes rurales/urbaines (c)
A55: - communes rurales | B55: 1212.6858 | C55: 946.9391 | D55: 838.7851 | E55: 882.4366 | F55: 1027.3748 | G55: 1130.0673 | H55: 1172.1638 | I55: 1274.0967 | J55: 1073.557 | K55: - | L55: - | M55: 958.4731 | N55: 1218.6994 | O55: 962.093
A56: - communes urbaines | B56: - | C56: 931.2957 | D56: 744.7592 | E56: 861.4633 | F56: 989.4232 | G56: 1138.7214 | H56: 1283.1067 | I56: 1400.2405 | J56: 1567.6881 | K56: 1687.5042 | L56: 1901.0504 | M56: 1166.2758 | N56: 1652.8595 | O56: 1529.0588
A58: montagne et tourisme (f) | B58: 1212.6858 | C58: 946.9322 | D58: 836.7841 | E58: 878.5627 | F58: 1010.4839 | G58: 1127.5399 | H58: 1250.3039 | I58: 1393.4786 | J58: 1559.5967 | K58: 1699.8541 | L58: 1907.1367 | M58: 1022.2301 | N58: 1652.9556 | O58: 1329.4513
A59: dont :
A60: - communes de montagne touristiques | B60: 1350.1002 | C60: 1358.6433 | D60: 1313.667 | E60: 1358.4741 | F60: 1570.6549 | G60: 1397.7495 | H60: 1540.1514 | I60: 1700.0715 | J60: 1370.6099 | K60: - | L60: - | M60: 1421.1006 | N60: 1642.659 | O60: 1436.9283
A61: - communes de montagne non touristiques | B61: 1409.6691 | C61: 1119.9159 | D61: 992.4646 | E61: 907.0151 | F61: 984.5873 | G61: 1096.9525 | H61: 1236.3237 | I61: 1368.5874 | J61: 1461.6772 | K61: - | L61: 1767.0885 | M61: 1030.3742 | N61: 1523.1044 | O61: 1137.4183
A62: - communes touristiques et hors montagne (e) | B62: 3190.5644 | C62: 1244.4543 | D62: 1014.0724 | E62: 1037.8494 | F62: 1137.0306 | G62: 1401.1242 | H62: 1379.1118 | I62: 1427.2977 | J62: 1447.0792 | K62: 1450.8609 | L62: - | M62: 1260.8002 | N62: 1438.7112 | O62: 1334.1121
A63: - communes non touristiques et hors montagne | B63: 1095.6213 | C63: 864.9712 | D63: 770.413 | E63: 830.2204 | F63: 957.4496 | G63: 1064.3606 | H63: 1225.716 | I63: 1384.8342 | J63: 1571.4545 | K63: 1710.7443 | L63: 1911.5181 | M63: 973.8517 | N63: 1669.7322 | O63: 1339.6812
A64: (a) Les strates sont calculées avec la population totale recensée par l'Insee en 2024 - année de référence 2021.
A65: (b) Les habitants «DGF» sont comptés selon la population «DGF» en 2024 - année de référence 2021.
A66: (c) En France entière (France métropolitaine et DOM).
A67: (d) Les communes touristiques concernent uniquement la France métropolitaine.
A68: (e) Le montant élevé pour les communes touristiques du littoral maritime de moins de 100 habitants est dû à la présence de la commune atypique du Mont-Saint-Michel.
A69: (f) En France métropolitaine.
A70: Source : DGFiP-Comptes de gestion ; budgets principaux - opérations réelles. Calculs DGCL. Strates de population calculées avec la population totale recensée par l'Insee en 2024 (année de référence 2021).
A72: T 3.c - Dépenses d'investissement hors remboursements de dette par «habitant DGF» (b) selon les caractéristiques des communes | O72: en € / habitant «DGF»
B73: Moins | C73: De 100 | D73: De 200 | E73: De 500 | F73: De 2 000 | G73: De 3 500 | H73: De 5 000 | I73: De 10 000 | J73: De 20 000 | K73: De 50 000 | L73: 100000 | M73: Communes | N73: Communes | O73: Ensemble
A74: Exercice 2024 | B74: de 100 | C74: à moins de | D74: à moins de | E74: à moins de | F74: à moins de | G74: à moins de | H74: à moins de | I74: à moins de | J74: à moins de | K74: à moins de | L74: habitants | M74: de moins | N74: de 10 000 hab. | O74: des
B75: habitants | C75: 200 hab. | D75: 500 hab. | E75: 2 000 hab. | F75: 3 500 hab. | G75: 5 000 hab. | H75: 10 000 hab. | I75: 20 000 hab. | J75: 50 000 hab. | K75: 100 000 hab. | L75: et plus | M75: de 10 000 hab. | N75: et plus | O75: communes
A76: Ensemble des communes (c) | B76: 583.888 | C76: 442.1253 | D76: 363.4217 | E76: 367.5607 | F76: 399.4486 | G76: 408.273 | H76: 416.3846 | I76: 391.2093 | J76: 419.4971 | K76: 460.5868 | L76: 451.2995 | M76: 393.2828 | N76: 429.9562 | O76: 411.5495
A78: communes touristiques (d) | B78: 664.713 | C78: 539.2277 | D78: 523.1751 | E78: 461.6282 | F78: 437.7992 | G78: 441.8624 | H78: 467.6942 | I78: 424.5006 | J78: 460.7457 | K78: 448.4732 | L78: - | M78: 459.4367 | N78: 442.2057 | O78: 454.103
A79: dont :
A80: - communes du littoral maritime (e) | B80: 1549.4618 | C80: 1057.3551 | D80: 699.3247 | E80: 505.6156 | F80: 450.5925 | G80: 509.4357 | H80: 496.4306 | I80: 482.4438 | J80: 541.4114 | K80: 379.9607 | L80: - | M80: 494.1932 | N80: 493.1529 | O80: 493.73
A81: - supports de stations de sports d'hiver | B81: 415.9327 | C81: 457.7296 | D81: 639.7186 | E81: 634.0547 | F81: 824.4607 | G81: 761.3925 | H81: 674.699 | I81: 620.9413 | J81: - | K81: - | L81: - | M81: 686.4884 | N81: 620.9413 | O81: 681.7842
A82: - autres communes de montagne | B82: 647.7296 | C82: 650.7563 | D82: 507.1821 | E82: 551.0024 | F82: 454.0862 | G82: 414.5043 | H82: 451.1825 | I82: 327.8969 | J82: 204.8086 | K82: - | L82: - | M82: 509.1181 | N82: 252.5802 | O82: 496.6571
A83: - autres communes touristiques | B83: 155.0658 | C83: 301.0378 | D83: 328.3931 | E83: 406.0682 | F83: 512.2272 | G83: 453.0871 | H83: 478.7432 | I83: 481.4703 | J83: 637.6719 | K83: - | L83: - | M83: 456.5463 | N83: 529.4126 | O83: 472.5228
A85: communes non touristiques (f) | B85: 580.5862 | C85: 430.367 | D85: 350.2898 | E85: 349.0242 | F85: 378.9986 | G85: 384.28 | H85: 397.6753 | I85: 376.9004 | J85: 413.704 | K85: 469.5686 | L85: 451.1705 | M85: 373.9866 | N85: 427.9574 | O85: 401.2281
A87: communes rurales/urbaines (c)
A89: - communes rurales | B89: 583.888 | C89: 442.1302 | D89: 362.5368 | E89: 370.7815 | F89: 410.4663 | G89: 415.0397 | H89: 415.042 | I89: 388.6654 | J89: 352.0669 | K89: - | L89: - | M89: 390.1804 | N89: 378.5554 | O89: 390.0187
A90: - communes urbaines | B90: - | C90: 431.0349 | D90: 479.4562 | E90: 340.2431 | F90: 375.843 | G90: 399.6171 | H90: 416.7768 | I90: 391.2919 | J90: 420.067 | K90: 460.5868 | L90: 451.2995 | M90: 399.4288 | N90: 430.4463 | O90: 422.5546
A92: montagne et tourisme (f) | B92: 583.888 | C92: 442.1253 | D92: 363.1733 | E92: 367.5154 | F92: 399.7285 | G92: 409.1732 | H92: 411.5253 | I92: 391.1544 | J92: 423.4122 | K92: 465.8136 | L92: 451.1705 | M92: 392.0476 | N92: 431.977 | O92: 411.4969
A93: dont :
A94: - communes de montagne touristiques | B94: 636.9552 | C94: 648.9268 | D94: 563.1027 | E94: 591.2113 | F94: 615.2744 | G94: 595.6154 | H94: 629.8749 | I94: 596.8102 | J94: 204.8086 | K94: - | L94: - | M94: 599.9513 | N94: 528.4994 | O94: 594.8469
A95: - communes de montagne non touristiques | B95: 814.7377 | C95: 629.3374 | D95: 506.2399 | E95: 431.5913 | F95: 452.7389 | G95: 517.532 | H95: 462.0836 | I95: 373.7844 | J95: 413.2957 | K95: - | L95: 358.9748 | M95: 478.4395 | N95: 377.6509 | O95: 456.5435
A96: - communes touristiques et hors montagne | B96: 351.695 | C96: 394.3676 | D96: 439.7416 | E96: 445.4149 | F96: 458.8715 | G96: 490.4088 | H96: 476.8355 | I96: 473.5774 | J96: 550.446 | K96: 379.9607 | L96: - | M96: 469.1478 | N96: 494.2088 | O96: 479.4747
A97: - communes non touristiques et hors montagne | B97: 467.0878 | C97: 374.4852 | D97: 320.4063 | E97: 338.0305 | F97: 372.2838 | G97: 373.7826 | H97: 391.7865 | I97: 377.1149 | J97: 413.7129 | K97: 469.5686 | L97: 454.0549 | M97: 361.417 | N97: 429.4733 | O97: 397.1947
A98: (a) Les strates sont calculées avec la population totale recensée par l'Insee en 2024 - année de référence 2021.
A99: (b) Les habitants «DGF» sont comptés selon la population «DGF» en 2024 - année de référence 2021.
A100: (c) En France entière (France métropolitaine et DOM).
A101: (d) Les communes touristiques concernent uniquement la France métropolitaine.
A102: (e) La commune atypique du Mont-Saint-Michel a un impcat important sur le montant des communes touristiques du littoral maritime de moins de 100 habitants.
A103: (f) En France métropolitaine.
A104: Source : DGFiP-Comptes de gestion ; budgets principaux - opérations réelles. Calculs DGCL. Strates de population calculées avec la population totale recensée par l'Insee en 2024 (année de référence 2021).
A106: T 3.d - Dépenses d'équipement «brutes» (b) par «habitant DGF» (c) selon les caractéristiques des communes | O106: en € / habitant «DGF»
B107: Moins | C107: De 100 | D107: De 200 | E107: De 500 | F107: De 2 000 | G107: De 3 500 | H107: De 5 000 | I107: De 10 000 | J107: De 20 000 | K107: De 50 000 | L107: 100000 | M107: Communes | N107: Communes | O107: Ensemble
A108: Exercice 2024 | B108: de 100 | C108: à moins de | D108: à moins de | E108: à moins de | F108: à moins de | G108: à moins de | H108: à moins de | I108: à moins de | J108: à moins de | K108: à moins de | L108: habitants | M108: de moins | N108: de 10 000 hab. | O108: des
B109: habitants | C109: 200 hab. | D109: 500 hab. | E109: 2 000 hab. | F109: 3 500 hab. | G109: 5 000 hab. | H109: 10 000 hab. | I109: 20 000 hab. | J109: 50 000 hab. | K109: 100 000 hab. | L109: et plus | M109: de 10 000 hab. | N109: et plus | O109: communes
A110: Ensemble des communes (d) | B110: 560.1766 | C110: 422.5753 | D110: 345.2202 | E110: 350.9341 | F110: 381.1697 | G110: 391.6061 | H110: 400.1515 | I110: 372.9102 | J110: 392.0874 | K110: 427.3598 | L110: 370.2252 | M110: 376.1818 | N110: 387.6292 | O110: 381.8837
A112: communes touristiques (e) | B112: 599.6585 | C112: 604.8239 | D112: 502.4117 | E112: 503.3276 | F112: 485.4758 | G112: 491.6858 | H112: 462.1678 | I112: 464.9747 | J112: 506.818 | K112: 317.2722 | L112: - | M112: 488.3218 | N112: 464.3827 | O112: 480.8545
A113: dont :
A114: - communes du littoral maritime (f) | B114: 1549.4618 | C114: 1055.2721 | D114: 654.8234 | E114: 485.907 | F114: 421.8073 | G114: 473.8054 | H114: 465.6065 | I114: 456.9802 | J114: 506.0155 | K114: 317.2722 | L114: - | M114: 464.3637 | N114: 458.0589 | O114: 461.5562
A115: - supports de stations de sports d'hiver | B115: 347.9871 | C115: 435.4526 | D115: 590.7485 | E115: 586.3161 | F115: 757.5996 | G115: 739.2077 | H115: 478.0108 | I115: 603.3793 | J115: - | K115: - | L115: - | M115: 622.1273 | N115: 603.3793 | O115: 620.7817
A116: - autres communes de montagne | B116: 623.6274 | C116: 633.5045 | D116: 468.6056 | E116: 527.3861 | F116: 435.3459 | G116: 412.9441 | H116: 433.6234 | I116: 294.7828 | J116: 178.7845 | K116: - | L116: - | M116: 487.3961 | N116: 223.8044 | O116: 474.5925
A117: - autres communes touristiques | B117: 143.3725 | C117: 272.026 | D117: 313.5115 | E117: 381.8377 | F117: 494.5351 | G117: 427.5005 | H117: 454.202 | I117: 467.4301 | J117: 618.17 | K117: - | L117: - | M117: 433.9498 | N117: 513.6961 | O117: 451.4349
A119: communes non touristiques (g) | B119: 557.2275 | C119: 410.6989 | D119: 333.606 | E119: 333.8488 | F119: 362.6991 | G119: 369.8815 | H119: 383.7952 | I119: 359.0639 | J119: 386.6811 | K119: 435.8948 | L119: 368.6507 | M119: 358.6747 | N119: 383.6893 | O119: 371.3007
A121: communes rurales/urbaines (d)
A123: - communes rurales | B123: 560.1766 | C123: 422.5716 | D123: 344.3222 | E123: 353.9087 | F123: 391.8077 | G123: 398.1396 | H123: 404.1489 | I123: 362.4217 | J123: 325.9218 | K123: - | L123: - | M123: 373.1146 | N123: 352.3389 | O123: 372.8256
A124: - communes urbaines | B124: - | C124: 431.0349 | D124: 462.9721 | E124: 325.7049 | F124: 358.3776 | G124: 383.2485 | H124: 398.9837 | I124: 373.2507 | J124: 392.6466 | K124: 427.3598 | L124: 370.2252 | M124: 382.258 | N124: 387.9657 | O124: 386.5135
...

Sheet T 4.1
A1: T 4.1.a - Dépenses et recettes par «habitant DGF» (a) des communes touristiques (b) par strate de population (c) en 2024 (France métropolitaine)
P3: en € / habitant «DGF»
B4: Moins | C4: De 100 | D4: De 200 | E4: De 500 | F4: De 2 000 | G4: De 3 500 | H4: De 5 000 | I4: De 10 000 | J4: De 20 000 | K4: De 50 000 | L4: 100000 | M4: Communes | N4: Communes de | O4: Ensemble | P4: Ensemble des
A5: Hors gestion active de la dette | B5: de 100 | C5: à moins de | D5: à moins de | E5: à moins de | F5: à moins de | G5: à moins de | H5: à moins de | I5: à moins de | J5: à moins de | K5: à moins de | L5: habitants | M5: de moins | N5: de 10 000 hab. | O5: des | P5: communes en
A6: en € / habitant «DGF» | B6: habitants | C6: 200 hab. | D6: 500 hab. | E6: 2 000 hab. | F6: 3 500 hab. | G6: 5 000 hab. | H6: 10 000 hab. | I6: 20 000 hab. | J6: 50 000 hab. | K6: 100 000 hab. | L6: et plus | M6: de 10 000 hab. | N6: et plus | O6: communes | P6: France métropolitaine
A8: DÉPENSES DE FONCTIONNEMENT (1) | B8: 992.70086 | C8: 1000.6271 | D8: 963.96491 | E8: 963.60155 | F8: 1026.2788 | G8: 1100.364 | H8: 1121.2226 | I8: 1201.6367 | J8: 1209.0527 | K8: 1323.506 | L8: - | M8: 1043.5629 | N8: 1219.2185 | O8: 1098.3546 | P8: 1132.2924
A9: Achats et charges externes | B9: 351.28665 | C9: 380.37748 | D9: 364.28986 | E9: 333.91219 | F9: 337.38778 | G9: 339.89175 | H9: 321.87281 | I9: 315.24968 | J9: 315.54593 | K9: 267.39352 | L9: - | M9: 334.90121 | N9: 309.6532 | O9: 327.02568 | P9: 298.70578
A10: Frais de personnel | B10: 315.17777 | C10: 346.38349 | D10: 353.52559 | E10: 404.03394 | F10: 491.85839 | G10: 568.04181 | H10: 618.57181 | I10: 692.73413 | J10: 680.8759 | K10: 804.15934 | L10: - | M10: 504.80293 | N10: 701.21284 | O10: 566.06842 | P10: 606.40868
A11: Charges financières | B11: 14.109053 | C11: 27.799726 | D11: 19.942757 | E11: 23.323124 | F11: 21.751312 | G11: 21.570006 | H11: 24.237401 | I11: 22.433724 | J11: 32.11799 | K11: 49.886719 | L11: - | M11: 22.738902 | N11: 29.660333 | O11: 24.897881 | P11: 23.64555
A12: Dépenses d'intervention | B12: 143.19477 | C12: 128.50369 | D12: 141.42851 | E12: 135.96617 | F12: 124.48057 | G12: 122.61988 | H12: 114.13743 | I12: 133.33128 | J12: 147.00412 | K12: 164.32384 | L12: - | M12: 125.60043 | N12: 142.60632 | O12: 130.90502 | P12: 158.3703
A13: Autres dépenses de fonctionnement | B13: 168.93261 | C13: 117.56276 | D13: 84.778188 | E13: 66.366124 | F13: 50.800766 | G13: 48.240538 | H13: 42.403121 | I13: 37.887875 | J13: 33.508732 | K13: 37.742583 | L13: - | M13: 55.519442 | N13: 36.085769 | O13: 49.45756 | P13: 45.162082
A14: RECETTES DE FONCTIONNEMENT (2) | B14: 1407.2928 | C14: 1346.8158 | D14: 1261.7149 | E14: 1229.877 | F14: 1293.9155 | G14: 1400.1497 | H14: 1406.348 | I14: 1459.3622 | J14: 1444.8777 | K14: 1450.8609 | L14: - | M14: 1324.3991 | N14: 1452.4433 | O14: 1364.3395 | P14: 1329.4513
A15: Impôts et taxes | B15: 583.75657 | C15: 586.58509 | D15: 632.61291 | E15: 714.39731 | F15: 827.86187 | G15: 933.40519 | H15: 985.25156 | I15: 1083.2925 | J15: 1066.2375 | K15: 1059.0897 | L15: - | M15: 842.63116 | N15: 1073.4502 | O15: 914.62977 | P15: 882.9185
A16: - Impôts locaux | B16: 464.02318 | C16: 495.1353 | D16: 528.40343 | E16: 601.47471 | F16: 707.9497 | G16: 759.65854 | H16: 817.53897 | I16: 910.66906 | J16: 914.74788 | K16: 876.59413 | L16: - | M16: 703.65408 | N16: 908.26058 | O16: 767.47631 | P16: 762.76738
A17: (dont : fiscalité reversée) | B17: 181.94982 | C17: 103.59693 | D17: 86.553917 | E17: 71.548112 | F17: 83.279386 | G17: 85.311382 | H17: 84.381872 | I17: 114.61091 | J17: 53.738762 | K17: 54.246616 | L17: - | M17: 81.599194 | N17: 82.590534 | O17: 81.908419 | P17: 153.50215
A18: - Autres impôts et taxes | B18: 119.73339 | C18: 91.44979 | D18: 104.20947 | E18: 112.9226 | F18: 119.91217 | G18: 173.74666 | H18: 167.71259 | I18: 172.6234 | J18: 151.48966 | K18: 182.49555 | L18: - | M18: 138.97708 | N18: 165.1896 | O18: 147.15346 | P18: 120.15112
A19: Concours de l'État | B19: 430.07553 | C19: 349.38571 | D19: 281.04959 | E19: 233.8071 | F19: 213.12879 | G19: 193.81041 | H19: 163.96411 | I19: 132.43285 | J19: 146.65575 | K19: 117.2609 | L19: - | M19: 208.72769 | N19: 136.41694 | O19: 186.17204 | P19: 220.77712
... A45: Dette au 31 décembre (12) | B45: 542.87091 | C45: 940.40337 | D45: 778.14866 | E45: 871.20932 | F45: 824.14615 | G45: 888.2112 | H45: 880.95911 | I45: 912.35998 | J45: 1194.5145 | K45: 1555.706 | L45: - | M45: 861.15979 | N45: 1104.2124 | O45: 936.97439 | P45: 922.65384
A46: Ratios
A47: R1 : Dépenses réelles de fonctionnement (DRF) (d) / habitant «DGF» | B47: 988.66934 | C47: 999.07544 | D47: 963.28077 | E47: 961.8634 | F47: 1021.7244 | G47: 1094.295 | H47: 1116.6707 | I47: 1195.7651 | J47: 1204.0631 | K47: 1323.125 | L47: - | M47: 1039.7411 | N47: 1214.3623 | O47: 1094.2101 | P47: 1129.889
A48: R2 : Produit des impositions directes hors fiscalité reversée / habitant «DGF» | B48: 335.11133 | C48: 425.88221 | D48: 470.87614 | E48: 555.66529 | F48: 643.90731 | G48: 698.71358 | H48: 754.15098 | I48: 825.0497 | J48: 878.95169 | K48: 835.14153 | L48: - | M48: 645.29153 | N48: 848.22345 | O48: 708.59141 | P48: 625.13533
A49: R2 bis : Produit des impositions directes y compris fiscalité reversée / habitant «DGF» | B49: 464.02318 | C49: 495.1353 | D49: 528.40343 | E49: 601.47471 | F49: 707.9497 | G49: 759.65854 | H49: 817.53897 | I49: 910.66906 | J49: 914.74788 | K49: 876.59413 | L49: - | M49: 703.65408 | N49: 908.26058 | O49: 767.47631 | P49: 762.76738
A50: R3 : Recettes réelles de fonctionnement (RRF) / habitant «DGF» | B50: 1407.2928 | C50: 1346.8158 | D50: 1261.7149 | E50: 1229.877 | F50: 1293.9155 | G50: 1400.1497 | H50: 1406.348 | I50: 1459.3622 | J50: 1444.8777 | K50: 1450.8609 | L50: - | M50: 1324.3991 | N50: 1452.4433 | O50: 1364.3395 | P50: 1329.4513
A51: R4 : Dépenses d'équipement brutes (e) / habitant «DGF» | B51: 599.65851 | C51: 604.8239 | D51: 502.41168 | E51: 503.32764 | F51: 485.47578 | G51: 491.68584 | H51: 462.16775 | I51: 464.97469 | J51: 506.81801 | K51: 317.2722 | L51: - | M51: 488.32178 | N51: 464.38267 | O51: 480.85453 | P51: 381.33041
A52: R5 : Dette / habitant «DGF» | B52: 542.87091 | C52: 940.40337 | D52: 778.14866 | E52: 871.20932 | F52: 824.14615 | G52: 888.2112 | H52: 880.95911 | I52: 912.35998 | J52: 1194.5145 | K52: 1555.706 | L52: - | M52: 861.15979 | N52: 1104.2124 | O52: 936.97439 | P52: 922.65384
A53: R6 : DGF / habitant «DGF» | B53: 241.79368 | C53: 210.80743 | D53: 188.51776 | E53: 182.34477 | F53: 169.15715 | G53: 155.4016 | H53: 134.01809 | I53: 108.81876 | J53: 126.75322 | K53: 106.76053 | L53: - | M53: 163.00132 | N53: 115.88218 | O53: 148.3036 | P53: 168.82118
A54: (a) Les habitants «DGF» sont comptés selon la population «DGF» en 2024 - année de référence 2021.
A55: (b) Les communes touristiques concernent uniquement la France métropolitaine.
A56: (c) Les strates de population sont calculées avec la population totale recensée par l'Insee en 2024 - année de référence 2021.
A57: (d) Diminuées des travaux en régie.
A58: (e) C'est-à-dire y compris les travaux en régie, les travaux effectués d'office pour le compte de tiers, les opérations di'nvestissement sur établissements d'enseignement et les opérations sous mandat.
A59: Lecture : pour l'ensemble des communes touristiques de moins de 100 habitants, les achats et charges externes représentent 351 € par « habitant DGF».
A60: Source : DGFiP-Comptes de gestion ; budgets principaux - opérations réelles. Calculs DGCL. Montants calculés hors gestion active de la dette.
A62: T 4.1.b - Structures des dépenses et des recettes des communes touristiques (a) par strate de population (b) en 2024 (France métropolitaine)
P63: en %
B64: Moins | C64: De 100 | D64: De 200 | E64: De 500 | F64: De 2 000 | G64: De 3 500 | H64: De 5 000 | I64: De 10 000 | J64: De 20 000 | K64: De 50 000 | L64: 100000 | M64: Communes | N64: Communes de | O64: Ensemble | P64: Ensemble des
A65: Hors gestion active de la dette | B65: de 100 | C65: à moins de | D65: à moins de | E65: à moins de | F65: à moins de | G65: à moins de | H65: à moins de | I65: à moins de | J65: à moins de | K65: à moins de | L65: habitants | M65: de moins | N65: de 10 000 hab. | O65: des | P65: communes en
A66: En % | B66: habitants | C66: 200 hab. | D66: 500 hab. | E66: 2 000 hab. | F66: 3 500 hab. | G66: 5 000 hab. | H66: 10 000 hab. | I66: 20 000 hab. | J66: 50 000 hab. | K66: 100 000 hab. | L66: et plus | M66: de 10 000 hab. | N66: et plus | O66: communes | P66: France métropolitaine
A67: Structure de fonctionnement
A68: DÉPENSES DE FONCTIONNEMENT | B68: =B8/B$8 -> 1 | C68: =C8/C$8 -> 1 | D68: =D8/D$8 -> 1 | E68: =E8/E$8 -> 1 | F68: =F8/F$8 -> 1 | G68: =G8/G$8 -> 1 | H68: =H8/H$8 -> 1 | I68: =I8/I$8 -> 1 | ... K68: =K8/K$8 -> 1 | L68: - | M68: =M8/M$8 -> 1 | N68: =N8/N$8 -> 1 | O68: =O8/O$8 -> 1 | P68: =P8/P$8 -> 1
A69: Achats et charges externes | B69: =B9/B$8 -> 0.3538696 | C69: =C9/C$8 -> 0.38013908 | D69: =D9/D$8 -> 0.3779078 | E69: =E9/E$8 -> 0.34652517 | F69: =F9/F$8 -> 0.32874866 | G69: =G9/G$8 -> 0.30889029 | H69: =H9/H$8 -> 0.28707308 | I69: =I9/I$8 -> 0.26235025 | ... K69: =K9/K$8 -> 0.20203424 | L69: - | M69: =M9/M$8 -> 0.32092095 | N69: =N9/N$8 -> 0.2539768 | O69: =O9/O$8 -> 0.29774145 | P69: =P9/P$8 -> 0.26380623
A70: Frais de personnel | B70: =B10/B$8 -> 0.31749521 | C70: =C10/C$8 -> 0.34616639 | D70: =D10/D$8 -> 0.36674114 | E70: =E10/E$8 -> 0.41929565 | F70: =F10/F$8 -> 0.4792639 | G70: =G10/G$8 -> 0.51623083 | H70: =H10/H$8 -> 0.55169404 | I70: =I10/I$8 -> 0.57649216 | ... K70: =K10/K$8 -> 0.6075978 | L70: - | M70: =M10/M$8 -> 0.48373023 | N70: =N10/N$8 -> 0.57513306 | O70: =O10/O$8 -> 0.51537859 | P70: =P10/P$8 -> 0.53555838
A71: Charges financières | B71: =B11/B$8 -> 0.014212794 | C71: =C11/C$8 -> 0.027782303 | D71: =D11/D$8 -> 0.02068826 | E71: =E11/E$8 -> 0.024204116 | F71: =F11/F$8 -> 0.02119435 | G71: =G11/G$8 -> 0.01960261 | H71: =H11/H$8 -> 0.02161694 | I71: =I11/I$8 -> 0.018669307 | ... K71: =K11/K$8 -> 0.037692855 | L71: - | M71: =M11/M$8 -> 0.02178968 | N71: =N11/N$8 -> 0.024327332 | O71: =O11/O$8 -> 0.022668345 | P71: =P11/P$8 -> 0.020882901
A72: Dépenses d'intervention | B72: =B12/B$8 -> 0.14424766 | C72: =C12/C$8 -> 0.12842315 | D72: =D12/D$8 -> 0.14671542 | E72: =E12/E$8 -> 0.14110207 | F72: =F12/F$8 -> 0.12129313 | G72: =G12/G$8 -> 0.11143574 | H72: =H12/H$8 -> 0.1017973 | I72: =I12/I$8 -> 0.11095806 | ... K72: =K12/K$8 -> 0.12415798 | L72: - | M72: =M12/M$8 -> 0.12035732 | N72: =N12/N$8 -> 0.11696535 | O72: =O12/O$8 -> 0.11918285 | P72: =P12/P$8 -> 0.13986697
A73: Autres dépenses de fonctionnement | B73: =B13/B$8 -> 0.17017474 | C73: =C13/C$8 -> 0.11748907 | D73: =D13/D$8 -> 0.08794738 | E73: =E13/E$8 -> 0.068872995 | F73: =F13/F$8 -> 0.049499966 | G73: =G13/G$8 -> 0.043840528 | H73: =H13/H$8 -> 0.037818647 | I73: =I13/I$8 -> 0.031530225 | ... K73: =K13/K$8 -> 0.028517123 | L73: - | M73: =M13/M$8 -> 0.053201816 | N73: =N13/N$8 -> 0.029597459 | O73: =O13/O$8 -> 0.045028775 | P73: =P13/P$8 -> 0.039885529
A74: RECETTES DE FONCTIONNEMENT | B74: =B14/B$14 -> 1 | C74: =C14/C$14 -> 1 | D74: =D14/D$14 -> 1 | E74: =E14/E$14 -> 1 | F74: =F14/F$14 -> 1 | G74: =G14/G$14 -> 1 | H74: =H14/H$14 -> 1 | I74: =I14/I$14 -> 1 | ... K74: =K14/K$14 -> 1 | L74: - | M74: =M14/M$14 -> 1 | N74: =N14/N$14 -> 1 | O74: =O14/O$14 -> 1 | P74: =P14/P$14 -> 1
A75: Impôts et taxes | B75: =B15/B$14 -> 0.41480818 | C75: =C15/C$14 -> 0.43553476 | D75: =D15/D$14 -> 0.50139134 | E75: =E15/E$14 -> 0.58086889 | F75: =F15/F$14 -> 0.63981138 | G75: =G15/G$14 -> 0.66664671 | H75: =H15/H$14 -> 0.70057453 | I75: =I15/I$14 -> 0.74230541 | ... K75: =K15/K$14 -> 0.72997329 | L75: - | M75: =M15/M$14 -> 0.63623656 | N75: =N15/N$14 -> 0.73906512 | O75: =O15/O$14 -> 0.67038281 | P75: =P15/P$14 -> 0.66412251
A76: - Impôts locaux | B76: =B16/B$14 -> 0.32972753 | C76: =C16/C$14 -> 0.36763402 | D76: =D16/D$14 -> 0.41879782 | E76: =E16/E$14 -> 0.48905272 | F76: =F16/F$14 -> 0.5471375 | G76: =G16/G$14 -> 0.54255522 | H76: =H16/H$14 -> 0.58132054 | I76: =I16/I$14 -> 0.62401853 | ... K76: =K16/K$14 -> 0.60418897 | L76: - | M76: =M16/M$14 -> 0.53130062 | N76: =N16/N$14 -> 0.6253329 | O76: =O16/O$14 -> 0.56252589 | P76: =P16/P$14 -> 0.57374603
A77: (dont: fiscalité reversée) | B77: =B17/B$14 -> 0.12929066 | C77: =C17/C$14 -> 0.076919897 | D77: =D17/D$14 -> 0.068600219 | E77: =E17/E$14 -> 0.058175012 | F77: =F17/F$14 -> 0.064362306 | G77: =G17/G$14 -> 0.060930186 | H77: =H17/H$14 -> 0.060000707 | I77: =I17/I$14 -> 0.078534933 | ... K77: =K17/K$14 -> 0.037389262 | L77: - | M77: =M17/M$14 -> 0.061612237 | N77: =N17/N$14 -> 0.056863172 | O77: =O17/O$14 -> 0.060035216 | P77: =P17/P$14 -> 0.11546279
A78: - Autres impôts et taxes | B78: =B18/B$14 -> 0.085080653 | C78: =C18/C$14 -> 0.067900742 | D78: =D18/D$14 -> 0.082593521 | E78: =E18/E$14 -> 0.091816168 | F78: =F18/F$14 -> 0.092673878 | G78: =G18/G$14 -> 0.12409149 | H78: =H18/H$14 -> 0.11925398 | I78: =I18/I$14 -> 0.11828688 | ... K78: =K18/K$14 -> 0.12578432 | L78: - | M78: =M18/M$14 -> 0.10493595 | N78: =N18/N$14 -> 0.11373222 | O78: =O18/O$14 -> 0.10785692 | P78: =P18/P$14 -> 0.090376473
A79: Concours de l'État | B79: =B19/B$14 -> 0.30560487 | C79: =C19/C$14 -> 0.25941611 | D79: =D19/D$14 -> 0.22275206 | E79: =E19/E$14 -> 0.19010608 | F79: =F19/F$14 -> 0.16471615 | G79: =G19/G$14 -> 0.13842121 | H79: =H19/H$14 -> 0.11658857 | I79: =I19/I$14 -> 0.090747075 | ... K79: =K19/K$14 -> 0.080821606 | L79: - | M79: =M19/M$14 -> 0.1576018 | N79: =N19/N$14 -> 0.093922389 | O79: =O19/O$14 -> 0.1364558 | P79: =P19/P$14 -> 0.16606635
A80: - DGF | B80: =B20/B$14 -> 0.17181476 | C80: =C20/C$14 -> 0.15652284 | D80: =D20/D$14 -> 0.14941391 | E80: =E20/E$14 -> 0.1482626 | F80: =F20/F$14 -> 0.13073276 | G80: =G20/G$14 -> 0.11098928 | H80: =H20/H$14 -> 0.095295113 | I80: =I20/I$14 -> 0.074565974 | ... K80: =K20/K$14 -> 0.073584267 | L80: - | M80: =M20/M$14 -> 0.12307568 | N80: =N20/N$14 -> 0.079784306 | O80: =O20/O$14 -> 0.10869992 | P80: =P20/P$14 -> 0.12698561
A81: - Autres dotations | B81: =B21/B$14 -> 0.043519864 | C81: =C21/C$14 -> 0.020846456 | D81: =D21/D$14 -> 0.010360056 | E81: =E21/E$14 -> 0.0033742011 | F81: =F21/F$14 -> 0.0028069559 | G81: =G21/G$14 -> 0.0019831717 | H81: =H21/H$14 -> 0.0019120459 | I81: =I21/I$14 -> 0.0015834469 | ... K81: =K21/K$14 -> 0.0041998778 | L81: - | M81: =M21/M$14 -> 0.003340186 | N81: =N21/N$14 -> 0.0021125377 | O81: =O21/O$14 -> 0.0029325212 | P81: =P21/P$14 -> 0.0045020344
A82: - Péréquation et compensations fiscales | B82: =B22/B$14 -> 0.090270244 | C82: =C22/C$14 -> 0.082046821 | D82: =D22/D$14 -> 0.062978092 | E82: =E22/E$14 -> 0.038469276 | F82: =F22/F$14 -> 0.031176433 | G82: =G22/G$14 -> 0.025448757 | H82: =H22/H$14 -> 0.019381416 | I82: =I22/I$14 -> 0.014597654 | ... K82: =K22/K$14 -> 0.0030374612 | L82: - | M82: =M22/M$14 -> 0.03118594 | N82: =N22/N$14 -> 0.012025545 | O82: =O22/O$14 -> 0.024823353 | P82: =P22/P$14 -> 0.034578704
A83: Subventions reçues et participations | B83: =B23/B$14 -> 0.017956103 | C83: =C23/C$14 -> 0.023126918 | D83: =D23/D$14 -> 0.026968841 | E83: =E23/E$14 -> 0.027315439 | F83: =F23/F$14 -> 0.031412139 | G83: =G23/G$14 -> 0.031362516 | H83: =H23/H$14 -> 0.037821253 | I83: =I23/I$14 -> 0.038470766 | ... K83: =K23/K$14 -> 0.031318956 | L83: - | M83: =M23/M$14 -> 0.031740467 | N83: =N23/N$14 -> 0.034307492 | O83: =O23/O$14 -> 0.032592898 | P83: =P23/P$14 -> 0.042669357
A84: Ventes de biens et services | B84: =B24/B$14 -> 0.10777816 | C84: =C24/C$14 -> 0.11049601 | D84: =D24/D$14 -> 0.12731467 | E84: =E24/E$14 -> 0.10666276 | F84: =F24/F$14 -> 0.083026087 | G84: =G24/G$14 -> 0.10246866 | H84: =H24/H$14 -> 0.094705597 | I84: =I24/I$14 -> 0.090456496 | ... K84: =K24/K$14 -> 0.12310755 | L84: - | M84: =M24/M$14 -> 0.098599841 | N84: =N24/N$14 -> 0.095794845 | O84: =O24/O$14 -> 0.097668387 | P84: =P24/P$14 -> 0.081465168
A85: Autres recettes de fonctionnement | B85: =B25/B$14 -> 0.15385269 | C85: =C25/C$14 -> 0.1714262 | D85: =D25/D$14 -> 0.12157309 | E85: =E25/E$14 -> 0.095046831 | F85: =F25/F$14 -> 0.081034239 | G85: =G25/G$14 -> 0.061100909 | H85: =H25/H$14 -> 0.050310049 | I85: =I25/I$14 -> 0.038020252 | ... K85: =K25/K$14 -> 0.034778599 | L85: - | M85: =M25/M$14 -> 0.075821326 | N85: =N25/N$14 -> 0.036910153 | O85: =O25/O$14 -> 0.062900105 | P85: =P25/P$14 -> 0.045676617
A86: Structure d'investissement | L86: -
A87: DÉPENSES D'INVESTISSEMENT hors remboursements | B87: =B28/B$28 -> 1 | C87: =C28/C$28 -> 1 | D87: =D28/D$28 -> 1 | E87: =E28/E$28 -> 1 | F87: =F28/F$28 -> 1 | G87: =G28/G$28 -> 1 | H87: =H28/H$28 -> 1 | I87: =I28/I$28 -> 1 | ... K87: =K28/K$28 -> 1 | L87: - | M87: =M28/M$28 -> 1 | N87: =N28/N$28 -> 1 | O87: =O28/O$28 -> 1 | P87: =P28/P$28 -> 1
A88: Dépenses d'équipement | B88: =B29/B$28 -> 0.9416232 | C88: =C29/C$28 -> 0.95795936 | D88: =D29/D$28 -> 0.91856188 | E88: =E29/E$28 -> 0.93657368 | F88: =F29/F$28 -> 0.92227473 | G88: =G29/G$28 -> 0.90862866 | H88: =H29/H$28 -> 0.89955542 | I88: =I29/I$28 -> 0.91137998 | ... K88: =K29/K$28 -> 0.80211208 | L88: - | M88: =M29/M$28 -> 0.9185396 | N88: =N29/N$28 -> 0.90374925 | O88: =O29/O$28 -> 0.91407775 | P88: =P29/P$28 -> 0.90955037
A89: Subventions d'équipement versées | B89: =B30/B$28 -> 0.019588576 | C89: =C30/C$28 -> 0.023613468 | D89: =D30/D$28 -> 0.041552423 | E89: =E30/E$28 -> 0.029778894 | F89: =F30/F$28 -> 0.041564397 | G89: =G30/G$28 -> 0.046389438 | H89: =H30/H$28 -> 0.062682491 | I89: =I30/I$28 -> 0.046245349 | ... K89: =K30/K$28 -> 0.11969904 | L89: - | M89: =M30/M$28 -> 0.044051525 | N89: =N30/N$28 -> 0.058402951 | O89: =O30/O$28 -> 0.048380967 | P89: =P30/P$28 -> 0.057863799
A90: Autres depenses d'investissement | B90: =B31/B$28 -> 0.038788228 | C90: =C31/C$28 -> 0.018427172 | D90: =D31/D$28 -> 0.039885693 | E90: =E31/E$28 -> 0.033647425 | F90: =F31/F$28 -> 0.036160872 | G90: =G31/G$28 -> 0.044981901 | H90: =H31/H$28 -> 0.037762092 | I90: =I31/I$28 -> 0.042374672 | ... K90: =K31/K$28 -> 0.078188884 | L90: - | M90: =M31/M$28 -> 0.037408872 | N90: =N31/N$28 -> 0.037847795 | O90: =O31/O$28 -> 0.037541284 | P90: =P31/P$28 -> 0.032585829
A91: RECETTES D'INVESTISSEMENT hors emprunts | B91: =B32/B$32 -> 1 | C91: =C32/C$32 -> 1 | D91: =D32/D$32 -> 1 | E91: =E32/E$32 -> 1 | F91: =F32/F$32 -> 1 | G91: =G32/G$32 -> 1 | H91: =H32/H$32 -> 1 | I91: =I32/I$32 -> 1 | ... K91: =K32/K$32 -> 1 | L91: - | M91: =M32/M$32 -> 1 | N91: =N32/N$32 -> 1 | O91: =O32/O$32 -> 1 | P91: =P32/P$32 -> 1
A92: FCTVA | B92: =B33/B$32 -> 0.26180943 | C92: =C33/C$32 -> 0.19644222 | D92: =D33/D$32 -> 0.19864553 | E92: =E33/E$32 -> 0.20607219 | F92: =F33/F$32 -> 0.16592436 | G92: =G33/G$32 -> 0.24160008 | H92: =H33/H$32 -> 0.23208347 | I92: =I33/I$32 -> 0.27041627 | ... K92: =K33/K$32 -> 0.12893785 | L92: - | M92: =M33/M$32 -> 0.2064874 | N92: =N33/N$32 -> 0.23534598 | O92: =O33/O$32 -> 0.21379932 | P92: =P33/P$32 -> 0.24609758
A93: Dotations et Subventions d'équipement | B93: =B34/B$32 -> 0.68800046 | C93: =C34/C$32 -> 0.66087858 | D93: =D34/D$32 -> 0.6838641 | E93: =E34/E$32 -> 0.59640123 | F93: =F34/F$32 -> 0.402954 | G93: =G34/G$32 -> 0.47889586 | H93: =H34/H$32 -> 0.55050348 | I93: =I34/I$32 -> 0.52111891 | ... K93: =K34/K$32 -> 0.32614034 | L93: - | M93: =M34/M$32 -> 0.52294973 | N93: =N34/N$32 -> 0.4469495 | O93: =O34/O$32 -> 0.5036935 | P93: =P34/P$32 -> 0.56153022
A94: Autres recettes d'investissement | B94: =B35/B$32 -> 0.050190114 | C94: =C35/C$32 -> 0.1426792 | D94: =D35/D$32 -> 0.11749038 | E94: =E35/E$32 -> 0.19752658 | F94: =F35/F$32 -> 0.43112164 | G94: =G35/G$32 -> 0.27950406 | H94: =H35/H$32 -> 0.21741305 | I94: =I35/I$32 -> 0.20846481 | ... K94: =K35/K$32 -> 0.54492181 | L94: - | M94: =M35/M$32 -> 0.27056287 | N94: =N35/N$32 -> 0.31770452 | O94: =O35/O$32 -> 0.28250718 | P94: =P35/P$32 -> 0.1923722
A95: Ratios
A96: Epargne brute / RRF (Taux d'épargne brute) | B96: 0.29460247 | C96: 0.2570423 | D96: 0.23598831 | E96: 0.21650579 | F96: 0.20684248 | G96: 0.21410976 | H96: 0.20274172 | I96: 0.17660148 | J96: 0.1632145 | K96: 0.087778825 | L96: - | M96: 0.21204803 | N96: 0.16057415 | O96: 0.19495512 | P96: 0.14830093
A97: R7 : Dépenses de personnel / DRF | B97: 0.31749521 | C97: 0.34616639 | D97: 0.36674114 | E97: 0.41929565 | F97: 0.4792639 | G97: 0.51623082 | H97: 0.55169404 | I97: 0.57649216 | J97: 0.56314825 | K97: 0.6075978 | L97: - | M97: 0.48373023 | N97: 0.57513306 | O97: 0.51537859 | P97: 0.53555838
A98: R9 : Marge d'autofinancement courant (MAC)=(DRF+Remboursement de dette) / RRF | B98: 0.77859018 | C98: 0.86107072 | D98: 0.8531705 | E98: 0.86526998 | F98: 0.86068678 | G98: 0.849737 | H98: 0.86293649 | I98: 0.88321099 | J98: 0.91463755 | K98: 1.0106509 | L98: - | M98: 0.85961758 | N98: 0.91116063 | O98: 0.87673347 | P98: 0.91681483
A99: R10 : Dépenses d'équipement brutes (c) / RRF (Taux d'équipement) | B99: 0.42610785 | C99: 0.44907694 | D99: 0.39819748 | E99: 0.40925037 | F99: 0.37519898 | G99: 0.35116662 | H99: 0.32862973 | I99: 0.318615 | J99: 0.3507688 | K99: 0.21867858 | L99: - | M99: 0.36871194 | N99: 0.31972516 | O99: 0.35244492 | P99: 0.28683294
A100: R11 : Dette / RRF (taux d'endettement) | B100: 0.38575548 | C100: 0.69824202 | D100: 0.61673892 | E100: 0.70837107 | F100: 0.63693969 | G100: 0.63436874 | H100: 0.62641617 | I100: 0.62517721 | J100: 0.82672362 | K100: 1.0722641 | L100: - | M100: 0.65022678 | N100: 0.76024477 | O100: 0.68676042 | P100: 0.69401104
A101: Dette / Epargne brute (Délai de désendettement, en années) | B101: 1.3094102 | C101: 2.7164479 | D101: 2.6134299 | E101: 3.2718343 | F101: 3.0793466 | G101: 2.9628202 | H101: 3.0897251 | I101: 3.5400452 | J101: 5.0652583 | K101: 12.215521 | L101: - | M101: 3.0664127 | N101: 4.7345402 | O101: 3.5226591 | P101: 4.6797484
A102: (a) Les communes touristiques concernent uniquement la France métropolitaine.
A103: (b) Les strates de population sont calculées avec la population totale recensée par l'Insee en 2024 - année de référence 2021.
A104: (c) C'est-à-dire y compris les travaux en régie, les travaux effectués d'office pour le compte de tiers, les opérations di'nvestissement sur établissements d'enseignement et les opérations sous mandat.
A105: Lecture : pour l'ensemble des communes touristiques de moins de 100 habitants, les achats et charges externes représentent 35,4 % des dépenses de fonctionnement.
A106: Source : DGFiP-Comptes de gestion ; budgets principaux - opérations réelles. Calculs DGCL. Montants calculés hors gestion active de la dette.
A108: T 4.1.c - Évolution 2024 / 2023 à champ constant (a) : communes touristiques (b) (France métropolitaine)
A110: Hors gestion active de la dette | B110: Moins | C110: De 100 | D110: De 200 | E110: De 500 | F110: De 2 000 | G110: De 3 500 | H110: De 5 000 | I110: De 10 000 | J110: De 20 000 | K110: De 50 000 | L110: 100000 | M110: Communes | N110: Communes de | O110: Ensemble | P110: Ensemble des
A111: calculs sur les montants en € courant | B111: de 100 | C111: à moins de | D111: à moins de | E111: à moins de | F111: à moins de | G111: à moins de | H111: à moins de | I111: à moins de | J111: à moins de | K111: à moins de | L111: habitants | M111: de moins | N111: de 10 000 hab. | O111: des | P111: communes en
A112: Evolutions en % | B112: habitants | C112: 200 hab. | D112: 500 hab. | E112: 2 000 hab. | F112: 3 500 hab. | G112: 5 000 hab. | H112: 10 000 hab. | I112: 20 000 hab. | J112: 50 000 hab. | K112: 100 000 hab. | L112: et plus | M112: de 10 000 hab. | N112: et plus | O112: communes | P112: France métropolitaine
A113: Budget de fonctionnement
A114: DÉPENSES DE FONCTIONNEMENT | B114: 2.3049705 | C114: 5.9357858 | D114: 5.9779353 | E114: 4.7364075 | F114: 4.4808797 | G114: 1.8635672 | H114: 5.1068348 | I114: 4.42334 | J114: 2.8327778 | K114: 4.6938908 | L114: - | M114: 4.2834016 | N114: 3.809187 | O114: 4.1187146 | P114: 4.1179418
A115: Achats et charges externes | B115: 3.2794456 | C115: 7.0995287 | D115: 7.9774129 | E115: 7.503076 | F115: 5.5783409 | G115: 2.9701255 | H115: 4.6088007 | I115: 3.9002094 | J115: 2.0711389 | K115: 2.9176133 | L115: - | M115: 5.4980275 | N115: 3.0319432 | O115: 4.7574556 | P115: 4.0108693
A116: Frais de personnel | B116: 4.3236813 | C116: 4.3157065 | D116: 5.2879343 | E116: 5.7534015 | F116: 5.7111005 | G116: 5.295751 | H116: 5.1388886 | I116: 4.7172874 | J116: 5.4653197 | K116: 4.3108981 | L116: - | M116: 5.4217587 | N116: 4.9558591 | O116: 5.2412471 | P116: 4.3575204
A117: Charges financières | B117: 24.274513 | C117: -0.24046042 | D117: 9.65332 | E117: 8.7162395 | F117: 4.6285217 | G117: 4.5451195 | H117: 4.7053813 | I117: 1.6484292 | J117: 14.85543 | K117: 7.4468801 | L117: - | M117: 5.9294205 | N117: 8.319956 | O117: 6.8053027 | P117: 9.3167024
A118: Dépenses d'intervention | B118: 1.6586588 | C118: 22.355341 | D118: 2.8219325 | E118: 11.147128 | F118: 10.789082 | G118: 6.3845113 | H118: 8.4521781 | I118: 5.5408939 | J118: 3.9603083 | K118: 3.4895416 | L118: - | M118: 9.1292372 | N118: 4.5874583 | O118: 7.5422966 | P118: 4.6011816
A119: Autres dépenses de fonctionnement | B119: -3.9478387 | C119: -5.5361848 | D119: 5.0407549 | E119: -20.597854 | F119: -20.95783 | G119: -35.489563 | H119: 0.18320063 | I119: 1.3298271 | J119: -35.114792 | K119: 33.761005 | L119: - | M119: -18.173781 | N119: -14.29233 | O119: -17.321619 | P119: -2.246826
A120: RECETTES DE FONCTIONNEMENT | B120: 4.6486558 | C120: 4.9741913 | D120: 6.6447815 | E120: 5.5327963 | F120: 8.2481411 | G120: 4.8473291 | H120: 6.7768246 | I120: 4.0572952 | J120: 2.2473636 | K120: 3.4924278 | L120: - | M120: 6.3537183 | N120: 3.2490481 | O120: 5.3022497 | P120: 2.998609
A121: Impôts et taxes | B121: -1.0891088 | C121: 2.3667517 | D121: 6.020911 | E121: 6.9765488 | F121: 7.4840048 | G121: 7.3173016 | H121: 7.1445246 | I121: 4.4257408 | J121: 2.6018673 | K121: 3.0784801 | L121: - | M121: 7.0979747 | N121: 3.5213052 | O121: 5.7602686 | P121: 2.5542568
A122: - Impôts locaux | B122: 4.3998322 | C122: 5.2930494 | D122: 9.0362417 | E122: 8.9125582 | F122: 9.5276782 | G122: 9.6377562 | H122: 9.7671701 | I122: 6.5925803 | J122: 5.3134816 | K122: 4.6545961 | L122: - | M122: 9.4035045 | N122: 5.8389506 | O122: 8.0600503 | P122: 4.376758
A123: (dont: fiscalité reversée) | B123: 0.99172739 | C123: 0.47277006 | D123: 3.0610933 | E123: -1.0782627 | F123: 3.2101679 | G123: 3.0677518 | H123: -1.4584941 | I123: 0.77406972 | J123: -1.3105874 | K123: -4.5900471 | L123: - | M123: 0.79272834 | N123: -0.22499199 | O123: 0.47039958 | P123: 0.87048807
A124: - Autres impôts et taxes | B124: -17.831533 | C124: -11.022068 | D124: -7.0174749 | E124: -2.276114 | F124: -3.1815818 | G124: -1.7723771 | H124: -4.0326817 | I124: -5.6883327 | J124: -11.203782 | K124: -3.8751535 | L124: - | M124: -3.2274454 | N124: -7.6033245 | O124: -4.8060847 | P124: -7.674875
A125: Concours de l'État | B125: 16.924068 | C125: 9.9168398 | D125: 7.2121346 | E125: 5.1844894 | F125: 4.2593021 | G125: 2.8384542 | H125: 3.5701267 | I125: 2.7875705 | J125: 1.392989 | K125: 0.084786985 | L125: - | M125: 4.570702 | N125: 1.890979 | O125: 3.9458635 | P125: 3.1945915
... A131: Autres recettes de fonctionnement | B131: 15.79165 | C131: 9.286931 | D131: 11.05169 | E131: 1.8440039 | F131: 33.064285 | G131: -14.920901 | H131: 18.031469 | I131: -4.7339369 | J131: -12.280985 | K131: 6.2813942 | L131: - | M131: 8.094565 | N131: -6.8385686 | O131: 4.8205185 | P131: 7.8138927
A132: Budget d'investissement
A133: DÉPENSES D'INVESTISSEMENT hors remboursements | B133: 0.97814771 | C133: 14.062258 | D133: 2.9281225 | E133: 14.100046 | F133: 20.666531 | G133: 18.213462 | H133: 9.1178954 | I133: 14.486662 | J133: 18.337472 | K133: -14.573422 | L133: - | M133: 14.117647 | N133: 12.610273 | O133: 13.658679 | P133: 10.163335
A134: Dépenses d'équipement | B134: 0.40484281 | C134: 12.45057 | D134: 7.4501103 | E134: 14.282761 | F134: 21.918212 | G134: 18.378278 | H134: 7.0944208 | I134: 12.78438 | J134: 18.29 | K134: 6.8380626 | L134: - | M134: 14.168178 | N134: 14.668261 | O134: 14.316878 | P134: 10.725449
A135: Subventions d'équipement versées | B135: -10.845476 | C135: 138.018 | D135: -39.967895 | E135: 9.2580241 | F135: -9.4514047 | G135: 6.9036989 | H135: 42.661884 | I135: 22.135614 | J135: 42.527743 | K135: 10.383537 | L135: - | M135: 9.1143043 | N135: 27.709615 | O135: 15.224005 | P135: 2.2363989
...

Sheet T 4.2
A1: T 4.2.a - Dépenses et recettes par «habitant DGF» (a) des communes touristiques (b) du littoral maritime par strate de population en 2024 (France métropolitaine)
P3: en € / habitant «DGF»
B4: Moins | C4: De 100 | D4: De 200 | E4: De 500 | F4: De 2 000 | G4: De 3 500 | H4: De 5 000 | I4: De 10 000 | J4: De 20 000 | K4: De 50 000 | L4: 100000 | M4: Communes | N4: Communes de | O4: Ensemble | P4: Ensemble des
A5: Hors gestion active de la dette | B5: de 100 | C5: à moins de | D5: à moins de | E5: à moins de | F5: à moins de | G5: à moins de | H5: à moins de | I5: à moins de | J5: à moins de | K5: à moins de | L5: habitants | M5: de moins | N5: de 10 000 hab. | O5: des | P5: communes en
A6: en € / habitant «DGF» | B6: habitants (*) | C6: 200 hab. | D6: 500 hab. | E6: 2 000 hab. | F6: 3 500 hab. | G6: 5 000 hab. | H6: 10 000 hab. | I6: 20 000 hab. | J6: 50 000 hab. | K6: 100 000 hab. | L6: et plus | M6: de 10 000 hab. | N6: et plus | O6: communes | P6: France métropolitaine
A8: DÉPENSES DE FONCTIONNEMENT (1) | B8: 2590.8553 | C8: 1091.0952 | D8: 896.45335 | E8: 862.48659 | F8: 882.22042 | G8: 1081.2336 | H8: 1107.8834 | I8: 1157.7407 | J8: 1200.2951 | K8: 1323.506 | L8: - | M8: 1009.9012 | N8: 1199.9033 | O8: 1094.5086 | P8: 1132.2924
A9: Achats et charges externes | B9: 590.08882 | C9: 397.43667 | D9: 307.32507 | E9: 288.04588 | F9: 287.80515 | G9: 319.6601 | H9: 315.80696 | I9: 301.28199 | J9: 311.81463 | K9: 267.39352 | L9: - | M9: 306.22533 | N9: 300.95642 | O9: 303.8791 | P9: 298.70578
A10: Frais de personnel | B10: 1687.6971 | C10: 514.21453 | D10: 424.31133 | E10: 422.11741 | F10: 458.64046 | G10: 590.06109 | H10: 622.6036 | I10: 675.04819 | J10: 681.60527 | K10: 804.15934 | L10: - | M10: 544.09006 | N10: 696.42171 | O10: 611.92292 | P10: 606.40868
A11: Charges financières | B11: 17.187425 | C11: 18.12793 | D11: 19.51924 | E11: 15.86799 | F11: 20.863515 | G11: 21.030337 | H11: 24.227824 | I11: 23.564181 | J11: 30.765232 | K11: 49.886719 | L11: - | M11: 21.32221 | N11: 30.450674 | O11: 25.387089 | P11: 23.64555
A12: Dépenses d'intervention | B12: 116.2988 | C12: 47.578135 | D12: 72.277693 | E12: 76.343426 | F12: 71.2273 | G12: 108.85214 | H12: 108.30594 | I12: 124.49802 | J12: 144.4293 | K12: 164.32384 | L12: - | M12: 94.461646 | N12: 138.8141 | O12: 114.21167 | P12: 158.3703
A13: Autres dépenses de fonctionnement | B13: 179.58311 | C13: 113.73797 | D13: 73.020021 | E13: 60.111887 | F13: 43.683997 | G13: 41.629968 | H13: 36.939127 | I13: 33.348293 | J13: 31.680713 | K13: 37.742583 | L13: - | M13: 43.802003 | N13: 33.260347 | O13: 39.107833 | P13: 45.162082
A14: RECETTES DE FONCTIONNEMENT (2) | B14: 3587.9967 | C14: 1512.1271 | D14: 1221.0445 | E14: 1117.5522 | F14: 1125.6105 | G14: 1372.1988 | H14: 1404.1831 | I14: 1422.0532 | J14: 1435.1073 | K14: 1450.8609 | L14: - | M14: 1287.14 | N14: 1431.8208 | O14: 1351.5659 | P14: 1329.4513
A15: Impôts et taxes | B15: 1306.4611 | C15: 584.60548 | D15: 553.22136 | E15: 667.20498 | F15: 741.24463 | G15: 944.48142 | H15: 996.06431 | I15: 1091.2697 | J15: 1069.8647 | K15: 1059.0897 | L15: - | M15: 868.88528 | N15: 1077.4163 | O15: 961.74356 | P15: 882.9185
A16: - Impôts locaux | B16: 1229.3906 | C16: 487.76131 | D16: 424.32328 | E16: 559.65465 | F16: 633.6587 | G16: 766.45646 | H16: 819.02492 | I16: 916.76385 | J16: 911.99415 | K16: 876.59413 | L16: - | M16: 719.03081 | N16: 908.93685 | O16: 803.59544 | P16: 762.76738
A17: (dont : fiscalité reversée) | B17: 726.59442 | C17: 108.96845 | D17: 84.928149 | E17: 51.224473 | F17: 55.855648 | G17: 70.660311 | H17: 73.525028 | I17: 81.824437 | J17: 46.735125 | K17: 54.246616 | L17: - | M17: 65.668022 | N17: 62.730732 | O17: 64.360055 | P17: 153.50215
A18: - Autres impôts et taxes | B18: 77.070494 | C18: 96.844166 | D18: 128.89808 | E18: 107.55033 | F18: 107.58592 | G18: 178.02496 | H18: 177.03939 | I18: 174.50581 | J18: 157.8705 | K18: 182.49555 | L18: - | M18: 149.85447 | N18: 168.47944 | O18: 158.14812 | P18: 120.15112
A19: Concours de l'État | B19: 463.96839 | C19: 319.63507 | D19: 238.98961 | E19: 192.67872 | F19: 179.53681 | G19: 168.6008 | H19: 145.99875 | I19: 117.34674 | J19: 132.57811 | K19: 117.2609 | L19: - | M19: 167.83777 | N19: 123.90299 | O19: 148.27373 | P19: 220.77712
... A29: Dépenses d'équipement | B29: 1544.3317 | C29: 1053.9159 | D29: 650.44594 | E29: 480.94547 | F29: 414.0713 | G29: 457.07278 | H29: 455.30676 | I29: 440.59058 | J29: 495.13278 | K29: 304.77106 | L29: - | M29: 454.00417 | N29: 444.60271 | O29: 449.81773 | P29: 374.27713
A30: Subventions d'équipement versées | B30: , | C30: 1.4678674 | D30: 11.849157 | E30: 14.59557 | F30: 24.695798 | G30: 31.516724 | H30: 24.506111 | I30: 24.373069 | J30: 33.048359 | K30: 45.480927 | L30: - | M30: 24.522458 | N30: 31.146286 | O30: 27.47203 | P30: 23.810772
A31: Autres depenses d'investissement | B31: 5.1301073 | C31: 1.9713855 | D31: 37.029568 | E31: 10.074539 | F31: 11.825419 | G31: 20.846203 | H31: 16.617773 | I31: 17.480196 | J31: 13.23026 | K31: 29.708702 | L31: - | M31: 15.666582 | N31: 17.403923 | O31: 16.440215 | P31: 13.408966
A32: RECETTES D'INVESTISSEMENT hors emprunts (5) | B32: 775.7194 | C32: 691.63354 | D32: 343.45805 | E32: 215.48757 | F32: 186.7808 | G32: 202.94276 | H32: 215.42703 | I32: 152.31107 | J32: 202.0327 | K32: 253.01528 | L32: - | M32: 208.51295 | N32: 188.21902 | O32: 199.47612 | P32: 177.39972
A33: FCTVA | B33: 457.60601 | C33: 133.85172 | D33: 52.368021 | E33: 49.539499 | F33: 46.825709 | G33: 48.993467 | H33: 53.069304 | I33: 46.39603 | J33: 49.720683 | K33: 32.623245 | L33: - | M33: 50.420768 | N33: 45.851449 | O33: 48.386063 | P33: 43.65764
A34: Dotations et Subventions d'équipement | B34: 310.94466 | C34: 545.27482 | D34: 271.07986 | E34: 128.78616 | F34: 106.83862 | G34: 93.657844 | H34: 98.875029 | I34: 83.774301 | J34: 81.999073 | K34: 82.518489 | L34: - | M34: 106.99575 | N34: 82.828341 | O34: 96.234071 | P34: 99.615302
A35: Autres recettes d'investissement | B35: 7.1687339 | C35: 12.50701 | D35: 20.010166 | E35: 37.161916 | F35: 33.116477 | G35: 60.291446 | H35: 63.482699 | I35: 22.140737 | J35: 70.312948 | K35: 137.87354 | L35: - | M35: 51.096437 | N35: 59.539225 | O35: 54.855987 | P35: 34.126774
A36: DÉPENSES TOTALES hors remboursements (6) = (1)+(4) | B36: 4140.3171 | C36: 2148.4503 | D36: 1595.778 | E36: 1368.1022 | F36: 1332.8129 | G36: 1590.6693 | H36: 1604.3141 | I36: 1640.1845 | J36: 1741.7065 | K36: 1703.4667 | L36: - | M36: 1504.0945 | N36: 1693.0562 | O36: 1588.2386 | P36: 1543.7893
A37: RECETTES TOTALES hors emprunts (7) = (2)+(5) | B37: 4363.7161 | C37: 2203.7606 | D37: 1564.5026 | E37: 1333.0398 | F37: 1312.3913 | G37: 1575.1415 | H37: 1619.6101 | I37: 1574.3642 | J37: 1637.14 | K37: 1703.8761 | L37: - | M37: 1495.653 | N37: 1620.0398 | O37: 1551.0421 | P37: 1506.851
A38: Capacité ou besoin de financement = (7)-(6) | B38: 223.39901 | C38: 55.310285 | D38: -31.275456 | E38: -35.062413 | F38: -20.421625 | G38: -15.527808 | H38: 15.296032 | I38: -65.820284 | J38: -104.56656 | K38: 0.4094531 | L38: - | M38: -8.4415003 | N38: -73.016381 | O38: -37.196514 | P38: -36.938295
A39: Remboursements de dette (8) | B39: 50.521202 | C39: 173.79171 | D39: 117.29047 | E39: 68.457716 | F39: 72.75306 | G39: 93.373194 | H39: 93.878166 | I39: 92.020739 | J39: 113.57738 | K39: 143.18876 | L39: - | M39: 85.397811 | N39: 108.66698 | O39: 95.759505 | P39: 88.97162
A40: Emprunts (9) | B40: 0 | C40: 108.87328 | D40: 57.61406 | E40: 79.908223 | F40: 75.173614 | G40: 94.569373 | H40: 66.276204 | I40: 129.1799 | J40: 160.04257 | K40: 163.80298 | L40: - | M40: 77.315223 | N40: 147.46284 | O40: 108.55176 | P40: 101.99548
A41: Flux net de dette = (9)-(8) | B41: -50.521202 | C41: -64.91843 | D41: -59.676406 | E41: 11.450507 | F41: 2.4205535 | G41: 1.1961792 | H41: -27.601962 | I41: 37.15916 | J41: 46.465185 | K41: 20.614214 | L41: - | M41: -8.0825883 | N41: 38.795867 | O41: 12.792257 | P41: 13.023865
A42: DÉPENSES TOTALES (10)=(6)+(8) | B42: 4190.8383 | C42: 2322.2421 | D42: 1713.0685 | E42: 1436.5599 | F42: 1405.566 | G42: 1684.0425 | H42: 1698.1923 | I42: 1732.2053 | J42: 1855.2839 | K42: 1846.6554 | L42: - | M42: 1589.4923 | N42: 1801.7232 | O42: 1683.9981 | P42: 1632.7609
... A45: Dette au 31 décembre (12) | B45: 396.28573 | C45: 685.32534 | D45: 743.16119 | E45: 660.30648 | F45: 742.3935 | G45: 830.48023 | H45: 849.52496 | I45: 930.62121 | J45: 1139.7398 | K45: 1555.706 | L45: - | M45: 789.41439 | N45: 1110.5926 | O45: 932.43413 | P45: 922.65384
A46: Ratios (voir définitions en annexe 3)
A47: R1 : Dépenses réelles de fonctionnement (DRF) (c) / habitant «DGF» | B47: 2590.8553 | C47: 1089.739 | D47: 895.90611 | E47: 861.1129 | F47: 877.0351 | G47: 1074.8178 | H47: 1103.3095 | I47: 1151.3513 | J47: 1196.637 | K47: 1323.125 | L47: - | M47: 1005.2842 | N47: 1195.5548 | O47: 1090.0112 | P47: 1129.889
A48: R2 : Produit des impositions directes hors fiscalité reversée / habitant «DGF» | B48: 562.49785 | C48: 442.82479 | D48: 370.09901 | E48: 551.46246 | F48: 605.04151 | G48: 734.81022 | H48: 769.80856 | I48: 869.04601 | J48: 884.96798 | K48: 835.14153 | L48: - | M48: 684.99067 | N48: 871.04231 | O48: 767.83894 | P48: 625.13533
A49: R2 bis : Produit des impositions directes y compris fiscalité reversée / habitant «DGF» | B49: 1229.3906 | C49: 487.76131 | D49: 424.32328 | E49: 559.65465 | F49: 633.6587 | G49: 766.45646 | H49: 819.02492 | I49: 916.76385 | J49: 911.99415 | K49: 876.59413 | L49: - | M49: 719.03081 | N49: 908.93685 | O49: 803.59544 | P49: 762.76738
A50: R3 : Recettes réelles de fonctionnement (RRF) / habitant «DGF» | B50: 3587.9967 | C50: 1512.1271 | D50: 1221.0445 | E50: 1117.5522 | F50: 1125.6105 | G50: 1372.1988 | H50: 1404.1831 | I50: 1422.0532 | J50: 1435.1073 | K50: 1450.8609 | L50: - | M50: 1287.14 | N50: 1431.8208 | O50: 1351.5659 | P50: 1329.4513
A51: R4 : Dépenses d'équipement brutes (d) / habitant «DGF» | B51: 1549.4618 | C51: 1055.2721 | D51: 654.82344 | E51: 485.90704 | F51: 421.80729 | G51: 473.80545 | H51: 465.60646 | I51: 456.98024 | J51: 506.01546 | K51: 317.2722 | L51: - | M51: 464.3637 | N51: 458.05892 | O51: 461.5562 | P51: 381.33041
A52: R5 : Dette / habitant «DGF» | B52: 396.28573 | C52: 685.32534 | D52: 743.16119 | E52: 660.30648 | F52: 742.3935 | G52: 830.48023 | H52: 849.52496 | I52: 930.62121 | J52: 1139.7398 | K52: 1555.706 | L52: - | M52: 789.41439 | N52: 1110.5926 | O52: 932.43413 | P52: 922.65384
A53: R6 : DGF / habitant «DGF» | B53: 357.4485 | C53: 201.48741 | D53: 179.21785 | E53: 159.65309 | F53: 160.42043 | G53: 149.1737 | H53: 124.4547 | I53: 102.52129 | J53: 114.77587 | K53: 106.76053 | L53: - | M53: 144.9348 | N53: 108.41505 | O53: 128.67266 | P53: 168.82118
A54: (a) Les habitants «DGF» sont comptés selon la population «DGF» en 2024 - année de référence 2021.
A55: (b) Les communes touristiques concernent uniquement la France métropolitaine.
A56: (c) Diminuées des travaux en régie.
A57: (d) C'est-à-dire y compris les travaux en régie, les travaux effectués d'office pour le compte de tiers, les opérations di'nvestissement sur établissements d'enseignement et les opérations sous mandat.
A58: (*) Les forts montants pour la strate des moins de 100 habitants proviennent de la commune atypique du Mont-Saint-Michel.
A59: Lecture: les achats et charges externes des communes touristiques du littoral maritime de moins de 100 habitants représentent 590 € par «habitant DGF».
A60: Source : DGFiP-Comptes de gestion ; budgets principaux - opérations réelles. Calculs DGCL. Montants calculés hors gestion active de la dette. Strates de population calculées selon la population totale en 2024 du recensement de l'Insee (année de référence 2021).
A62: T 4.2.b - Structure des dépenses et des recettes des communes touristiques (a) du littoral maritime par strate de population en 2024 (France métropolitaine)
B64: Moins | C64: De 100 | D64: De 200 | E64: De 500 | F64: De 2 000 | G64: De 3 500 | H64: De 5 000 | I64: De 10 000 | J64: De 20 000 | K64: De 50 000 | L64: 100000 | M64: Communes | N64: Communes de | O64: Ensemble | P64: Ensemble des
A65: Hors gestion active de la dette | B65: de 100 | C65: à moins de | D65: à moins de | E65: à moins de | F65: à moins de | G65: à moins de | H65: à moins de | I65: à moins de | J65: à moins de | K65: à moins de | L65: habitants | M65: de moins | N65: de 10 000 hab. | O65: des | P65: communes en
A66: En % | B66: habitants | C66: 200 hab. | D66: 500 hab. | E66: 2 000 hab. | F66: 3 500 hab. | G66: 5 000 hab. | H66: 10 000 hab. | I66: 20 000 hab. | J66: 50 000 hab. | K66: 100 000 hab. | L66: et plus | M66: de 10 000 hab. | N66: et plus | O66: communes | P66: France métropolitaine
A67: Structure de fonctionnement
A68: DÉPENSES DE FONCTIONNEMENT | B68: =B8/B$8 -> 1 | C68: =C8/C$8 -> 1 | D68: =D8/D$8 -> 1 | E68: =E8/E$8 -> 1 | F68: =F8/F$8 -> 1 | G68: =G8/G$8 -> 1 | H68: =H8/H$8 -> 1 | I68: =I8/I$8 -> 1 | ... K68: =K8/K$8 -> 1 | L68: - | M68: =M8/M$8 -> 1 | N68: =N8/N$8 -> 1 | O68: =O8/O$8 -> 1 | P68: =P8/P$8 -> 1
A69: Achats et charges externes | B69: =B9/B$8 -> 0.22775831 | C69: =C9/C$8 -> 0.36425479 | D69: =D9/D$8 -> 0.34282327 | E69: =E9/E$8 -> 0.33397143 | F69: =F9/F$8 -> 0.32622816 | G69: =G9/G$8 -> 0.29564387 | H69: =H9/H$8 -> 0.28505431 | I69: =I9/I$8 -> 0.26023271 | ... K69: =K9/K$8 -> 0.20203424 | L69: - | M69: =M9/M$8 -> 0.30322304 | N69: =N9/N$8 -> 0.25081724 | O69: =O9/O$8 -> 0.27763975 | P69: =P9/P$8 -> 0.26380623
A70: Frais de personnel | B70: =B10/B$8 -> 0.6514054 | C70: =C10/C$8 -> 0.4712829 | D70: =D10/D$8 -> 0.47332227 | E70: =E10/E$8 -> 0.48941909 | F70: =F10/F$8 -> 0.5198706 | G70: =G10/G$8 -> 0.5457295 | H70: =H10/H$8 -> 0.56197572 | I70: =I10/I$8 -> 0.58307374 | ... K70: =K10/K$8 -> 0.6075978 | L70: - | M70: =M10/M$8 -> 0.53875571 | N70: =N10/N$8 -> 0.58039822 | O70: =O10/O$8 -> 0.55908461 | P70: =P10/P$8 -> 0.53555838
A71: Charges financières | B71: =B11/B$8 -> 0.0066338807 | C71: =C11/C$8 -> 0.016614434 | D71: =D11/D$8 -> 0.021773849 | E71: =E11/E$8 -> 0.018397956 | F71: =F11/F$8 -> 0.023648869 | G71: =G11/G$8 -> 0.019450317 | H71: =H11/H$8 -> 0.021868567 | I71: =I11/I$8 -> 0.020353591 | ... K71: =K11/K$8 -> 0.037692855 | L71: - | M71: =M11/M$8 -> 0.021113163 | N71: =N11/N$8 -> 0.025377607 | O71: =O11/O$8 -> 0.023194966 | P71: =P11/P$8 -> 0.020882901
A72: Dépenses d'intervention | B72: =B12/B$8 -> 0.044888187 | C72: =C12/C$8 -> 0.043605849 | D72: =D12/D$8 -> 0.080626273 | E72: =E12/E$8 -> 0.088515493 | F72: =F12/F$8 -> 0.080736399 | G72: =G12/G$8 -> 0.10067402 | H72: =H12/H$8 -> 0.097759326 | I72: =I12/I$8 -> 0.10753532 | ... K72: =K12/K$8 -> 0.12415798 | L72: - | M72: =M12/M$8 -> 0.093535527 | N72: =N12/N$8 -> 0.11568774 | O72: =O12/O$8 -> 0.10434972 | P72: =P12/P$8 -> 0.13986697
A73: Autres dépenses de fonctionnement | B73: =B13/B$8 -> 0.069314219 | C73: =C13/C$8 -> 0.10424202 | D73: =D13/D$8 -> 0.081454345 | E73: =E13/E$8 -> 0.069696025 | F73: =F13/F$8 -> 0.049515967 | G73: =G13/G$8 -> 0.038502287 | H73: =H13/H$8 -> 0.03334207 | I73: =I13/I$8 -> 0.028804631 | ... K73: =K13/K$8 -> 0.028517123 | L73: - | M73: =M13/M$8 -> 0.043372561 | N73: =N13/N$8 -> 0.027719191 | O73: =O13/O$8 -> 0.035730951 | P73: =P13/P$8 -> 0.039885529
A74: RECETTES DE FONCTIONNEMENT | B74: =B14/B$14 -> 1 | C74: =C14/C$14 -> 1 | D74: =D14/D$14 -> 1 | E74: =E14/E$14 -> 1 | F74: =F14/F$14 -> 1 | G74: =G14/G$14 -> 1 | H74: =H14/H$14 -> 1 | I74: =I14/I$14 -> 1 | ... K74: =K14/K$14 -> 1 | L74: - | M74: =M14/M$14 -> 1 | N74: =N14/N$14 -> 1 | O74: =O14/O$14 -> 1 | P74: =P14/P$14 -> 1
A75: Impôts et taxes | B75: =B15/B$14 -> 0.36411991 | C75: =C15/C$14 -> 0.38661134 | D75: =D15/D$14 -> 0.45307223 | E75: =E15/E$14 -> 0.59702355 | F75: =F15/F$14 -> 0.65852675 | G75: =G15/G$14 -> 0.68829782 | H75: =H15/H$14 -> 0.70935501 | I75: =I15/I$14 -> 0.7673902 | ... K75: =K15/K$14 -> 0.72997329 | L75: - | M75: =M15/M$14 -> 0.67505111 | N75: =N15/N$14 -> 0.75247986 | O75: =O15/O$14 -> 0.71157723 | P75: =P15/P$14 -> 0.66412251
A76: - Impôts locaux | B76: =B16/B$14 -> 0.34263982 | C76: =C16/C$14 -> 0.32256635 | D76: =D16/D$14 -> 0.34750845 | E76: =E16/E$14 -> 0.50078614 | F76: =F16/F$14 -> 0.56294669 | G76: =G16/G$14 -> 0.55856081 | H76: =H16/H$14 -> 0.58327502 | I76: =I16/I$14 -> 0.64467622 | ... K76: =K16/K$14 -> 0.60418897 | L76: - | M76: =M16/M$14 -> 0.55862673 | N76: =N16/N$14 -> 0.63481189 | O76: =O16/O$14 -> 0.59456621 | P76: =P16/P$14 -> 0.57374603
A77: (dont: fiscalité reversée) | B77: =B17/B$14 -> 0.20250699 | C77: =C17/C$14 -> 0.072063026 | D77: =D17/D$14 -> 0.069553688 | E77: =E17/E$14 -> 0.045836314 | F77: =F17/F$14 -> 0.049622536 | G77: =G17/G$14 -> 0.051494224 | H77: =H17/H$14 -> 0.052361425 | I77: =I17/I$14 -> 0.057539647 | ... K77: =K17/K$14 -> 0.037389262 | L77: - | M77: =M17/M$14 -> 0.051018554 | N77: =N17/N$14 -> 0.04381186 | O77: =O17/O$14 -> 0.047618879 | P77: =P17/P$14 -> 0.11546279
A78: - Autres impôts et taxes | B78: =B18/B$14 -> 0.02148009 | C78: =C18/C$14 -> 0.064044991 | D78: =D18/D$14 -> 0.10556378 | E78: =E18/E$14 -> 0.096237412 | F78: =F18/F$14 -> 0.095580064 | G78: =G18/G$14 -> 0.12973701 | H78: =H18/H$14 -> 0.12607999 | I78: =I18/I$14 -> 0.12271399 | ... K78: =K18/K$14 -> 0.12578432 | L78: - | M78: =M18/M$14 -> 0.11642437 | N78: =N18/N$14 -> 0.11766797 | O78: =O18/O$14 -> 0.11701103 | P78: =P18/P$14 -> 0.090376473
A79: Concours de l'État | B79: =B19/B$14 -> 0.12931126 | C79: =C19/C$14 -> 0.21138109 | D79: =D19/D$14 -> 0.19572555 | E79: =E19/E$14 -> 0.17241138 | F79: =F19/F$14 -> 0.15950172 | G79: =G19/G$14 -> 0.12286908 | H79: =H19/H$14 -> 0.10397415 | I79: =I19/I$14 -> 0.082519233 | ... K79: =K19/K$14 -> 0.080821606 | L79: - | M79: =M19/M$14 -> 0.13039589 | N79: =N19/N$14 -> 0.086535262 | O79: =O19/O$14 -> 0.10970514 | P79: =P19/P$14 -> 0.16606635
A80: - DGF | B80: =B20/B$14 -> 0.099623418 | C80: =C20/C$14 -> 0.13324767 | D80: =D20/D$14 -> 0.14677421 | E80: =E20/E$14 -> 0.14285962 | F80: =F20/F$14 -> 0.1425186 | G80: =G20/G$14 -> 0.10871144 | H80: =H20/H$14 -> 0.088631393 | I80: =I20/I$14 -> 0.072093855 | ... K80: =K20/K$14 -> 0.073584267 | L80: - | M80: =M20/M$14 -> 0.1126022 | N80: =N20/N$14 -> 0.07571831 | O80: =O20/O$14 -> 0.095202648 | P80: =P20/P$14 -> 0.12698561
A81: - Autres dotations | B81: =B21/B$14 -> 0.014231231 | C81: =C21/C$14 -> 0.016735344 | D81: =D21/D$14 -> 0.013011872 | E81: =E21/E$14 -> 0.0027160068 | F81: =F21/F$14 -> 0.0032889037 | G81: =G21/G$14 -> 0.0018475831 | H81: =H21/H$14 -> 0.0017719861 | I81: =I21/I$14 -> 0.0016640703 | ... K81: =K21/K$14 -> 0.0041998778 | L81: - | M81: =M21/M$14 -> 0.0023793807 | N81: =N21/N$14 -> 0.0020325729 | O81: =O21/O$14 -> 0.0022157781 | P81: =P21/P$14 -> 0.0045020344
A82: - Péréquation et compensations fiscales | B82: =B22/B$14 -> 0.015456615 | C82: =C22/C$14 -> 0.061398073 | D82: =D22/D$14 -> 0.03593947 | E82: =E22/E$14 -> 0.026835749 | F82: =F22/F$14 -> 0.01369422 | G82: =G22/G$14 -> 0.012310058 | H82: =H22/H$14 -> 0.013570773 | I82: =I22/I$14 -> 0.0087613085 | ... K82: =K22/K$14 -> 0.0030374612 | L82: - | M82: =M22/M$14 -> 0.015414308 | N82: =N22/N$14 -> 0.0087843797 | O82: =O22/O$14 -> 0.012286715 | P82: =P22/P$14 -> 0.034578704
A83: Subventions reçues et participations | B83: =B23/B$14 -> 0.027840957 | C83: =C23/C$14 -> 0.0063513287 | D83: =D23/D$14 -> 0.049380293 | E83: =E23/E$14 -> 0.024992006 | F83: =F23/F$14 -> 0.025676447 | G83: =G23/G$14 -> 0.029328412 | H83: =H23/H$14 -> 0.037612168 | I83: =I23/I$14 -> 0.025678854 | ... K83: =K23/K$14 -> 0.031318956 | L83: - | M83: =M23/M$14 -> 0.031365449 | N83: =N23/N$14 -> 0.029429674 | O83: =O23/O$14 -> 0.030452269 | P83: =P23/P$14 -> 0.042669357
A84: Ventes de biens et services | B84: =B24/B$14 -> 0.37440726 | C84: =C24/C$14 -> 0.13723455 | D84: =D24/D$14 -> 0.16476508 | E84: =E24/E$14 -> 0.11856155 | F84: =F24/F$14 -> 0.089602737 | G84: =G24/G$14 -> 0.10730869 | H84: =H24/H$14 -> 0.10172944 | I84: =I24/I$14 -> 0.087662976 | ... K84: =K24/K$14 -> 0.12310755 | L84: - | M84: =M24/M$14 -> 0.10383624 | N84: =N24/N$14 -> 0.096651237 | O84: =O24/O$14 -> 0.1004468 | P84: =P24/P$14 -> 0.081465168
A85: Autres recettes de fonctionnement | B85: =B25/B$14 -> 0.10432061 | C85: =C25/C$14 -> 0.2584217 | D85: =D25/D$14 -> 0.13705684 | E85: =E25/E$14 -> 0.087011509 | F85: =F25/F$14 -> 0.066692344 | G85: =G25/G$14 -> 0.052195995 | H85: =H25/H$14 -> 0.047329231 | I85: =I25/I$14 -> 0.036748733 | ... K85: =K25/K$14 -> 0.034778599 | L85: - | M85: =M25/M$14 -> 0.05935131 | N85: =N25/N$14 -> 0.03490397 | O85: =O25/O$14 -> 0.047818557 | P85: =P25/P$14 -> 0.045676617
A86: Structure d'investissement
A87: DÉPENSES D'INVESTISSEMENT hors remboursements | B87: =B28/B$28 -> 1 | C87: =C28/C$28 -> 1 | D87: =D28/D$28 -> 1 | E87: =E28/E$28 -> 1 | F87: =F28/F$28 -> 1 | G87: =G28/G$28 -> 1 | H87: =H28/H$28 -> 1 | I87: =I28/I$28 -> 1 | ... K87: =K28/K$28 -> 1 | L87: - | M87: =M28/M$28 -> 1 | N87: =N28/N$28 -> 1 | O87: =O28/O$28 -> 1 | P87: =P28/P$28 -> 1
A88: Dépenses d'équipement | B88: =B29/B$28 -> 0.9966891 | C88: =C29/C$28 -> 0.99674731 | D88: =D29/D$28 -> 0.93010582 | E88: =E29/E$28 -> 0.95120778 | F88: =F29/F$28 -> 0.91894846 | G88: =G29/G$28 -> 0.89721387 | H88: =H29/H$28 -> 0.91716087 | I88: =I29/I$28 -> 0.91324738 | ... K88: =K29/K$28 -> 0.80211208 | L88: - | M88: =M29/M$28 -> 0.91867747 | N88: =N29/N$28 -> 0.90155141 | O88: =O29/O$28 -> 0.9110602 | P88: =P29/P$28 -> 0.90955037
A89: Subventions d'équipement versées | B89: - | C89: =C30/C$28 -> 0.0013882445 | D89: =D30/D$28 -> 0.016943714 | E89: =E30/E$28 -> 0.02886693 | F89: =F30/F$28 -> 0.054807387 | G89: =G30/G$28 -> 0.06186595 | H89: =H30/H$28 -> 0.049364623 | I89: =I30/I$28 -> 0.050520013 | J89: =J30/J$28 -> 0.061041121 | K89: =K30/K$28 -> 0.11969904 | L89: - | M89: =M30/M$28 -> 0.049621196 | N89: =N30/N$28 -> 0.063157461 | O89: =O30/O$28 -> 0.055641812 | P89: =P30/P$28 -> 0.057863799
A90: Autres depenses d'investissement | B90: =B31/B$28 -> 0.0033108963 | C90: =C31/C$28 -> 0.0018644497 | D90: =D31/D$28 -> 0.052950468 | E90: =E31/E$28 -> 0.019925294 | F90: =F31/F$28 -> 0.026244154 | G90: =G31/G$28 -> 0.040920185 | H90: =H31/H$28 -> 0.03347451 | I90: =I31/I$28 -> 0.036232603 | ... K90: =K31/K$28 -> 0.078188884 | L90: - | M90: =M31/M$28 -> 0.031701331 | N90: =N31/N$28 -> 0.035291127 | O90: =O31/O$28 -> 0.033297989 | P90: =P31/P$28 -> 0.032585829
A91: RECETTES D'INVESTISSEMENT hors emprunts | B91: =B32/B$32 -> 1 | C91: =C32/C$32 -> 1 | D91: =D32/D$32 -> 1 | E91: =E32/E$32 -> 1 | F91: =F32/F$32 -> 1 | G91: =G32/G$32 -> 1 | H91: =H32/H$32 -> 1 | I91: =I32/I$32 -> 1 | ... K91: =K32/K$32 -> 1 | L91: - | M91: =M32/M$32 -> 1 | N91: =N32/N$32 -> 1 | O91: =O32/O$32 -> 1 | P91: =P32/P$32 -> 1
A92: FCTVA | B92: =B33/B$32 -> 0.58991178 | C92: =C33/C$32 -> 0.19352982 | D92: =D33/D$32 -> 0.15247283 | E92: =E33/E$32 -> 0.22989492 | F92: =F33/F$32 -> 0.25069872 | G92: =G33/G$32 -> 0.2414152 | H92: =H33/H$32 -> 0.24634468 | I92: =I33/I$32 -> 0.30461365 | ... K92: =K33/K$32 -> 0.12893785 | L92: - | M92: =M33/M$32 -> 0.2418112 | N92: =N33/N$32 -> 0.24360689 | O92: =O33/O$32 -> 0.24256569 | P92: =P33/P$32 -> 0.24609758
A93: Dotations et Subventions d'équipement | B93: =B34/B$32 -> 0.40084682 | C93: =C34/C$32 -> 0.78838689 | D93: =D34/D$32 -> 0.7892663 | E93: =E34/E$32 -> 0.59765004 | F93: =F34/F$32 -> 0.57199999 | G93: =G34/G$32 -> 0.46149883 | H93: =H34/H$32 -> 0.45897225 | I93: =I34/I$32 -> 0.5500211 | ... K93: =K34/K$32 -> 0.32614034 | L93: - | M93: =M34/M$32 -> 0.51313718 | N93: =N34/N$32 -> 0.44006362 | O93: =O34/O$32 -> 0.48243404 | P93: =P34/P$32 -> 0.56153022
A94: Autres recettes d'investissement | B94: =B35/B$32 -> 0.0092414008 | C94: =C35/C$32 -> 0.01808329 | D94: =D35/D$32 -> 0.058260873 | E94: =E35/E$32 -> 0.17245503 | F94: =F35/F$32 -> 0.17730129 | G94: =G35/G$32 -> 0.29708597 | H94: =H35/H$32 -> 0.29468307 | I94: =I35/I$32 -> 0.14536526 | ... K94: =K35/K$32 -> 0.54492181 | L94: - | M94: =M35/M$32 -> 0.24505162 | N94: =N35/N$32 -> 0.31632949 | O94: =O35/O$32 -> 0.27500027 | P94: =P35/P$32 -> 0.1923722
A95: Ratios
A96: Epargne brute / RRF (Taux d'épargne brute) | B96: 0.27791035 | C96: 0.27843681 | D96: 0.26583073 | E96: 0.22823596 | F96: 0.2162294 | G96: 0.212043 | H96: 0.21101211 | I96: 0.18586681 | J96: 0.16361991 | K96: 0.087778825 | L96: - | M96: 0.2153913 | N96: 0.16197385 | O96: 0.19019223 | P96: 0.14830093
A97: R7 : Dépenses de personnel / DRF | B97: 0.6514054 | C97: 0.4712829 | D97: 0.47332227 | E97: 0.4894191 | F97: 0.5198706 | G97: 0.5457295 | H97: 0.56197572 | I97: 0.58307374 | J97: 0.56786472 | K97: 0.6075978 | L97: - | M97: 0.53875571 | N97: 0.58039822 | O97: 0.55908461 | P97: 0.53555838
A98: R9 : Marge d'autofinancement courant (MAC)=(DRF+Remboursement de dette) / RRF | B98: 0.73617027 | C98: 0.83559825 | D98: 0.82977857 | E98: 0.83179168 | F98: 0.84379823 | G98: 0.85132782 | H98: 0.8525866 | I98: 0.87434991 | J98: 0.91297312 | K98: 1.0106509 | L98: - | M98: 0.84736861 | N98: 0.91088339 | O98: 0.87733098 | P98: 0.91681483
A99: R10 : Dépenses d'équipement brutes (b) / RRF (Taux d'équipement) | B99: 0.43184594 | C99: 0.69787259 | D99: 0.53628138 | E99: 0.43479584 | F99: 0.37473645 | G99: 0.34528922 | H99: 0.3315853 | I99: 0.32135243 | J99: 0.35259766 | K99: 0.21867858 | L99: - | M99: 0.36077171 | N99: 0.31991359 | O99: 0.34149736 | P99: 0.28683294
A100: R11 : Dette / RRF (taux d'endettement) | B100: 0.11044763 | C100: 0.4532194 | D100: 0.60862744 | E100: 0.59085068 | F100: 0.65954742 | G100: 0.60521861 | H100: 0.60499587 | I100: 0.65442083 | J100: 0.79418436 | K100: 1.0722641 | L100: - | M100: 0.61330888 | N100: 0.77565054 | O100: 0.6898917 | P100: 0.69401104
A101: Dette / Epargne brute (Capacité de désendettement, en années) | B101: 0.39742179 | C101: 1.627728 | D101: 2.28953 | E101: 2.5887712 | F101: 3.0502208 | G101: 2.8542258 | H101: 2.8671144 | I101: 3.5209127 | J101: 4.8538368 | K101: 12.215521 | L101: - | M101: 2.8474172 | N101: 4.7887393 | O101: 3.6273391 | P101: 4.6797484
A102: (a) Les communes touristiques concernent uniquement la France métropolitaine.
A103: (b) C'est-à-dire y compris les travaux en régie, les travaux effectués d'office pour le compte de tiers, les opérations di'nvestissement sur établissements d'enseignement et les opérations sous mandat.
A104: Lecture : les achats et charges externes représentent 22,8 % des dépenses de fonctionnement des communes touristiques du littoral maritime de moins de 100 habitants.
A105: Source : DGFiP-Comptes de gestion ; budgets principaux - opérations réelles. Calculs DGCL. Montants calculés hors gestion active de la dette. Strates de population calculées selon la population totale en 2024 du recensement de l'Insee (année de référence 2021).
A107: T 4.2.c - Évolution 2024 / 2023 à champ constant (a) : communes touristiques (b) du littoral maritime (France métropolitaine)
P108: en %
A109: Hors gestion active de la dette | B109: Moins | C109: De 100 | D109: De 200 | E109: De 500 | F109: De 2 000 | G109: De 3 500 | H109: De 5 000 | I109: De 10 000 | J109: De 20 000 | K109: De 50 000 | L109: 100000 | M109: Communes | N109: Communes de | O109: Ensemble | P109: Ensemble des
A110: calculs sur les montants en € courant | B110: de 100 | C110: à moins de | D110: à moins de | E110: à moins de | F110: à moins de | G110: à moins de | H110: à moins de | I110: à moins de | J110: à moins de | K110: à moins de | L110: habitants | M110: de moins | N110: de 10 000 hab. | O110: des | P110: communes en
A111: Evolutions en % | B111: habitants | C111: 200 hab. | D111: 500 hab. | E111: 2 000 hab. | F111: 3 500 hab. | G111: 5 000 hab. | H111: 10 000 hab. | I111: 20 000 hab. | J111: 50 000 hab. | K111: 100 000 hab. | L111: et plus | M111: de 10 000 hab. | N111: et plus | O111: communes | P111: France métropolitaine
A112: Budget de fonctionnement
A113: DÉPENSES DE FONCTIONNEMENT | B113: 5.2206431 | C113: 7.1493485 | D113: 6.3640954 | E113: 5.5627683 | F113: 5.3279862 | G113: 3.7971478 | H113: 5.2432005 | I113: 4.8151872 | J113: 2.9857123 | K113: 4.6938908 | L113: - | M113: 4.9380323 | N113: 3.9991061 | O113: 4.4775617 | P113: 4.1179418
A114: Achats et charges externes | B114: 8.636679 | C114: 12.585934 | D114: 3.4331201 | E114: 7.3993103 | F114: 6.7409688 | G114: 1.9545196 | H114: 6.0369572 | I114: 3.9829713 | J114: 2.8080265 | K114: 2.9176133 | L114: - | M114: 5.3159563 | N114: 3.3188887 | O114: 4.4257851 | P114: 4.0108693
A115: Frais de personnel | B115: 4.5762375 | C115: 5.570516 | D115: 5.7426582 | E115: 6.5365379 | F115: 6.0759195 | G115: 5.4258519 | H115: 5.0190244 | I115: 4.8997776 | J115: 5.738288 | K115: 4.3108981 | L115: - | M115: 5.5166649 | N115: 5.1532741 | O115: 5.3321898 | P115: 4.3575204
A116: Charges financières | B116: -9.5477353 | C116: 3.6644283 | D116: 34.909788 | E116: 13.890734 | F116: 8.8507527 | G116: 4.1815894 | H116: 2.6550988 | I116: 2.7522656 | J116: 16.774694 | K116: 7.4468801 | L116: - | M116: 5.7938462 | N116: 9.6143685 | O116: 7.8006767 | P116: 9.3167024
...

Sheet T 4.3
A1: T 4.3.a - Dépenses et des recettes par «habitant DGF» (a) des communes touristiques (b) «supports de stations de sports d'hiver» par strate de population (c) en 2024 (France métropolitaine)
P3: en € / habitant «DGF»
B4: Moins | C4: De 100 | D4: De 200 | E4: De 500 | F4: De 2 000 | G4: De 3 500 | H4: De 5 000 | I4: De 10 000 | J4: De 20 000 | K4: De 50 000 | L4: 100000 | M4: Communes | N4: Communes | O4: Ensemble | P4: Ensemble des
A5: Hors gestion active de la dette | B5: de 100 | C5: à moins de | D5: à moins de | E5: à moins de | F5: à moins de | G5: à moins de | H5: à moins de | I5: à moins de | J5: à moins de | K5: à moins de | L5: habitants | M5: de moins | N5: de 10 000 hab. | O5: des | P5: communes en
A6: en € / habitant «DGF» | B6: habitants | C6: 200 hab. | D6: 500 hab. | E6: 2 000 hab. | F6: 3 500 hab. | G6: 5 000 hab. | H6: 10 000 hab. | I6: 20 000 hab. | J6: 50 000 hab. | K6: 100 000 hab. | L6: et plus | M6: de 10 000 hab. | N6: et plus | O6: communes | P6: France métropolitaine
A8: DÉPENSES DE FONCTIONNEMENT (1) | B8: 1159.2672 | C8: 1131.1867 | D8: 1219.8739 | E8: 1300.6124 | F8: 1786.9322 | G8: 1288.5497 | H8: 1465.7195 | I8: 1354.7988 | J8: - | K8: - | L8: - | M8: 1393.9987 | N8: 1354.7988 | O8: 1391.1854 | P8: 1132.2924
A9: Achats et charges externes | B9: 472.8341 | C9: 466.47685 | D9: 491.13188 | E9: 455.48117 | F9: 621.19129 | G9: 482.81418 | H9: 438.11377 | I9: 428.30875 | J9: - | K9: - | L9: - | M9: 490.72135 | N9: 428.30875 | O9: 486.24206 | P9: 298.70578
A10: Frais de personnel | B10: 192.31495 | C10: 393.02964 | D10: 366.33654 | E10: 443.95285 | F10: 638.94111 | G10: 463.26048 | H10: 673.92338 | I10: 699.26775 | J10: - | K10: - | L10: - | M10: 498.07773 | N10: 699.26775 | O10: 512.51695 | P10: 606.40868
A11: Charges financières | B11: 9.5150464 | C11: 50.935548 | D11: 29.140408 | E11: 39.797986 | F11: 31.590615 | G11: 26.951091 | H11: 43.692201 | I11: 26.568825 | J11: - | K11: - | L11: - | M11: 36.114103 | N11: 26.568825 | O11: 35.429047 | P11: 23.64555
A12: Dépenses d'intervention | B12: 369.07769 | C12: 141.95737 | D12: 244.89499 | E12: 287.68527 | F12: 420.40044 | G12: 244.2351 | H12: 182.32845 | I12: 122.47213 | J12: - | K12: - | L12: - | M12: 287.77114 | N12: 122.47213 | O12: 275.90779 | P12: 158.3703
A13: Autres dépenses de fonctionnement | B13: 115.52539 | C13: 78.787305 | D13: 88.370049 | E13: 73.695143 | F13: 74.808751 | G13: 71.288885 | H13: 127.66167 | I13: 78.18136 | J13: - | K13: - | L13: - | M13: 81.314398 | N13: 78.18136 | O13: 81.089543 | P13: 45.162082
A14: RECETTES DE FONCTIONNEMENT (2) | B14: 1564.4957 | C14: 1463.2298 | D14: 1584.4028 | E14: 1663.7512 | F14: 2284.7366 | G14: 1733.081 | H14: 1928.9485 | I14: 1673.8233 | J14: - | K14: - | L14: - | M14: 1802.9679 | N14: 1673.8233 | O14: 1793.6993 | P14: 1329.4513
A15: Impôts et taxes | B15: 719.84001 | C15: 783.79348 | D15: 877.15965 | E15: 1040.3388 | F15: 1497.3161 | G15: 1054.2188 | H15: 1319.6866 | I15: 1062.0993 | J15: - | K15: - | L15: - | M15: 1134.4545 | N15: 1062.0993 | O15: 1129.2616 | P15: 882.9185
A16: - Impôts locaux | B16: 514.98305 | C16: 680.36435 | D16: 739.75702 | E16: 856.33802 | F16: 1217.2756 | G16: 798.32164 | H16: 986.42494 | I16: 787.10991 | J16: - | K16: - | L16: - | M16: 912.94082 | N16: 787.10991 | O16: 903.91005 | P16: 762.76738
A17: (dont : fiscalité reversée) | B17: 132.73139 | C17: 47.848534 | D17: 115.39692 | E17: 81.001258 | F17: 104.97341 | G17: 43.988741 | H17: 1.4024784 | I17: 20.119334 | J17: - | K17: - | L17: - | M17: 74.631848 | N17: 20.119334 | O17: 70.719537 | P17: 153.50215
A18: - Autres impôts et taxes | B18: 204.85697 | C18: 103.42913 | D18: 137.40263 | E18: 184.00082 | F18: 280.04046 | G18: 255.8972 | H18: 333.26162 | I18: 274.98942 | J18: - | K18: - | L18: - | M18: 221.51367 | N18: 274.98942 | O18: 225.35158 | P18: 120.15112
A19: Concours de l'État | B19: 370.03586 | C19: 325.64002 | D19: 293.80827 | E19: 244.87305 | F19: 245.97267 | G19: 277.24626 | H19: 219.36345 | I19: 173.01259 | J19: - | K19: - | L19: - | M19: 252.97572 | N19: 173.01259 | O19: 247.23684 | P19: 220.77712
... A45: Dette au 31 décembre (12) | B45: 315.58654 | C45: 1482.6908 | D45: 1105.3973 | E45: 1349.962 | F45: 1305.2285 | G45: 1217.4142 | H45: 1484.9303 | I45: 1176.694 | J45: - | K45: - | L45: - | M45: 1314.4392 | N45: 1176.694 | O45: 1304.5534 | P45: 922.65384
A46: Ratios (voir définitions en annexe 3)
A47: R1 : Dépenses réelles de fonctionnement (DRF) (d) / habitant «DGF» | B47: 1159.2672 | C47: 1131.1867 | D47: 1218.5962 | E47: 1299.0178 | F47: 1784.4143 | G47: 1284.219 | H47: 1462.8355 | I47: 1345.9381 | J47: - | K47: - | L47: - | M47: 1391.8002 | N47: 1345.9381 | O47: 1388.5087 | P47: 1129.889
A48: R2 : Produit des impositions directes hors fiscalité reversée / habitant «DGF» | B48: 415.8368 | C48: 670.11929 | D48: 639.22863 | E48: 803.82824 | F48: 1139.4206 | G48: 771.52584 | H48: 1016.5165 | I48: 802.45801 | J48: - | K48: - | L48: - | M48: 864.2307 | N48: 802.45801 | O48: 859.79733 | P48: 625.13533
A49: R2 bis : Produit des impositions directes y compris fiscalité reversée / habitant «DGF» | B49: 514.98305 | C49: 680.36435 | D49: 739.75702 | E49: 856.33802 | F49: 1217.2756 | G49: 798.32164 | H49: 986.42494 | I49: 787.10991 | J49: - | K49: - | L49: - | M49: 912.94082 | N49: 787.10991 | O49: 903.91005 | P49: 762.76738
A50: R3 : Recettes réelles de fonctionnement (RRF) / habitant «DGF» | B50: 1564.4957 | C50: 1463.2298 | D50: 1584.4028 | E50: 1663.7512 | F50: 2284.7366 | G50: 1733.081 | H50: 1928.9485 | I50: 1673.8233 | J50: - | K50: - | L50: - | M50: 1802.9679 | N50: 1673.8233 | O50: 1793.6993 | P50: 1329.4513
A51: R4 : Dépenses d'équipement brutes (e) / habitant «DGF» | B51: 347.98712 | C51: 435.45264 | D51: 590.74851 | E51: 586.31612 | F51: 757.59959 | G51: 739.20773 | H51: 478.01078 | I51: 603.37932 | J51: - | K51: - | L51: - | M51: 622.12726 | N51: 603.37932 | O51: 620.78174 | P51: 381.33041
A52: R5 : Dette / habitant «DGF» | B52: 315.58654 | C52: 1482.6908 | D52: 1105.3973 | E52: 1349.962 | F52: 1305.2285 | G52: 1217.4142 | H52: 1484.9303 | I52: 1176.694 | J52: - | K52: - | L52: - | M52: 1314.4392 | N52: 1176.694 | O52: 1304.5534 | P52: 922.65384
A53: R6 : DGF / habitant «DGF» | B53: 202.86289 | C53: 210.41522 | D53: 167.57541 | E53: 179.36546 | F53: 145.67628 | G53: 175.00747 | H53: 130.11137 | I53: 85.160935 | J53: - | K53: - | L53: - | M53: 166.60165 | N53: 85.160935 | O53: 160.75673 | P53: 168.82118
A54: (a) Les habitants «DGF» sont comptés selon la population «DGF» en 2024 - année de référence 2021.
A55: (b) Les communes touristiques concernent uniquement la France métropolitaine.
A56: (c) Les strates de population sont calculées avec la population totale recensée par l'Insee en 2024 - année de référence 2021.
A57: (d) Diminuées des travaux en régie.
A58: (e) C'est-à-dire y compris les travaux en régie, les travaux effectués d'office pour le compte de tiers, les opérations di'nvestissement sur établissements d'enseignement et les opérations sous mandat.
A59: Lecture : les achats et charges externes représentent 473 € par «habitant DGF» pour les communes touristiques «supports de stations de sports d'hiver» de moins de 100 habitants.
A60: Source : DGFiP-Comptes de gestion ; budgets principaux - opérations réelles. Calculs DGCL. Montants calculés hors gestion active de la dette.
A62: T 4.3.b - Structure des dépenses et des recettes des communes touristiques (a) «supports de stations de sports d'hiver» par strate de population en 2024 (France métropolitaine)
P63: en %
B64: Moins | C64: De 100 | D64: De 200 | E64: De 500 | F64: De 2 000 | G64: De 3 500 | H64: De 5 000 | I64: De 10 000 | J64: De 20 000 | K64: De 50 000 | L64: 100000 | M64: Communes | N64: Communes | O64: Ensemble | P64: Ensemble des
A65: Hors gestion active de la dette | B65: de 100 | C65: à moins de | D65: à moins de | E65: à moins de | F65: à moins de | G65: à moins de | H65: à moins de | I65: à moins de | J65: à moins de | K65: à moins de | L65: habitants | M65: de moins | N65: de 10 000 hab. | O65: des | P65: communes en
A66: En % | B66: habitants | C66: 200 hab. | D66: 500 hab. | E66: 2 000 hab. | F66: 3 500 hab. | G66: 5 000 hab. | H66: 10 000 hab. | I66: 20 000 hab. | J66: 50 000 hab. | K66: 100 000 hab. | L66: et plus | M66: de 10 000 hab. | N66: et plus | O66: communes | P66: France métropolitaine
A67: Structure de fonctionnement
A68: DÉPENSES DE FONCTIONNEMENT | B68: =B8/B$8 -> 1 | C68: =C8/C$8 -> 1 | D68: =D8/D$8 -> 1 | E68: =E8/E$8 -> 1 | F68: =F8/F$8 -> 1 | G68: =G8/G$8 -> 1 | H68: =H8/H$8 -> 1 | I68: =I8/I$8 -> 1 | J68: - | K68: - | L68: - | M68: =M8/M$8 -> 1 | N68: =N8/N$8 -> 1 | O68: =O8/O$8 -> 1 | P68: =P8/P$8 -> 1
A69: Achats et charges externes | B69: =B9/B$8 -> 0.40787328 | C69: =C9/C$8 -> 0.4123783 | D69: =D9/D$8 -> 0.40260874 | E69: =E9/E$8 -> 0.35020515 | F69: =F9/F$8 -> 0.34763003 | G69: =G9/G$8 -> 0.37469581 | H69: =H9/H$8 -> 0.29890698 | I69: =I9/I$8 -> 0.31614196 | J69: - | K69: - | L69: - | M69: =M9/M$8 -> 0.35202425 | N69: =N9/N$8 -> 0.31614196 | O69: =O9/O$8 -> 0.34951637 | P69: =P9/P$8 -> 0.26380623
A70: Frais de personnel | B70: =B10/B$8 -> 0.16589355 | C70: =C10/C$8 -> 0.34744895 | D70: =D10/D$8 -> 0.3003069 | E70: =E10/E$8 -> 0.34134139 | F70: =F10/F$8 -> 0.35756315 | G70: =G10/G$8 -> 0.35952084 | H70: =H10/H$8 -> 0.45979015 | I70: =I10/I$8 -> 0.5161414 | J70: - | K70: - | L70: - | M70: =M10/M$8 -> 0.35730143 | N70: =N10/N$8 -> 0.5161414 | O70: =O10/O$8 -> 0.36840306 | P70: =P10/P$8 -> 0.53555838
A71: Charges financières | B71: =B11/B$8 -> 0.0082078115 | C71: =C11/C$8 -> 0.045028418 | D71: =D11/D$8 -> 0.023888051 | E71: =E11/E$8 -> 0.03059942 | F71: =F11/F$8 -> 0.017678687 | G71: =G11/G$8 -> 0.020915833 | H71: =H11/H$8 -> 0.029809388 | I71: =I11/I$8 -> 0.019610901 | J71: - | K71: - | L71: - | M71: =M11/M$8 -> 0.025906841 | N71: =N11/N$8 -> 0.019610901 | O71: =O11/O$8 -> 0.025466805 | P71: =P11/P$8 -> 0.020882901
A72: Dépenses d'intervention | B72: =B12/B$8 -> 0.31837155 | C72: =C12/C$8 -> 0.1254942 | D72: =D12/D$8 -> 0.20075436 | E72: =E12/E$8 -> 0.22119216 | F72: =F12/F$8 -> 0.23526379 | G72: =G12/G$8 -> 0.18954262 | H72: =H12/H$8 -> 0.12439519 | I72: =I12/I$8 -> 0.090398756 | J72: - | K72: - | L72: - | M72: =M12/M$8 -> 0.20643573 | N72: =N12/N$8 -> 0.090398756 | O72: =O12/O$8 -> 0.19832568 | P72: =P12/P$8 -> 0.13986697
A73: Autres dépenses de fonctionnement | B73: =B13/B$8 -> 0.09965381 | C73: =C13/C$8 -> 0.069650132 | D73: =D13/D$8 -> 0.072441956 | E73: =E13/E$8 -> 0.056661879 | F73: =F13/F$8 -> 0.041864348 | G73: =G13/G$8 -> 0.0553249 | H73: =H13/H$8 -> 0.087098296 | I73: =I13/I$8 -> 0.057706989 | J73: - | K73: - | L73: - | M73: =M13/M$8 -> 0.058331759 | N73: =N13/N$8 -> 0.057706989 | O73: =O13/O$8 -> 0.058288093 | P73: =P13/P$8 -> 0.039885529
A74: RECETTES DE FONCTIONNEMENT | B74: =B14/B$14 -> 1 | C74: =C14/C$14 -> 1 | D74: =D14/D$14 -> 1 | E74: =E14/E$14 -> 1 | F74: =F14/F$14 -> 1 | G74: =G14/G$14 -> 1 | H74: =H14/H$14 -> 1 | I74: =I14/I$14 -> 1 | J74: - | K74: - | L74: - | M74: =M14/M$14 -> 1 | N74: =N14/N$14 -> 1 | O74: =O14/O$14 -> 1 | P74: =P14/P$14 -> 1
